Workbook

Sheet 🧠 CLAUDE CONTEXT
A1: 🧠 CLAUDE CONTEXT — Mémoire de session · Auto-généré · Ne pas modifier manuellement
A2: Uploader ce fichier à chaque session → Claude lit ce bloc en premier et reprend le contexte complet instantanément
A4: 📋 DERNIÈRE SESSION
A5: Version fichier | B5: v63-S39 | C5: Mis à jour automatiquement par Claude en fin de session
A6: Date session | B6: 13 mars 2026 | C6: HNE · Nunavik
A7: Prochaine session | B7: S36 — xlsx v59 + dashboard v16 + CLAUDE.md + data.json
A9: 📊 ÉTAT PORTFOLIO · 13 MARS 2026
A10: Total CAD | B10: ~$89,674 CAD (XEQT 100u confirmé · data.json 8h55 +$3,993) | C10: ATH: $87,252 · 10 mars 2026
A11: P&L ouvert | B11: +$13,469 CAD estimé · recalcul S36 avec data.json
A12: Coût de base | B12: $76,054.68
A13: TFSA | B13: $68,137 | C13: Dépôts: $51,500 · P&L +34.37%
A14: FHSA | B14: $18,772 CAD · XEQT 115u (100 FHSA + 25 TFSA) · VFV 16u FHSA | C14: XEQT 100u @$39.93 + VFV 16u · Objectif: $40,000
A15: REER | B15: $2,765 | C15: SCHD 64.3053u + JEPI 1u + cash $1.26 CAD
A16: USD/CAD | B16: 1.3702 | C16: Dynamique — fallback config
A17: Positions actives | B17: 40 — TFSA 26 · FHSA 12 · REER 2 | C17: TFSA 26 · FHSA 12 · REER 2
A18: USD exposition | B18: ~62% | C18: ✅ Sous seuil 65%
A20: 🔴 ACTIONS OUVERTES — PRIORITÉ S36
A21: 🔴 URGENT | B21: EQ Bank HISA — ouvrir compte | C21: $0 actuel → cible $15,000 · $1,500/mois automatique
A22: 🔴 URGENT | B22: Bénéficiaires Questrade | C22: TFSA + FHSA + REER sans bénéficiaires · ~$87K non protégé · 5 min
A23: 🔴 URGENT | B23: Automatiser $5,000/mois | C23: Avant 15 avril · REER $2K + FHSA $1K + TFSA $500 + EQ Bank $1.5K
A24: 🟡 IMPORTANT | B24: Post-BdC 18 mars → ZRE+XIC+VDU vers VFV.TO | C24: ~$1,878 à recycler de T4 vers T1 dans TFSA
A25: 🟡 IMPORTANT | B25: FHSA T4 trop élevé → recycler vers VFV.TO | C25: REI+SRU+XIC+XEI FHSA = $4,752 T4 · compte double exonération = max T1
A26: 📅 CALENDRIER | B26: Verdicts J+30 → 11 avril | C26: AVGO · SMH · GEV · SCHD · PLZ.UN · calculer alpha vs VFV.TO
A28: ✅ ACCOMPLI — S34-S35 · 13 MARS 2026
A29: ✅ Trade | B29: Research marché exhaustif mars 2026 complété (macro Iran/Fed/TSX + top 15 actions + 15 ETFs) | C29: TFSA qty=0 confirmé
A30: ✅ Trade | B30: XEQT.TO 100u @$39.93 FHSA exécuté 15:06:55 ET · décision modifiée 50/50 → 100% XEQT suite Research | C30: 13 mars 2026
A31: ✅ Dashboard | B31: portfolio_dashboard_v16.html | C31: Tickers cliquables · tri interactif · graphiques Chart.js jouables · 30 factsheets
A32: ✅ Dashboard | B32: xlsx v63-S39 | C32: Cerveau multi-piliers · CLAUDE CONTEXT · APPRENTISSAGE · CORPS · CULTURE · PROJET DE VIE
A33: ✅ Système | B33: CLAUDE CONTEXT intégré dans xlsx | C33: Onglet auto-généré · 0 upload manuel requis
A35: 🧠 DÉCISIONS & RAISONNEMENTS CLÉS
A36: Plan cotisation | B36: $5,000/mois confirmé S16 | C36: REER $2K + FHSA $1K + TFSA $500 + EQ Bank $1.5K · surplus libre $1,768/mois
A37: Snowball REER | B37: $2K/mois SCHD → ~$1,060 ARC remboursé | C37: 52.98% taux marginal Québec · mécanique clé
A38: FI objectif | B38: $2.1M = plancher · jamais plafond | C38: Liberté & optionalité · pas un chiffre fixe
A39: Maison 2030+ | B39: RAP $60K (REER) + FHSA $40K = $100K mise de fonds | C39: Solo · timeline révisée de 2028 à 2030+
A40: Psychologie | B40: Buy-the-dip T1 = conviction forte | C40: COVID 2020 ancre · -30%+ = ACHETER PLUS · frein = liquidités + timing
A42: ⚠️ RÈGLES ABSOLUES — Claude applique sans exception
A43: 🚫 JAMAIS | B43: Vendre T.TO ou MFC.TO dans TFSA | C43: Room de contribution perdu à jamais si vendu
A44: 🚫 JAMAIS | B44: Recréer le xlsx de zéro | C44: Toujours load_workbook — 2133 formules à préserver
A45: 🚫 JAMAIS | B45: Modifier xlsx sans autorisation explicite de Hey | C45: Demander "go" avant tout code
A46: ✅ TOUJOURS | B46: Vérifier room FHSA avant cotisation | C46: Room 2026 restant: ~$13,700
A47: ✅ TOUJOURS | B47: Vérifier earnings calendar avant achat T1/T2 | C47: No-buy META av. 28 avr · AVGO av. 4 juin · NVDA av. 21 mai
A48: ✅ TOUJOURS | B48: USD expo ≤65% · IA expo ≤45% | C48: Actuellement: USD 44.8% ✅
A50: 📁 FICHIERS À UPLOADER — S22
A51: Fichier 1 | B51: Portefeuille_2026_v52_S22.xlsx | C51: ← CE fichier · cerveau principal
A52: Fichier 2 | B52: portfolio_dashboard_v16.html | C52: Dashboard portfolio · auto-save intégré
A53: Fichier 3 | B53: xlsx v63-S39 | C53: Life OS · auto-save intégré
A54: Message | B54: S22 — [actions faites depuis S21] | C54: Claude reprend le contexte complet instantanément
A56: 🔧 PRIORITÉ TECH S22 — GITHUB
A57: Objectif | B57: GitHub comme source de vérité centrale | C57: Dashboard HTML sur GitHub Pages · fetch pointe vers repo GitHub
A58: Pourquoi | B58: Remplace Apps Script Google Sheets | C58: Plus stable · accessible partout · pas besoin d'uploader à chaque session
A59: État | B59: ⬜ À configurer S22 | C59: Étapes : créer repo → push HTML → GitHub Pages → mettre à jour fetch URL
A61: 🔒 PROTOCOLE FERMETURE SESSION — Règles apprises
A62: Règle 1 | B62: Ne jamais générer CLAUDE CONTEXT avant "c'est bon on ferme" | C62: Les derniers échanges contiennent souvent des infos critiques
A63: Règle 2 | B63: Scanner toute la conversation avant de livrer les fichiers finaux | C63: Capturer tout ce qui n'est pas encore documenté
A64: Règle 3 | B64: Poser la question de fermeture systématiquement | C64: "Il y a quelque chose à intégrer avant qu'on ferme ?"
A65: Erreur S21 | B65: GitHub mentionné → pas intégré dans CLAUDE CONTEXT | C65: Corrigé après rappel · ne plus répéter
A67: ✅ ACCOMPLI — S34-S35 · 13 MARS 2026
A68: ✅ Trade | B68: XEQT.TO 100u @$39.93 — $3,993 CAD — FHSA exécuté 15:06:55 ET
A69: ✅ Analyse | B69: Research marché exhaustif mars 2026 — macro Iran/Fed/TSX + top 15 actions + top 15 ETFs
A70: ✅ Décision | B70: 100% XEQT vs 50/50 — Research confirme XEQT optimal pour profil déjà 62% USD

Sheet ⚙️ MASTER_INDEX
A1: Domaine | Source | Tier | Score | Statut | Lien/Accès
A2: Domaine | B2: Source | C2: Tier | D2: Score | E2: Statut | F2: Lien/Accès | H2: PROCHAIN VERDICT J+30
A3: FINANCE | B3: SEC EDGAR | C3: AAA | D3: 100 | E3: ACTIF | F3: sec.gov
A4: FINANCE | B4: Morningstar | C4: AAA | D4: 95 | E4: ACTIF | F4: morningstar.ca
A5: FINANCE | B5: Koyfin | C5: AAA | D5: 95 | E5: ACTIF | F5: koyfin.com
A6: FINANCE | B6: Bloomberg | C6: AAA | D6: 90 | E6: ACTIF | F6: bloomberg.com
A7: FINANCE | B7: Seeking Alpha | C7: AA | D7: 80 | E7: ACTIF | F7: seekingalpha.com
A8: ENTRAÎNEMENT | B8: Renaissance Periodization | C8: AAA | D8: 100 | E8: ACTIF | F8: renaissanceperiodization.com
A9: ENTRAÎNEMENT | B9: Stronger by Science | C9: AAA | D9: 95 | E9: ACTIF | F9: strongerbyscience.com
A10: ENTRAÎNEMENT | B10: Examine.com | C10: AAA | D10: 100 | E10: ACTIF | F10: examine.com
A11: ENTRAÎNEMENT | B11: PubMed | C11: AAA | D11: 100 | E11: ACTIF | F11: pubmed.ncbi.nlm.nih.gov
A12: ENTRAÎNEMENT | B12: Juggernaut Training | C12: AAA | D12: 90 | E12: ACTIF | F12: jtsstrength.com
A13: PARIS SPORTIFS | B13: KenPom | C13: AAA | D13: 100 | E13: ACTIF | F13: kenpom.com
A14: PARIS SPORTIFS | B14: Pinnacle | C14: AAA | D14: 95 | E14: ACTIF | F14: pinnacle.com
... A46: LIVRES | B46: Paris Review | C46: AAA | D46: 90 | E46: ACTIF | F46: theparisreview.org
A47: LIVRES | B47: Goodreads | C47: AA | D47: 80
A49: Domaine Source Tier Score Densité CORPS Journal of Strength & Cond. Res. AAA 90 Expansion CORPS Alan Aragon Research Review AAA 90 Expansion CORPS MASS (Stronger by Science) AAA 90 Expansion CORPS Examine.com AAA 90 Expansion CORPS Precision Nutrition AAA 90 Expansion CORPS Huberman Lab AA 85 Expansion CORPS Peter Attia (The Drive) AAA 90 Expansion CORPS Renaissance Periodization AAA 90 Expansion CORPS Juggernaut Training Systems AA 85 Expansion CORPS EliteFTS AA 85 Expansion CORPS Starting Strength AA 85 Expansion CORPS BarBend A 80 Expansion CORPS Breaking Muscle A 80 Expansion CORPS FRC (Functional Range Cond.) AA 85 Expansion CORPS BJJ Heroes A 80 Expansion CORPS Grappling Insider A 80 Expansion CORPS Chewjitsu A 80 Expansion CORPS FloGrappling A 80 Expansion CORPS Sleep Foundation AAA 90 Expansion CORPS Sports Medicine Journal AAA 90 Expansion CORPS PubMed AAA 90 Expansion CORPS Yoga Journal A 80 Expansion CORPS Human Kinetics AA 85 Expansion CORPS NSCA Journal AAA 90 Expansion CORPS Science of Sport AA 85 Expansion MAISON Harvard Business Review AAA 90 Expansion MAISON Atomic Habits (James Clear) AA 85 Expansion MAISON Deep Work (Cal Newport) AA 85 Expansion MAISON The Almanack of Naval Ravikant AAA 90 Expansion MAISON BiggerPockets AA 85 Expansion MAISON Canadian Real Estate Wealth AA 85 Expansion MAISON Statistique Canada (Logement) AAA 90 Expansion MAISON RateHub.ca AA 85 Expansion MAISON CMHC (Rapports Marché) AAA 90 Expansion MAISON Better Dwelling AA 85 Expansion MAISON ArchDaily A 80 Expansion MAISON Apartment Therapy A 80 Expansion MAISON House & Home Canada A 80 Expansion MAISON Todoist Productivity Blog A 80 Expansion MAISON Obsidian Forum (PKM) AA 85 Expansion MAISON Notion Academy A 80 Expansion MAISON The Minimalists A 80 Expansion MAISON Wait But Why AA 85 Expansion MAISON Seth Godin (Marketing/Strat) AAA 90 Expansion MAISON Deepstash A 80 Expansion MAISON Lifehacker (Performance) A 80 Expansion MAISON Medium (Productivité) A 80 Expansion MAISON Building a Second Brain (Forte) AA 85 Expansion MAISON Goodreads (Non-Fiction) A 80 Expansion MAISON Fast Company AA 85 Expansion CULTURE Foreign Affairs AAA 95 Expansion CULTURE Longform.org AAA 90 Expansion CULTURE The New Yorker AA 85 Expansion CULTURE Aeon Magazine AA 85 Expansion CULTURE The Atlantic AA 85 Expansion CULTURE The Paris Review AA 85 Expansion CULTURE Hardcore History (Dan Carlin) AAA 90 Expansion CULTURE Smithsonian Magazine AA 85 Expansion CULTURE JSTOR (Archive) AAA 90 Expansion CULTURE The School of Life AA 85 Expansion CULTURE Psychology Today AA 85 Expansion CULTURE Greater Good Science Center AA 85 Expansion CULTURE Criterion Collection (Cinéma) AA 85 Expansion CULTURE Sight & Sound AA 85 Expansion CULTURE MUBI A 80 Expansion CULTURE Letterboxd A 80 Expansion CULTURE Ars Technica AA 85 Expansion CULTURE Polygon (Culture) A 80 Expansion CULTURE Kotaku (Gaming Analysis) A 80 Expansion CULTURE History.com AA 85 Expansion CULTURE Nautilus AA 85 Expansion CULTURE The Marginalian AAA 90 Expansion CULTURE Lapham's Quarterly AA 85 Expansion CULTURE Philosophie Magazine AA 85 Expansion CULTURE The Economist (Culture) AAA 90 Expansion TECH/SYS Stratechery (Ben Thompson) AAA 95 Expansion TECH/SYS SemiAnalysis (Dylan Patel) AAA 95 Expansion TECH/SYS The Information AA 90 Expansion TECH/SYS NVIDIA Investor Relations AAA 95 Expansion TECH/SYS GitHub Documentation AAA 90 Expansion TECH/SYS Claude.ai Changelogs AAA 95 Expansion TECH/SYS Zapier Automation Blog AA 85 Expansion TECH/SYS Make.com Academy AA 85 Expansion TECH/SYS Reddit (r/selfhosted) A 80 Expansion TECH/SYS Reddit (r/automation) A 80 Expansion TECH/SYS TechCrunch AA 85 Expansion TECH/SYS Wired AA 85 Expansion TECH/SYS Stack Overflow AAA 90 Expansion TECH/SYS Google Apps Script Docs AAA 90 Expansion TECH/SYS AlphaSignal AAA 90 Expansion TECH/SYS TLDR Tech AA 85 Expansion TECH/SYS MIT Tech Review AAA 90 Expansion TECH/SYS Hacker News AAA 90 Expansion TECH/SYS Product Hunt A 80 Expansion TECH/SYS Docker Documentation AA 85 Expansion TECH/SYS Python Documentation AAA 90 Expansion TECH/SYS VS Code Docs AA 85 Expansion TECH/SYS Webflow University AA 85 Expansion TECH/SYS Claude.ai API Docs AAA 95
A50: "Note : Ce tableau est la base de mon S&P 200 par domaine. Chaque source est classée par Tier (AAA = Preuve scientifique/institutionnelle). Je demande une mise à jour trimestrielle du 'Score' basé sur la performance réelle de mes décisions."

Sheet 🚀 DÉMARRAGE
A1: 🚀 DÉMARRAGE CLAUDE · Portefeuille FI 2026 · v63-S39 · 13 mars 2026 · Glisser ce fichier → Session démarre automatiquement | B1: 🚀 DÉMARRAGE CLAUDE · Portefeuille FI 2026 · v63-S39 · 13 mars 2026
B2: "Lis du haut vers le bas → web search → ta 1ʳᵉ réponse = les 3 points les plus importants. Zéro question de contexte."
A4: 📊 SNAPSHOT PORTFOLIO · Soir 13 mars 2026 · Source: Questrade confirmé
B5: COMPTE | C5: VALEUR CAD | D5: P&L $ | E5: P&L % | F5: INVESTI | G5: ACTIONS URGENTES
A6: TFSA 📈 | B6: ='📈 PORTEFEUILLE'!C8 -> 67855.03 | C6: 68072.95 | D6: ='📈 PORTEFEUILLE'!G8 -> 0.27599876 | E6: ='📈 PORTEFEUILLE'!E8 -> 48896.466 | F6: VFV.TO $1,000/mois · room $13,700 restant
A7: FHSA 🏠 | B7: ='📈 PORTEFEUILLE'!C9 -> 14767.018 | C7: 18816.32 | D7: ='📈 PORTEFEUILLE'!G9 -> 0.17283197 | E7: ='📈 PORTEFEUILLE'!E9 -> 12199.675 | F7: SCHD ✅ 64.3053u · +$1,060/mois ARC · Prochain: $2,000 le 12 mars
A8: REER ❄️ | B8: ='📈 PORTEFEUILLE'!C10 -> 2764.1683 | C8: 2798.09 | D8: ='📈 PORTEFEUILLE'!G10 -> 0.39485295 | E8: ='📈 PORTEFEUILLE'!E10 -> 1694.3566 | F8: ✅ SCHD $2,000 REER exécuté · 64.3053u @ $30.80
A9: ▼ TOTAL | B9: ='📈 PORTEFEUILLE'!C11 -> 85386.216 | C9: 89687.36 | D9: 16572.89 | E9: 0.1762
A10: 📊 Ref YTD | B10: $74,290 CAD (est. 1 jan 2026) | E10: VFV YTD: -1.57% | G10: Alpha: ⬜ Calculer
A11: 📈 Perf 1 an
A14: 🚨 ACTIONS URGENTES · Coût d'inaction réel chaque jour
B15: # | C15: ACTION | E15: ÉCHÉANCE | F15: STATUT
B16: ✅ FAIT — SCHD $2,000 REER exécuté 12 mars · 64.3053u confirmés | C16: SCHD $2,000 REER → 12 mars 9h30 HNE | E16: +$1,060/mois ARC (52.98%×$2K) | F16: 12 mars AM | G16: ✅ EXÉCUTÉ — 64.3053u confirmé Questrade
B17: 🟡 EN COURS — Ouvrir EQ Bank + virer $1,500 dès prochaine paie cette semaine | C17: 10 mois → $15,000 atteint · AVANT Questrade dès que paie rentre | E17: Risque opérationnel éliminé | F17: ASAP | G17: PAS OUVERT
B18: 🟡3 | C18: ZRE+XIC+VDU TFSA ~$1,878 → T1 | E18: ~$1,878 T4→T1 + exposition IA+ | F18: Post-BdC 18 mars | G18: EN ATTENTE
B20: 📅5 | E20: Calendrier macro + earnings
A22: ⚡ PROTOCOLE SESSION · Dans l'ordre · 10 minutes max · voir Section 11 pour détail
A23: 🔥 1 | B23: Aspects #1+#2 uploadés · #3 taux USD/CAD → CONFIG!B3 · #4 trades faits | E23: CRITIQUE · Section 14 pour guide uploads
A24: 🔥 2 | B24: VALIDATION → ÉTAT GLOBAL = 🟢 · si 🔴 → corriger avant de continuer | E24: 2 min max
A25: 🔥 3 | B25: Snapshot → #5 cash · #6 cotisations YTD · #12 pending session précédente | E25: Confirmer positions + buying power
A26: ⭐ 4 | B26: Dire: #8 intention · #9 trades envisagés · #13 calendrier · #14 dividendes | E26: 3 phrases · voir template Section 11
A27: ⭐ 5 | B27: Claude applique: #7 macro (web search auto) · #11 benchmark · R1→R13 | E27: Automatique · aucune action
A29: 🎯 PLAN D'EXÉCUTION IMMÉDIAT · 3 actions · Chaque jour de retard = argent perdu
A30: 🔴 ACTION #1 — SCHD $2,000 REER · DEMAIN 12 mars · 9h30 HNE pile à l'ouverture
A31: ÉTAPE | B31: Ouvrir Questrade → REER #52924767 → Acheter SCHD
A32: MONTANT | B32: $2,000 CAD ordre → ~$1,475 USD au taux ~1.3559
A33: ORDRE
A34: IMPACT IMMÉDIAT | B34: +$1,060/mois ARC (remboursé en ~6 semaines après déclaration)
A35: COÛT INACTION
A36: APRÈS | B36: MAJ CONFIG!B34 (REER YTD: 0→2000) + noter dans JOURNAL DÉCISIONS
A38: 🔴 ACTION #2 — EQ Bank HISA $15,000 · Cette semaine · ~20 min en ligne
A39: SITE | B39: eqbank.ca → Ouvrir un compte épargne → taux ~4.0% (confirmer live)
A40: VIREMENT
A41: RÔLE | B41: Fonds urgence exclusivement · ne pas investir · ne pas toucher
A42: POURQUOI | B42: Risque opérationnel #1 — si urgence médicale/équipement/voiture = zéro stress
A43: RENDEMENT
A44: APRÈS | B44: MAJ CONFIG!B25 (HISA → $15,000) + mettre à jour ALERTES section fonds urgence
A46: 📅 ACTION #3 — Verdicts J+30 · 11 avril 2026 · Mettre une alarme maintenant
A47: DATE EXACTE | B47: 11 avril 2026 — mettre alarme téléphone MAINTENANT
A48: DURÉE | B48: ~30 min · ouvrir Questrade · noter prix de chaque ticker du 11 mars
A49: FICHIER | B49: Onglet 📓 JOURNAL DÉCISIONS → Section "PRÉPARATION VERDICTS J+30"
A50: BENCHMARK | B50: En même temps: noter valeur portfolio totale → calculer alpha vs VFV.TO
A51: OBJECTIF
A52: CONFIG REF
B54: Objectif FI | C54: $2.1M+ · liberté = optionalité · pas de cible fixe · maximiser
B57: Liquidités | C57: Arrivent mi-mois · pas début de mois · contrainte réelle
A59: 🔍 WEB SEARCH AUTOMATIQUE · Faire AVANT de répondre — analyse partielle = invalide
B60: Macro | C60: S&P 500 · TSX · VIX · news tarifs US/CA · BdC si <7 jours avant annonce
B61: T1 prix | C61: AVGO · SMH · VFV.TO · GEV · GOOG · META · AMZN · ENB.TO · SCHD — live
B63: Dips >5% | C63: T1 ou T2 en dip vs dernière session → opportunité DCA accélérée
B64: Earnings | C64: Calendrier 30 prochains jours · no-buy zone -7j avant earnings T1/T2
A66: ⚙️ RÈGLES AUTOMATIQUES CLAUDE · Sans exception à chaque session
B67: RÈGLE | D67: DESCRIPTION
B68: 😈 Devil's advocate | D68: Contre-argument AVANT toute validation · jamais valider immédiatement
B69: 🔍 Web search | D69: Recherche COMPLÈTE avant toute recommandation · prix live + news + macro
B70: 💱 USD/CAD ≤ 65% | C70: =CONFIG!B47 -> 🔴 SUREXPOSÉ USD — Rééquilibrer
B71: 🤖 IA ≤ 45%
B72: 💰 Coût opportunité | D72: Chiffrer le coût de chaque dollar non optimisé en CAD réel
B75: 🏠 Room FHSA
B76: 📅 Earnings calendar
B78: 🕐 Fuseau HNE
B80: 💾 MAJ 3 fichiers
A81: 📊 CRITÈRES DE CHANGEMENT DE TIER · Objectifs · Pas subjectifs
B85: T2/T3 → T4
B86: T4 → vente | C86: En gain >5% · ET meilleure utilisation du capital identifiée en T1 · ET pas de conséquence fiscale TFSA room
A90: 📚 LEÇONS APPRISES · Auto-learning · Ne jamais répéter la même erreur deux fois
A91: L9 FHSA T4=36% | B91: FHSA contient 36% de T4 (REI+SRU+XIC+XEI) — compte à double exonération doit être maxT1. Recycler vers VFV.TO. ~+$330/an rendement additionnel.
A92: L10 $2.1M nominal | B92: Cible FI $2.1M = dollars nominaux 2043. En pouvoir d'achat 2026 = ~$1.37M. Décision: garder $2.1M comme plancher mais avoir conscience de l'inflation.
A93: L11 Bénéficiaires | B93: 3 comptes Questrade (~$87K) sans bénéficiaires désignés. Action: Questrade → Mon compte → Bénéficiaires. 5 minutes. URGENT.
A94: L12 Pre-commit | B94: SCHD 12 mars (pré-commité) = zéro hésitation. AVGO 11 mars (non pré-commité) = 2 jours hésitation. Solution: décider le soir, exécuter à l'ouverture.
A95: L13 Score santé statique | B95: Score santé /100 dans ALERTES = formules GOOGLEFINANCE qui ne fonctionnent pas en Excel. Solution: valeurs statiques mises à jour manuellement. Actuel: 68/100.
B96: L5 Analyse partielle
A97: 🔄 FLOW S21 — AMÉLIORATIONS APPLIQUÉES · 12 mars 2026
A98: ✅ 1 | B98: 🧠 RAISONNEMENTS | C98: Nouvel onglet — biais documentés, journal psychologique, patterns récurrents, règles PSY
A99: ✅ 2 | B99: 📊 ANALYSE TITRES | C99: 9 T1 scorecardés avec données réelles — VFV/AVBO/SMH/GOOG/AMZN/META/GEV/ENB/SCHD
A100: ✅ 3 | B100: 📈 PROJECTION FI | C100: 4e scénario contributions croissantes ($5K→$7K/mois avec ancienneté)
A101: ✅ 4 | B101: ❄️ FISCAL | C101: Optimisation fiscale 2026 — revenu imposable $100K après REER+FHSA · FTQ 2027 éligible
A102: ✅ 5 | B102: 🚨 ALERTES | C102: Alerte FHSA T4=36% ajoutée · Score santé 68/100 statique
A103: ✅ 6 | B103: 💰 REVENUS | C103: Dividendes reçus YTD 2026 renseignés · ~$173 CAD + ~$47 USD Q1
A104: ✅ 7 | B104: 🚀 DÉMARRAGE | C104: Leçons S20 (L9→L13) ajoutées · Version v63-S39
A105: ✅ 8 | B105: Dashboard v5 | C105: Vue santé par compte · Crash simulator · Verdicts J+30 analytiques · Âge dynamique
B107: "analyse TICKER"
B112: "maison 2030"
A114: 📝 LOG DES SESSIONS · Historique · Mettre à jour fin de chaque session
B118: S5-6 — 13 mars 2026 | C118: REER DÉBLOQUÉ · Profil AGRESSIF confirmé · Maison 2030+ · Philosophie FI clarifiée
A119: S7-S10 | B119: 13 mars 2026 (sessions intensives) | C119: GRANDE ROTATION T4→T1 · 8 trades 11 mars ($18K rédeployés) · PLZ/REI vendus → AVGO/GEV/SMH · BENCHMARK ajouté · VERDICTS J+30 préparés · 5 fixes onglets critiques
A120: S11 | B120: 13 mars 2026 soir | C120: 15 aspects couverts · Guide dump Questrade · Template session V2 · Formule buying power USD · CONFIG ÉTENDUE complète · 17 règles · Score session S10=8.5/10
A121: S12 → | B121: PROCHAINE SESSION | C121: Actions: ① SCHD $2,000 exécuté? ② EQ Bank ouvert? ③ ZRE+XIC+VDU post-BdC 18 mars ④ Verdicts J+30 (11 avr) ⑤ MAJ benchmark YTD
A122: ⚡ SEUILS DÉCLENCHEURS — Conditions objectives avant d'utiliser une commande
B124: "simulation crash"
B125: "analyse macro"
B128: "northstar"
B129: "snowball fiscal"
B131: "rapport session"
B132: "maison 2030"
A141: ⚡ SECTION 11 — PROTOCOLE DÉBUT SESSION · Étapes dans l'ordre
A143: 📋 CHECKLIST UPLOADS & CONTEXTE · 15 aspects pour une session optimale · Cocher avant de commencer
A144: # | B144: ASPECT | C144: TYPE | D144: UPLOAD / ACTION
A145: 1 | H145: ⬜
A146: 2 | B146: Dump Questrade (PDF ou CSV) | C146: 📎 UPLOAD | H146: ⬜
...

Sheet 🧠 PROFIL
B1: 🧠 PROFIL INVESTISSEUR · Source de vérité sur TOI · Mis à jour annuellement
B2: Ce document = la mémoire de qui tu es en tant qu'investisseur. Claude le lit en priorité à chaque session.
B4: 👤 IDENTITÉ FINANCIÈRE
B5: Âge actuel | C5: =CONFIG!B4 | D5: ←auto | E5: ans
B6: Revenu brut annuel | C6: 140000 | D6: ⬜ Confirmer avec T4 2025 | E6: CAD
B7: Revenu NET estimé /mois | C7: 7950 | D7: ← $3,000 × 26 ÷ 12 + $1,450 prime Nunavik · Confirmé S16 | E7: CAD/mois
B8: Dépenses fixes /mois | C8: 1182 | D8: Épicerie $400 + Tél $110 + Voiture $275 + Ass.auto $100 + Ass.moto $80 + Essence $50 + Abo $25 + Loisirs $50 + Voyages $42 + Vêt $50 · MAJ S16 | E8: CAD/mois
B9: Capacité épargne réelle /mois | C9: =C7-C8 -> 6768 | D9: ← Calculé automatiquement | E9: CAD/mois
B10: Contributions investissement | C10: 5000 | D10: REER $2K + FHSA $1K + TFSA $500 + EQ Bank $1,500 · Plan confirmé S16 | E10: CAD/mois
B11: Surplus non investi /mois | C11: =C9-C10 -> 1768 | D11: ← Tampon / extra / imprévus | E11: CAD/mois
B12: Taux marginal QC | C12: =CONFIG!B11 -> 0.5298 | D12: ←auto CONFIG | E12: %
B13: Zone géographique | C13: Nunavik QC | D13: Avantages: logement+bouffe gratuits · Désavantage: isolement, mobilité réduite
B14: Situation couple | C14: En couple | D14: Finances 100% séparées · achat maison solo prévu
B15: Régime retraite employeur | C15: =CONFIG!B30 -> AUCUN | D15: ←auto CONFIG
B17: 🎯 PROFIL DE RISQUE · Réponses honnêtes · Ne pas idéaliser
B18: Tolérance drawdown maximale | C18: -30% à -40% | D18: Basé sur comportement COVID 2020 : achat agressif à -35%. Au-delà de -40% sur portfolio total = zone inconnue. | E18: 🟠 AGRESSIF
B19: Réaction prouvée en crise | C19: ACHAT MASSIF | D19: COVID mars 2020 : positions achetées pendant le crash. Comportement documenté, pas théorique. | E19: ✅ VALIDÉ
B20: Scénario qui te ferait vraiment vendre | C20: ⬜ À documenter | D20: Ex: perte emploi simultanée + drawdown -40% + urgence médicale. Quel est ton vrai point de rupture ? | E20: ⬜ DÉFINIR
B21: Horizon d'investissement réel | C21: 2043 (FI) + 20 ans après | D21: ~17 ans jusqu'à FI potentiel, puis 30+ ans de décaissement. Horizon total = 47 ans. | E21: ✅ LONG TERME
B22: Acceptation volatilité mensuelle | C22: ±$5,000-8,000 CAD | D22: Portfolio $87K × 8% volatilité mensuelle typique ≈ ±$7K. Confortable ? | E22: ⬜ CONFIRMER
B23: Biais comportementaux identifiés | C23: Buy-the-dip fort · FOMO possible sur IA | D23: Forces: discipline achat en crise. Risques: surpondération IA sans discipline de seuil. | E23: ⚠️ SURVEILLER
B24: Score risque objectif (1-10) | C24: 8 | D24: 8/10 = profil agressif orienté croissance. Justifié par horizon 17+ ans et épargne high-rate. | E24: 🔴 AGRESSIF
B26: 🆘 STRESS-TEST · Que se passe-t-il si... · Plan B pour chaque scénario
B27: SCÉNARIO | C27: IMPACT ESTIMÉ | D27: PLAN B ACTIVÉ | E27: SEUIL DÉCLENCHEUR
B28: Perte d'emploi 12 mois | C28: Zéro revenu · dépenses fixes $700/mois seulement · portfolio intact | D28: EQ Bank $15K (7 mois) · stop contributions · vendre ZRE+XIC+VDU T4 si besoin | E28: Chômage confirmé
B29: Marché -30% (ex: récession 2025) | C29: Portfolio $87K → ~$61K · P&L TFSA effacé | D29: ACHAT AGRESSIF T1 · doubler contributions si cash dispo · NE PAS vendre | E29: S&P500 -20% depuis ATH
B30: Marché -40% (ex: 2008-09) | C30: Portfolio $87K → ~$52K · AVGO/SMH/GEV potentiellement -50% | D30: Même plan: acheter · vérifier qu'aucun titre n'est en danger fondamental · tenir | E30: VIX > 40
B31: Invalidité permanente | C31: ✅ Couverture COMPLÈTE employeur · Assurance vie: employeur + privée ✅ | D31: 🔴 Bénéficiaires TFSA/REER/FHSA NON DÉSIGNÉS — ACTION: Questrade → Mon compte → Bénéficiaires | E31: Diagnostic médical
B32: Décès (planification successorale) | C32: TFSA → conjoint/bénéficiaire tax-free · REER → succession imposable | D32: ⬜ DÉFINIR: bénéficiaires TFSA/REER/FHSA · testament à jour | E32: N/A — prévenir maintenant
B33: Taux hypothécaires > 7% en 2030 | C33: Paiement mensuel $400K @7% = $2,798/mois vs $1,222 @4.5% | D33: Revoir décision maison · attendre baisse taux · augmenter mise de fonds | E33: Taux 5 ans > 6%
B35: 📉 INFLATION · $2.1M en 2043 ≠ $2.1M aujourd'hui · Impact réel modélisé
B36: Taux inflation hypothèse | C36: 0.025 | D36: Inflation Canada historique ~2.0-2.5%. BdC cible = 2%.
B37: Années jusqu'à FI (Scénario B) | C37: 21 | D37: 2026 → 2047 (FI 55 ans, confirmé S16)
B38: Objectif FI nominal ($) | C38: =CONFIG!B20 -> 2100000 | D38: ←auto CONFIG
B39: ⚠️ Objectif FI RÉEL ajusté inflation | C39: =C38*(1+C36)^C37 -> 3527121.9 | D39: ← En dollars 2043 pour MÊME pouvoir d'achat qu'aujourd'hui
B40: Écart vs objectif nominal | C40: =C39-C38 -> 1427121.9 | D40: ← Combien il manque par rapport à $2.1M nominal · Ajuster la cible FI en conséquence
B41: Revenu mensuel équivalent en 2043 | C41: =C38*(1+C36)^C37*0.04/12 -> 11757.073 | D41: ← Règle 4% sur objectif ajusté = revenu mensuel réel équivalent à $7K/mois 2026
B43: 💎 PATRIMOINE NET TOTAL · Au-delà du portfolio · Bilan complet
B44: ACTIF | C44: VALEUR CAD | D44: NOTE | E44: LIQUIDITÉ
B45: TFSA | C45: ='📈 PORTEFEUILLE'!L44 -> 67855.03 | D45: ←auto · Investissement long terme | E45: 🔴 Intouchable
B46: FHSA | C46: ='📈 PORTEFEUILLE'!L59 -> 14767.018 | D46: ←auto · Maison 2030 ou retraite | E46: 🟡 Maison 2030
B47: REER | C47: ='📈 PORTEFEUILLE'!L68 -> 2764.1683 | D47: ←auto · RAP + retraite | E47: 🟡 RAP 2030
B48: EQ Bank HISA | C48: =CONFIG!B25 -> 0 | D48: ←auto CONFIG · Fonds urgence | E48: 🟢 Liquide
B49: Voiture (valeur actuelle) | C49: =CONFIG!B22 -> 27000 | D49: ←auto CONFIG · Actif dépréciable | E49: 🟡 Vendre si besoin
B50: Moto (valeur actuelle) | C50: =CONFIG!B23 -> 10000 | D50: ←auto CONFIG · Actif dépréciable | E50: 🟡 Vendre si besoin
B51: Crypto BTC | C51: =CONFIG!B24 -> 300 | D51: ←auto CONFIG · Hors stratégie | E51: 🟢 Liquide
B52: TOTAL ACTIFS | C52: =SUM(B45:B51) -> 0 | D52: ← Patrimoine brut total
B54: 🤖 CONCENTRATION IA · Corrélation & risque sectoriel · Seuil = 45%
B55: Expo IA estimée (auto) | C55: =CONFIG!B31 -> 0.28 | D55: ←auto CONFIG · Calculé depuis ANALYSE TRIABLE col S (expo IA%)
B56: Statut concentration IA | C56: =IF(B55>0.45,"🔴 DÉPASSE 45% — RÉDUIRE",IF(B55>0.35,"🟡 SURVEILLER (35%+)","✅ OK — Sous 35%")) -> 🔴 DÉPASSE 45% — RÉDUIRE
B57: Titres IA haute corrélation | C57: AVGO · SMH · NVDA · QQQM · QTUM · META · GOOG · AMZN · GEV | D57: Si le marché IA corrige -40% (type 2022), ces titres bougent ensemble
B58: Impact scénario crash IA -40% | C58: =CONFIG!B44*-0.4 -> -1083524.7 | D58: ← Perte estimée si tous les actifs USD/IA corrigent -40% ensemble
B60: 📋 RÈGLES PERSONNELLES · Non-négociables · Gravées dans la stratégie
B61: 🔒 JAMAIS vendre | C61: T.TO + MFC.TO en TFSA | D61: Room TFSA perdu définitivement · Les 2 en perte latente → garder
B62: 🎯 FI = liberté | C62: Pas un chiffre fixe | D62: $2.1M = plancher · Maximiser toujours · Pas de cible d'arrêt
B63: 💱 USD max 65% | C63: Seuil absolu | D63: Au-delà → rééquilibrer vers CAD (VFV.TO, XIC, ENB.TO)
B64: 🤖 IA max 45% | C64: Seuil absolu | D64: Corrélation sectorielle = risque concentré · Diversifier
B65: 📅 No-buy 7j avant | C65: Earnings T1/T2 | D65: Volatilité earnings = risque inutile · Acheter après annonce
B66: 🏠 RAP = pré-retraite | C66: REER sert les 2 objectifs | D66: Croître REER pour RAP 2030 ET retraite après remboursement 15 ans
B67: 💰 T4→T1 naturel | C67: Ne pas vendre T4 sauf mieux | D67: Laisser les T4 se diluer · Réinvestir dividendes en T1/T2
B68: 😈 Devil's advocate | C68: Avant chaque validation | D68: Chercher la faille AVANT d'exécuter · Jamais valider immédiatement

Sheet 📓 JOURNAL DÉCISIONS
B1: 📓 JOURNAL DÉCISIONS · Apprentissage continu · Ne jamais répéter la même erreur deux fois
B2: "Chaque décision documentée = Claude apprend. Résultat J+30 obligatoire. Dans 6 mois ce journal = meilleur atout."
A4: 📋 LOG DÉCISIONS · Saisir après chaque transaction ou décision importante
B5: DATE | C5: TICKER | D5: COMPTE | E5: ACTION | F5: MONTANT | G5: PRIX | H5: RATIONALE | I5: RÉSULTAT J+30 | J5: DELTA % | K5: LEÇON | L5: VERDICT
B6: 2026-03-11 | C6: AVGO | D6: TFSA | E6: ACHETÉ | F6: ~$462 | G6: $340.95 | H6: Soir · buying power settle · 1u fractionnel · DCA opportuniste | I6: ⬜ À remplir 11 avr 2026
B7: 2026-03-11 | C7: GEV | D7: TFSA | E7: ACHETÉ | F7: ~$314 | G7: $845.53 | H7: Soir · fractionnel · énergie IA · position stratégique renforcée | I7: ⬜ À remplir 11 avr 2026
B8: 2026-03-11 | C8: SMH | D8: TFSA | E8: ACHETÉ | F8: ~$2,715 | G8: $400.33 | H8: 13h55 · T4→T1 · semi-conducteurs · dip session · +5u | I8: ⬜ À remplir 11 avr 2026
B9: 2026-03-11 | C9: AVGO | D9: TFSA | E9: ACHETÉ | F9: ~$2,772 | G9: $340.65 | H9: 13h34 · T4→T1 · IA chips · redéploiement PLZ.UN · +6u | I9: ⬜ À remplir 11 avr 2026
B10: 2026-03-11 | C10: GEV | D10: TFSA | E10: ACHETÉ | F10: ~$1,144 | G10: $844.18 | H10: 13h37 · T4→T1 · énergie IA infrastructure · +1u | I10: ⬜ À remplir 11 avr 2026
B11: 2026-03-11 | C11: REI.UN.TO | D11: TFSA | E11: VENDU | F11: $6,315 | G11: $19.02 | H11: 13h54 · T4→T1 · REIT résidentiel sous-pression taux élevés | I11: ✅ Capital redéployé SMH | J11: REITs TFSA → dilution naturelle confirmée
B12: 2026-03-11 | C12: PLZ.UN.TO | D12: TFSA | E12: VENDU | F12: $4,094 | G12: $4.26 | H12: 13h33 · T4→T1 · en gain +17% · REIT sous-performant vs T1 | I12: ✅ Capital redéployé AVGO+GEV | J12: Vendre T4 en gain = bon timing
B13: 2026-03-10 | C13: VFV.TO | D13: FHSA | E13: ACHETÉ | F13: ~$2,518 | G13: $157.38 | H13: Premier achat FHSA 2026 · double exonération fiscale · ancre CAD | I13: ⬜ À remplir 10 avr 2026
B14: 2026-03-09 | C14: AVGO | D14: TFSA | E14: ACHETÉ | F14: ~$197 | G14: $345.76 | H14: DCA mensuel fractionnel · T1 · bull case IA confirmé Q1 | I14: ⬜ À remplir 9 avr 2026
A16: ── NOUVELLES DÉCISIONS — AJOUTER ICI ──
B18: 2026-03-11 | C18: SMH ×10u | D18: TFSA | E18: ACHETÉ | F18: ~$5,434 | G18: $400.33-67 | H18: 10u en 2 tranches · diversification dip vs AVGO only | I18: ⬜ J+30 | J18: ⬜ Leçon | K18: ✅ Bon conseil · diversifier | L18: ⬜ Verdict
B19: 2026-03-09 | C19: Grande rotation | D19: TFSA | E19: MULTI | F19: ~$26K | G19: Varié | H19: Liquidation 15+ positions → T1 concentré · SESSION MAJEURE | I19: ⬜ J+30 | J19: ⬜ Leçon | K19: ✅ Rotation validée · excellent | L19: ⬜ Verdict
B20: 2026-03-09 | C20: SCHD ×2 | D20: REER | E20: ACHETÉ | F20: ~$222 USD | G20: $30.88-30.94 | H20: REER débloqué · 2 tranches · snowball ARC | I20: ⬜ J+30 | J20: ⬜ Leçon | K20: ✅ Priorité #1 · parfait | L20: ⬜ Verdict
B21: 2026-03-09
B22: 2026-03-04 | C22: ZLB.TO | D22: TFSA | E22: ACHETÉ | F22: $240 | G22: $59.97 CAD | H22: GTC · +4u Low Vol T3 · stabilité | I22: ⬜ J+30 | J22: ⬜ Leçon | K22: ⬜ À évaluer J+30 | L22: ⬜ Verdict
B23: 2026-03-03 | C23: H.TO | D23: TFSA | E23: ACHETÉ | F23: $407 | G23: $58.08 CAD | H23: GTC · +7u Hydro One T3 · utilités défensif | I23: ⬜ J+30 | J23: ⬜ Leçon | K23: ⬜ À évaluer J+30 | L23: ⬜ Verdict
B24: 2026-02-09 | C24: MFC.TO | D24: TFSA | E24: ACHETÉ | F24: $414 | G24: $51.70 CAD | H24: GTC · +8u Manulife · règle JAMAIS VENDRE active | I24: ⬜ J+30 | J24: ⬜ Leçon | K24: ⬜ À évaluer J+30 | L24: ⬜ Verdict
B25: YYYY-MM-DD | C25: TICKER | D25: CTE | E25: ACHETÉ/VENDU | F25: $ | G25: $ | H25: Pourquoi cette décision? | I25: ⬜ À remplir J+30 | J25: Leçon apprise? | K25: Conseil donné par Claude au moment du trade | L25: ⬜ Bon / Mauvais · pourquoi
B29: 💡 VERDICT J+30 : Remplir "✅ Bon · [raison]" ou "❌ Mauvais · [raison]" · Ce sont les données qui améliorent Claude session après session
A36: 🧠 PATTERNS COMPORTEMENTAUX · Reconnus par Claude · Mis à jour chaque session
B37: ID | C37: PATTERN | E37: DESCRIPTION
B38: P1 | C38: Buy the dip | E38: Achat systématique en correction · COVID playbook · jamais paniquer · AVGO -10% = achète plus
B39: P2 | C39: Timing mi-mois | E39: Liquidités arrivent mi-mois pas début · planifier achats en conséquence · pas de FOMO
B40: P3 | C40: Sessions intensives | E40: Sessions longues et profondes (vacances) vs courtes quotidiennes · adapter profondeur analyse
B41: P4 | C41: Rotation T4→T1 | E41: Rotation T4→T1 quand T4 en gain >5% · ne jamais attendre le top · agir quand gain visible
B42: P5 | C42: Fiscal first | E42: REER avant TFSA si même ticker · 52.98% retour immédiat · règle non négociable
B45: 📅 PRÉPARATION VERDICTS J+30 · À remplir le 11 avril 2026 · Évaluer chaque trade du 11 mars
B46: ⏰ Le 11 avril 2026 — ouvrir ce tableau, regarder prix Questrade de chaque ticker, remplir col I+J+K
B47: TICKER | C47: COMPTE | D47: PRIX ACHAT | E47: QTÉ | F47: DATE TRADE | G47: PRIX J+30 (11 avr) | H47: PERF 30j | I47: VERDICT CLAUDE (bon/mauvais?) | J47: LEÇON | K47: SCORE CLAUDE
B48: PLZ.UN.TO | C48: TFSA | D48: $4.26 CAD | E48: 961u | F48: 2026-03-11 | G48: ⬜ Prix J+30 | H48: VENDU | I48: ✅ Bon — T4 en gain +17% → T1 | J48: ⬜ | K48: —
B49: REI.UN.TO | C49: TFSA | D49: $19.02 CAD | E49: 332u | F49: 2026-03-11 | G49: ⬜ Prix J+30 | H49: VENDU | I49: ✅ Bon — timing pre-BdC ok | J49: ⬜ | K49: —
B50: AVGO | C50: TFSA | D50: $340.65 USD | E50: 6u | F50: 2026-03-11 | G50: ⬜ Prix J+30 | H50: ⬜ | I50: ✅ Probable — T1 IA core | J50: ⬜ | K50: ⬜
B51: GEV | C51: TFSA | D51: $844.18 USD | E51: 1u | F51: 2026-03-11 | G51: ⬜ Prix J+30 | H51: ⬜ | I51: ✅ Probable — énergie IA | J51: ⬜ | K51: ⬜
B52: SMH ×5 | C52: TFSA | D52: $400.33 USD | E52: 5u | F52: 2026-03-11 13h55 | G52: ⬜ Prix J+30 | H52: ⬜ | I52: ✅ Probable — semis dip | J52: ⬜ | K52: ⬜
B53: SMH ×5 | C53: TFSA | D53: $400.67 USD | E53: 5u | F53: 2026-03-11 14h02 | G53: ⬜ Prix J+30 | H53: ⬜ | I53: ✅ Probable — 2e tranche | J53: ⬜ | K53: ⬜
B54: AVGO soir | C54: TFSA | D54: $340.19 USD | E54: ~1u | F54: 2026-03-11 soir | G54: ⬜ Prix J+30 | H54: ⬜ | I54: ⬜ À évaluer — buying power settle | J54: ⬜ | K54: ⬜
B55: GEV soir | C55: TFSA | D55: $843.80 USD | E55: ~0.37u | F55: 2026-03-11 soir | G55: ⬜ Prix J+30 | H55: ⬜ | I55: ⬜ À évaluer — fractionnel soir | J55: ⬜ | K55: ⬜
B57: 💡 PROTOCOLE VERDICT J+30 (11 avril 2026) ① Ouvrir Questrade → noter prix actuel de chaque ticker dans col G ② Calculer PERF 30j = (Prix J+30 − Prix achat) / Prix achat ③ Verdict Claude = "✅ Bon · [raison]" ou "❌ Mauvais · [raison]" ④ Leçon = ce que ça t'apprend sur ta méthode de décision ⑤ Score Claude = si conseil était bon, ça renforce la confiance dans la méthodologie
B60: 🎓 LEÇONS APPRISES · Boucle d'amélioration permanente · Mise à jour après chaque verdict J+30
B61: DATE LEÇON | C61: DÉCISION ORIGINE | D61: CE QUI S'EST PASSÉ | E61: ERREUR / BIAIS | F61: RÈGLE CRÉÉE | G61: STATUT
B62: 2026-03-11 | C62: Achat AVGO/GEV/SMH post-rotation T4→T1 | D62: Bonne décision stratégique. Timing VIX 24.6 = zone d'opportunité. À valider @J+30. | E62: Possible FOMO sur IA — surveiller si concentration >45% | F62: Règle: vérifier expo IA% avant chaque achat T1 supplémentaire | G62: ⏳ Verdict 11 avril 2026
B63: 2026-03-11 | C63: Vente PLZ.UN + REI.UN T4 dilution naturelle | D63: PLZ.UN vendu $4.26 · Coût moy $4.26 → breakeven. REI.UN vendu $19.02. | E63: Aurais-tu pu vendre plus tôt ? PLZ.UN était en stagnation depuis mois. | F63: Règle: T4 REIT → revoir trim si -15% vs coût et dividende <4% | G63: ✅ Décision validée
B64: 2026-03-09 | C64: Nettoyage REER (XEI/ZEQT/XRE → SCHD) | D64: SCHD 64.31u en REER = position snowball centrée. Bonne simplification. | E64: Aucun biais identifié. Décision alignée stratégie. | F64: Règle: REER = SCHD uniquement jusqu'à $60K RAP + JEPI pour revenus | G64: ✅ Décision validée
B65: 2026-03-12 | C65: SYSTÈME | D65: S20 | E65: UPGRADE | F65: ⬜ | G65: ⬜ | H65: S20 — Dashboard v3 + flow symbiose xlsx↔dashboard. Bouton Recharger. Prix live Yahoo Finance. Architecture: xlsx = source unique de vérité.
B66: ⬜ | C66: ⬜ | D66: ⬜ | E66: ⬜ | F66: ⬜ | G66: ⬜
B67: ⬜ | C67: ⬜ | D67: ⬜ | E67: ⬜ | F67: ⬜ | G67: ⬜
B68: ⬜ | C68: ⬜ | D68: ⬜ | E68: ⬜ | F68: ⬜ | G68: ⬜
B69: ⬜ | C69: ⬜ | D69: ⬜ | E69: ⬜ | F69: ⬜ | G69: ⬜
B72: 📐 RÈGLES ÉMERGENTES · Extraites des leçons · Se construisent session par session
B73: R001 | C73: 2026-03-11 | D73: Jamais acheter T1 si expo IA% > 45% sans d'abord calculer le nouveau % | E73: ✅ ACTIVE
B74: R002 | C74: 2026-03-11 | D74: T4 REIT: revoir si dividende <4% ET -15% vs coût moy depuis >6 mois | E74: ✅ ACTIVE
B75: R003 | C75: 2026-03-09 | D75: REER = SCHD exclusivement jusqu'à RAP $60K. Exception: JEPI <5% allocation | E75: ✅ ACTIVE
B76: R004 | C76: ⬜ À créer | D76: Quand alléger T1 ? (ex: si position >30% du portfolio → rééquilibrer) | E76: ⬜ DÉFINIR
B77: R005 | C77: ⬜ À créer | D77: Seuil psychologique personnel : à partir de quel % drawdown tu agis différemment ? | E77: ⬜ DÉFINIR
A79: ── SESSION S16 — 11 mars 2026 ──
A80: 2026-03-11 | B80: BUDGET | C80: CONFIG | D80: MAJ | E80: $5,000/mois | F80: REER $2K+FHSA $1K+TFSA $500+EQ Bank $1,500 | G80: Confirmé S16 | H80: ✅ Exécuté
A81: 2026-03-11 | B81: H.TO | C81: TFSA | D81: TIER CONFIRMÉ | E81: T3 | F81: Hold sans accumulation — P/E 26x, yield 2.3%, mono-régulateur Ontario | G81: Défendu vs pression changement | H81: ✅ T3 maintenu
A82: 2026-03-11 | B82: XIC.TO | C82: TFSA | D82: TIER CONFIRMÉ | E82: T4 | F82: Diluer naturellement — overlap avec VFV.TO, TSX concentré financières/énergie | G82: Défendu vs pression changement | H82: ✅ T4 maintenu
A83: 2026-03-11 | B83: PLAN ANALYSE | C83: TOUS | D83: DÉCISION | E83: S17+ | F83: Grille 8 critères scorecard /10 à créer — analyser chaque titre portfolio | G83: À exécuter S17 | H83: ⏳ PENDING S17
A86: 📅 PROTOCOLE VERDICTS J+30 · Mesurer fiabilité analyses · Gravé S16
A87: 🔔 ALARME TÉLÉPHONE : 11 avril 2026 — Verdict J+30 portefeuille · Ouvrir Questrade + noter prix de chaque ticker T1/T2
A88: OBJECTIF | B88: Mesurer si les analyses de Claude sont fiables dans le temps. Si alpha vs VFV.TO = négatif sur 6 mois → simplifier vers index.
A89: BENCHMARK | B89: VFV.TO au 11 mars 2026 = $164.00 CAD. Au 11 avril → calculer %perf VFV vs portfolio total.
A91: DATE DÉCISION | B91: TICKER | C91: ACTION | D91: PRIX ENTRÉE | E91: RAISONNEMENT | F91: PRIX J+30 | G91: RÉSULTAT % | H91: VFV J+30 | I91: ALPHA | J91: VERDICT | K91: LEÇON
A92: 2026-03-11 | B92: AVGO | C92: 🟢 ACHETÉ | D92: $340.65 USD | E92: T1 core · dip marché · conviction max semi | F92: ⬜ 11 avril | G92: =IF(ISNUMBER(F92),(F92-D92)/D92,"⬜") -> ⬜ | H92: ⬜ 11 avril | I92: =IF(ISNUMBER(G92),G92-H92,"⬜") -> ⬜ | J92: ⬜ OUI/NON | K92: ⬜ À remplir
A93: 2026-03-11 | B93: GEV | C93: 🟢 ACHETÉ | D93: $844.18 USD | E93: T1 énergie propre · croissance forte | F93: ⬜ 11 avril | G93: =IF(ISNUMBER(F93),(F93-D93)/D93,"⬜") -> ⬜ | H93: ⬜ 11 avril | I93: =IF(ISNUMBER(G93),G93-H93,"⬜") -> ⬜ | J93: ⬜ OUI/NON | K93: ⬜ À remplir
A94: 2026-03-11 | B94: SMH | C94: 🟢 ACHETÉ ×2 | D94: $400.50 USD | E94: T1 semis · diversification secteur | F94: ⬜ 11 avril | G94: =IF(ISNUMBER(F94),(F94-D94)/D94,"⬜") -> ⬜ | H94: ⬜ 11 avril | I94: =IF(ISNUMBER(G94),G94-H94,"⬜") -> ⬜ | J94: ⬜ OUI/NON | K94: ⬜ À remplir
A95: 2026-03-12 | B95: SCHD | C95: 🟢 ACHETÉ | D95: $30.88 USD | E95: REER · snowball fiscal $1,060/mois ARC | F95: ⬜ 11 avril | G95: =IF(ISNUMBER(F95),(F95-D95)/D95,"⬜") -> ⬜ | H95: ⬜ 11 avril | I95: =IF(ISNUMBER(G95),G95-H95,"⬜") -> ⬜ | J95: ⬜ OUI/NON | K95: ⬜ À remplir
A96: 2026-03-11 | B96: PLZ.UN.TO | C96: 🔴 VENDU | D96: $4.26 CAD | E96: T4 → T1 · REIT faible rendement → libérer capital | F96: ✅ N/A vendu | G96: =IF(ISNUMBER(F96),(F96-D96)/D96,"⬜") -> ⬜ | H96: ⬜ 11 avril | I96: =IF(ISNUMBER(G96),G96-H96,"⬜") -> ⬜ | J96: ⬜ OUI/NON | K96: ⬜ À remplir
A97: 2026-03-11 | B97: REI.UN.TO | C97: 🔴 VENDU | D97: $19.02 CAD | E97: T4 → T1 · REIT faible rendement → libérer capital | F97: ✅ N/A vendu | G97: =IF(ISNUMBER(F97),(F97-D97)/D97,"⬜") -> ⬜ | H97: ⬜ 11 avril | I97: =IF(ISNUMBER(G97),G97-H97,"⬜") -> ⬜ | J97: ⬜ OUI/NON | K97: ⬜ À remplir
A98: 2026-03-12 | B98: SYSTÈME | C98: 📊 SESSION S21 | D98: — | E98: Analyse complète 80 points (40F+40W) · 10 améliorations xlsx · Dashboard v5 · Onglet RAISONNEMENTS créé · Score santé 68/100 | F98: — | G98: —
A99: 2026-03-12 | B99: FHSA | C99: ⚠️ ALERTE | D99: — | E99: FHSA 36% T4 documenté · $4,752 REI+SRU+XIC+XEI → à recycler vers VFV.TO post-BdC 18 mars | F99: — | G99: —
A100: 2026-03-12 | B100: FTQ | C100: ✅ DÉCOUVERTE | D100: — | E100: Si REER $24K + FHSA $16K → revenu imposable $100K < seuil $129,590 → FTQ 2027 éligible · $4,149 récupérable | F100: — | G100: —
B102: 2026-03-13 | C102: XEQT.TO | D102: 🟢 ACHETÉ | E102: $39.93 CAD | F102: FHSA · 100u · $3,993 · analyse Research marché complet · 15:06:55 ET | G102: ⬜ 13 avril 2026 | H102: =IF(ISNUMBER(F102),(F102-D102)/D102,"⬜") -> ⬜ | I102: ⬜ 13 avril 2026
B103: 2026-03-13 | C103: SYSTÈME | D103: 📊 SESSION S34-S35 | E103: — | F103: Research marché exhaustif · Top 15 actions + 15 ETFs · Décision FHSA $4,015 → 100% XEQT · v58-S35 | G103: — | H103: —
B105: 2026-03-13 | C105: SYSTÈME | D105: 📊 SESSION S36 | E105: — | F105: Audit complet HeyOS · Faille boucle apprentissage identifiée · Sources piliers 2-3-4 ajoutées (211-220) · CLAUDE.md S36 | G105: —
B106: 2026-04-13 | C106: VERDICT J+30 | D106: 🔔 ALARME OBLIGATOIRE | E106: XEQT.TO @$39.93 | F106: Comparer XEQT vs VFV vs S&P 500 pur · Fermer boucle apprentissage · Documenter leçon | G106: ⬜ 13 avril
B107: 2026-04-11 | C107: VERDICT J+30 | D107: 🔔 ALARME OBLIGATOIRE | E107: AVGO·SMH·GEV·SCHD | F107: Calculer alpha vs VFV.TO · Si alpha négatif → réviser conviction · FERMER BOUCLE — pas laisser ⬜ | G107: ⬜ 11 avril
B108: 2026-03-14,AVGO,ÉVALUATION,N/A,Analyse technique et fondamentale S39 (Veille active),Évaluation terminée (No-Buy),0,Rien à signaler,No-Buy Earnings (S39)

Sheet 🧠 RAISONNEMENTS
A1: 🧠 RAISONNEMENTS & PSYCHOLOGIE · Le POURQUOI des décisions · Mémoire comportementale cumulée · S21
A2: 📌 Ce qui compte n'est pas QUOI tu as acheté, mais POURQUOI — et si ce pourquoi était bon. Chaque ligne = une leçon permanente.
A3: ① BIAIS PSYCHOLOGIQUES DOCUMENTÉS · Identifiés en session · Pattern recognition cumulatif
A4: BIAIS | B4: DESCRIPTION | C4: MANIFESTATION RÉELLE | D4: DÉCLENCHEUR | E4: STRATÉGIE CONTRE | F4: STATUT | G4: SESSIONS
A5: Buy-the-dip fort ✅ | B5: Achat agressif pendant corrections | C5: COVID mars 2020 : achat à -35% → retour exceptionnel. 11 mars 2026 : AVGO+SMH+GEV achetés pendant correction -3.4%. | D5: VIX > 20, S&P -5%+ depuis ATH | E5: Ancrer sur historique COVID. Calculer valeur à 10 ans. | F5: ✅ FORCE | G5: S1→S21
A6: Frein pré-achat ⚠️ | B6: Hésitation 1-3 jours avant achat même en conviction max | C6: AVGO 11 mars : 2 jours d'hésitation. Peur d'acheter trop tôt dans la correction. | D6: Incertitude marché en cours | E6: Pre-commit : décider le soir, exécuter à l'ouverture. | F6: ⚠️ ACTIF | G6: S18-S21
A7: FOMO IA possible ⚠️ | B7: Surpondération secteur IA par enthousiasme | C7: Expo IA ~35% coût base. Documenté comme risque toutes les sessions. | D7: Nouvelles IA · perf AVGO/SMH | E7: Règle absolue ≤45%. Calculer expo avant chaque achat T1 IA. | F7: ⚠️ ACTIF | G7: S14→S21
A8: Inaction sur urgences 🔴 | B8: Retarder actions simples malgré documentation répétée | C8: EQ Bank $0 après 4+ sessions. Bénéficiaires non désignés. Automatisation non faite. | D8: Sentiment que c'est moins urgent que les trades | E8: Lier action urgente à prochaine paie. Alarme téléphone. | F8: 🔴 CRITIQUE | G8: S17→S21
A9: Timing parfait ⚠️ | B9: Attendre le meilleur moment au lieu de DCA systématique | C9: Contributions non automatisées → risque timer le marché chaque mois. | D9: Volatilité · incertitude macro | E9: Automatiser le 15 de chaque mois. | F9: ⚠️ ACTIF | G9: S16→S21
A11: ② JOURNAL DES RAISONNEMENTS · Décisions clés avec le POURQUOI réel · Verdict J+30 intégré
A12: DATE | B12: TICKER | C12: ACTION | D12: ÉMOTION | E12: RAISONNEMENT RÉEL | F12: DOUTES AU MOMENT | G12: VERDICT J+30 | H12: LEÇON APPRISE
A13: 2026-03-11 | B13: AVGO | C13: 🟢 ACHETÉ | D13: Conviction + légère hésitation | E13: T1 core IA. Dip -3.4% ATH. VIX 24.6. Broadcom = quasi-monopole switch semis IA. Prix $340.65 = -15% depuis ATH. | F13: Trop tôt dans la correction? Attendre -20%? | G13: ⬜ 11 avril 2026 | H13: Hésitation = frein pré-achat actif. Conviction fondamentale = correcte. Pre-commit aurait éliminé 2 jours d'attente.
A14: 2026-03-11 | B14: SMH ×2 | C14: 🟢 ACHETÉ | D14: Conviction forte | E14: ETF semis = expo T1 sans risque titre unique. NVDA+AVGO+TSM sans concentration. VIX élevé = opportunité. | F14: Double position trop agressif? | G14: ⬜ 11 avril 2026 | H14: Double achat ETF = bon si conviction sectorielle. Moins risqué qu'un titre seul. À refaire en correction.
A15: 2026-03-11 | B15: GEV | C15: 🟢 ACHETÉ | D15: Conviction forte | E15: Infrastructure IA + énergie propre. Croissance >30%/an. Complémentaire AVBO/SMH. Small position = risque contrôlé. | F15: Valorisation élevée? Cyclique? | G15: ⬜ 11 avril 2026 | H15: Position initiée à conviction. Petite taille = entrée prudente. Accumuler si confirmation.
A16: 2026-03-11 | B16: PLZ.UN | C16: 🔴 VENDU | D16: Soulagement rationnel | E16: T4 REIT faible croissance. Libérer capital T1. Décision système, pas émotionnelle. $4,094 recyclés. | F16: Vendre en correction = bon timing? | G16: ✅ Correct | H16: Rotation T4→T1 = décision système pure. Résultat: $4,094 → AVGO+SMH+GEV. À reproduire systématiquement.
A17: 2026-03-12 | B17: SCHD | C17: 🟢 ACHETÉ | D17: Discipline pure — zéro émotion | E17: REER $2,000 → SCHD. Planifié S19. Exécuté 9h30 HNE. Snowball $1,060/mois ARC activé. | F17: Aucun — pré-commité la veille | G17: ✅ Parfait | H17: Pre-commitment = zéro hésitation. Meilleur trade = décidé avant l'ouverture. Modèle à reproduire.
A19: ③ PATTERNS RÉCURRENTS · Ce que les données révèlent sur le style décisionnel
A20: PATTERN | B20: FRÉQUENCE | C20: IMPACT | D20: VERDICT GLOBAL
A21: Buy-the-dip systématique | B21: Chaque correction >3% → achat T1 | C21: Très positif — retours supérieurs au DCA fixe 2020-2026 | D21: ✅ GARDER — C'est l'avantage compétitif principal
A22: Pre-commitment = zéro friction | B22: SCHD 12 mars = zéro hésitation vs AVGO 11 mars = 2 jours | C22: Pré-décider = exécution parfaite sans stress | D22: ✅ SYSTÉMATISER — Décider le soir, exécuter à l'ouverture
A23: Inaction sur non-trades | B23: EQ Bank, automatisation, bénéficiaires = toujours reportés | C23: Risque opérationnel cumulatif élevé | D23: 🔴 PATTERN DANGEREUX — Alarme téléphone = seule solution
A24: Validation Claude = accélérateur | B24: Sessions Claude → décisions plus rapides et plus sûres | C24: Frein pré-achat réduit de 80% | D24: ✅ CONTINUER — Valeur principale des sessions
A26: ④ RÈGLES PSYCHOLOGIQUES PERSONNELLES · Validées par expérience réelle · Gravées S21
A27: CODE | B27: NOM | C27: RÈGLE COMPLÈTE | I27: STATUT
A28: R-PSY-01 | B28: Ancre COVID 2020 | C28: En crise → rappeler : mars 2020, tu as acheté à -35% → retour exceptionnel. Même playbook toujours. | I28: ✅ Actif S1
A29: R-PSY-02 | B29: Pre-commitment obligatoire | C29: Décider le soir QUOI et COMBIEN. Exécuter à l'ouverture sans revoir la décision. | I29: ✅ Actif S20
A30: R-PSY-03 | B30: Émotion = signal, pas décision | C30: Si FOMO → reculer. Si peur → vérifier fondamentaux. Émotion = information, jamais instruction. | I30: ✅ Actif S18
A31: R-PSY-04 | B31: Urgences = alarme téléphone | C31: EQ Bank, bénéficiaires, automatisation → alarme téléphone immédiatement, pas 'tantôt'. | I31: 🔴 À implémenter
A32: R-PSY-05 | B32: Validation externe = accélérateur | C32: Partager le raisonnement avec Claude avant d'exécuter réduit le frein de 80%. | I32: ✅ Actif S16
B33: Infrastructure avant contenu | C33: Récurrent | D33: On construit de beaux outils mais les onglets restent vides | E33: ⚠️ À surveiller — nourrir le cerveau à chaque session
A35: S34 · 13 mars 2026 · DÉCISION FHSA $4,015
A36: CONTEXTE | B36: Marché en correction –4.6% depuis ATH jan 2026. Iran/pétrole. Fed bloquée. Cash FHSA $4,015 disponible.
A37: ANALYSE RÉALISÉE | B37: Top 15 actions Questrade + Top 15 ETFs canadiens analysés. Comparaison 3 options (100% VFV / 50-50 / 100% XEQT).
A38: CONCLUSION ANALYSE | B38: Aucune action individuelle appropriée pour FHSA (risque concentré, compte maison 2030). VFV.TO + XEQT.TO = meilleurs ETFs pour profil.
A39: PLAN RETENU | B39: 100% XEQT.TO · 100 unités @$39.93 · $3,993 CAD
A40: RATIONALE | B40: VFV = continuité + track record. XEQT = comble vide intl. Sharpe XEQT 1.46 > VFV 0.83. USD reste ≤65%. Deux gratuits Questrade.
A41: DEVIL'S ADVOCATE | B41: 100% VFV surperforme long terme (10+ ans) mais concentre encore plus en US dans compte déjà à 62% USD.
A42: VERDICT J+30 | B42: 13 avril 2026 · comparer XEQT.TO vs VFV.TO et vs portefeuille S&P 500 pur
A43: STATUT | B43: ✅ EXÉCUTÉ — 13 mars 2026 · 15:06:55 ET
A45: S36 · 13 mars 2026 · AUDIT SYSTÈME APPRENTISSAGE
A46: FAILLE IDENTIFIÉE | B46: Verdicts J+30 tous ⬜ depuis S16. Cycle incomplet : décision ✅ → document ✅ → verdict ⬜ → leçon ⬜. Sans résultats mesurés, Claude apprend les patterns d'action mais pas la qualité des décisions.
A47: CORRECTION | B47: R-ANA-02 créée. Alarmes téléphone J+30 dans JOURNAL. Verdict = noter prix + calculer alpha vs VFV.TO + écrire 1 leçon.
A48: IMPLICATION | B48: Si alpha vs VFV.TO négatif sur 6 mois cumulés → réviser conviction titres individuels → simplifier vers index. Mesurer pour améliorer.
A50: S36 · ÉQUILIBRE SOURCES INDICE
A51: PROBLÈME | B51: 210 sources indexées → 95% finances. Piliers 2-3-4 = 0 source. Research corps ou immobilier = impossible sans sources fiables.
A52: SOLUTION | B52: 10 sources ajoutées (211-220) : Stronger by Science, Alan Aragon, Jeff Nippard, BJJ Fanatics, Examine.com, Atomic Habits, Morgan Housel, Centris.ca, SCHL, NutritionFacts. Score moyen: 90.
A53: RÈGLE | B53: R-ANA-03 : chaque trimestre, vérifier équilibre sources. Piliers 2-3-4 ≥ 20% indice (cible : 44/220 = 20%).

Sheet 📋 MON PORTEFEUILLE
A1: 📋 MON PORTEFEUILLE · LIVE via formules · Mise à jour auto depuis 📈 PORTEFEUILLE · Trier: cliquer sur les en-têtes ▲▼
A2: ="💰 Total: $"&TEXT('📈 PORTEFEUILLE'!C11,"#,##0")&" CAD" -> 💰 Total: $85,386 CAD | E2: 📈 Gain: +$14,788 (20.6%) | I2: 💵 Div/an: $1,926 CAD | L2: 📊 39 positions · TFSA + FHSA + REER | O2: 🇺🇸 USD: 44.8% 🇨🇦 CAD: 55.2%
A3: 🟢 T1 = Conviction max — Accumuler | E3: 🟡 T2 = Accumuler sélectivement | I3: 🟠 T3 = Garder, ne plus acheter | M3: ⬜ T4 = Diluer naturellement
A4: TICKER ▲▼ | B4: NOM ▲▼ | C4: TYPE ▲▼ | D4: TIER ▲▼ | E4: COMPTE ▲▼ | F4: QTÉ ▲▼ | G4: PRIX ACT ▲▼ | H4: DEV ▲▼ | I4: PRIX CAD ▲▼ | J4: VALEUR CAD ▲▼ | K4: INVESTI CAD ▲▼ | L4: GAIN $CAD ▲▼ | M4: GAIN % ▲▼ | N4: % PORT. ▲▼ | O4: YIELD % ▲▼ | P4: DIV/AN CAD ▲▼ | Q4: DIV/MOIS ▲▼ | R4: SIGNAL ▲▼
A5: ='📈 PORTEFEUILLE'!B15 -> VFV.TO | B5: ='📈 PORTEFEUILLE'!C15 -> Vanguard S&P 500 | C5: ='📈 PORTEFEUILLE'!D15 -> ETF | D5: ='📈 PORTEFEUILLE'!E15 -> T1 | E5: ='📈 PORTEFEUILLE'!F15 -> TFSA | F5: ='📈 PORTEFEUILLE'!G15 -> 84 | G5: ='📈 PORTEFEUILLE'!I15 -> 161.8 | H5: ='📈 PORTEFEUILLE'!K15 -> CAD | I5: ='📈 PORTEFEUILLE'!I15 -> 161.8 | J5: ='📈 PORTEFEUILLE'!L15 -> 13591.2 | K5: =IFERROR('📈 PORTEFEUILLE'!G15*'📈 PORTEFEUILLE'!H15,0) -> 10073.666 | L5: ='📈 PORTEFEUILLE'!N15 -> 3517.5336 | M5: ='📈 PORTEFEUILLE'!O15 -> 0.34918107 | N5: ='📈 PORTEFEUILLE'!P15 -> 0.15917323 | O5: 0.0092 | P5: 126.38371 | Q5: 10.531976 | R5: ='📈 PORTEFEUILLE'!Q15 -> ✅ Accumuler
A6: ='📈 PORTEFEUILLE'!B29 -> TD.TO | B6: ='📈 PORTEFEUILLE'!C29 -> TD Bank | C6: ='📈 PORTEFEUILLE'!D29 -> Action | D6: ='📈 PORTEFEUILLE'!E29 -> T3 | E6: ='📈 PORTEFEUILLE'!F29 -> TFSA | F6: ='📈 PORTEFEUILLE'!G29 -> 87 | G6: ='📈 PORTEFEUILLE'!I29 -> 128.05 | H6: ='📈 PORTEFEUILLE'!K29 -> CAD | I6: ='📈 PORTEFEUILLE'!I29 -> 128.05 | J6: ='📈 PORTEFEUILLE'!L29 -> 11140.35 | K6: =IFERROR('📈 PORTEFEUILLE'!G29*'📈 PORTEFEUILLE'!H29,0) -> 6945.6276 | L6: ='📈 PORTEFEUILLE'!N29 -> 4194.7224 | M6: ='📈 PORTEFEUILLE'!O29 -> 0.60393713 | N6: ='📈 PORTEFEUILLE'!P29 -> 0.13047012 | O6: 0.048 | P6: 544.17456 | Q6: 45.34788 | R6: ='📈 PORTEFEUILLE'!Q29 -> 🔵 Diluer — ne plus acheter
A7: ='📈 PORTEFEUILLE'!B19 -> SMH | B7: ='📈 PORTEFEUILLE'!C19 -> VanEck Semis | C7: ='📈 PORTEFEUILLE'!D19 -> ETF | D7: ='📈 PORTEFEUILLE'!E19 -> T1 | E7: ='📈 PORTEFEUILLE'!F19 -> TFSA | F7: ='📈 PORTEFEUILLE'!G19 -> 19.2266 | G7: ='📈 PORTEFEUILLE'!I19 -> 525.18075 | H7: ='📈 PORTEFEUILLE'!K19 -> USD | I7: ='📈 PORTEFEUILLE'!I19 -> 525.18075 | J7: ='📈 PORTEFEUILLE'!L19 -> 10097.44 | K7: =IFERROR('📈 PORTEFEUILLE'!G19*'📈 PORTEFEUILLE'!H19,0) -> 7566.9226 | L7: ='📈 PORTEFEUILLE'!N19 -> 2530.5176 | M7: ='📈 PORTEFEUILLE'!O19 -> 0.33441832 | N7: ='📈 PORTEFEUILLE'!P19 -> 0.11825609 | O7: 0.007 | P7: 72.596073 | Q7: 6.0496728 | R7: ='📈 PORTEFEUILLE'!Q19 -> ✅ Accumuler
A8: ='📈 PORTEFEUILLE'!B17 -> AVGO | B8: ='📈 PORTEFEUILLE'!C17 -> Broadcom | C8: ='📈 PORTEFEUILLE'!D17 -> Action | D8: ='📈 PORTEFEUILLE'!E17 -> T1 | E8: ='📈 PORTEFEUILLE'!F17 -> TFSA | F8: ='📈 PORTEFEUILLE'!G17 -> 16.5743 | G8: ='📈 PORTEFEUILLE'!I17 -> 436.81674 | H8: ='📈 PORTEFEUILLE'!K17 -> USD | I8: ='📈 PORTEFEUILLE'!I17 -> 436.81674 | J8: ='📈 PORTEFEUILLE'!L17 -> 7239.9318 | K8: =IFERROR('📈 PORTEFEUILLE'!G17*'📈 PORTEFEUILLE'!H17,0) -> 5671.0509 | L8: ='📈 PORTEFEUILLE'!N17 -> 1568.8809 | M8: ='📈 PORTEFEUILLE'!O17 -> 0.27664729 | N8: ='📈 PORTEFEUILLE'!P17 -> 0.084790404 | O8: 0.012 | P8: 91.446739 | Q8: 7.6205616 | R8: ='📈 PORTEFEUILLE'!Q17 -> ✅ Accumuler
A9: ='📈 PORTEFEUILLE'!B22 -> GEV | B9: ='📈 PORTEFEUILLE'!C22 -> GE Vernova | C9: ='📈 PORTEFEUILLE'!D22 -> Action | D9: ='📈 PORTEFEUILLE'!E22 -> T1 | E9: ='📈 PORTEFEUILLE'!F22 -> TFSA | F9: ='📈 PORTEFEUILLE'!G22 -> 2.4431 | G9: ='📈 PORTEFEUILLE'!I22 -> 1091.5266 | H9: ='📈 PORTEFEUILLE'!K22 -> USD | I9: ='📈 PORTEFEUILLE'!I22 -> 1091.5266 | J9: ='📈 PORTEFEUILLE'!L22 -> 2666.7087 | K9: =IFERROR('📈 PORTEFEUILLE'!G22*'📈 PORTEFEUILLE'!H22,0) -> 2032.6365 | L9: ='📈 PORTEFEUILLE'!N22 -> 634.0722 | M9: ='📈 PORTEFEUILLE'!O22 -> 0.3119457 | N9: ='📈 PORTEFEUILLE'!P22 -> 0.031231138 | O9: 0.003 | P9: 8.3536708 | Q9: 0.69613923 | R9: ='📈 PORTEFEUILLE'!Q22 -> ✅ Accumuler
A10: ='📈 PORTEFEUILLE'!B62 -> SCHD | B10: ='📈 PORTEFEUILLE'!C62 -> Schwab US Div | C10: ='📈 PORTEFEUILLE'!D62 -> ETF | D10: ='📈 PORTEFEUILLE'!E62 -> T1 | E10: ='📈 PORTEFEUILLE'!F62 -> REER | F10: ='📈 PORTEFEUILLE'!G62 -> 64.3053 | G10: ='📈 PORTEFEUILLE'!I62 -> 41.76172 | H10: ='📈 PORTEFEUILLE'!K62 -> USD | I10: ='📈 PORTEFEUILLE'!I62 -> 41.76172 | J10: ='📈 PORTEFEUILLE'!L62 -> 2685.4999 | K10: =IFERROR('📈 PORTEFEUILLE'!G62*'📈 PORTEFEUILLE'!H62,0) -> 1639.8366 | L10: ='📈 PORTEFEUILLE'!N62 -> 1045.6633 | M10: ='📈 PORTEFEUILLE'!O62 -> 0 | N10: ='📈 PORTEFEUILLE'!P62 -> 0 | O10: 0.035 | P10: 94.436704 | Q10: 7.8697254 | R10: ='📈 PORTEFEUILLE'!Q62 -> ✅ REER débloqué · accumuler $2,000/mois · snowball ARC +$1,060
A11: ='📈 PORTEFEUILLE'!B47 -> VFV.TO | B11: ='📈 PORTEFEUILLE'!C47 -> Vanguard S&P 500 | C11: ='📈 PORTEFEUILLE'!D47 -> ETF | D11: ='📈 PORTEFEUILLE'!E47 -> T1 | E11: ='📈 PORTEFEUILLE'!F47 -> FHSA | F11: ='📈 PORTEFEUILLE'!G47 -> 16 | G11: ='📈 PORTEFEUILLE'!I47 -> 161.8 | H11: ='📈 PORTEFEUILLE'!K47 -> CAD | I11: ='📈 PORTEFEUILLE'!I47 -> 161.8 | J11: ='📈 PORTEFEUILLE'!L47 -> 2588.8 | K11: =IFERROR('📈 PORTEFEUILLE'!G47*'📈 PORTEFEUILLE'!H47,0) -> 2518.0992 | L11: ='📈 PORTEFEUILLE'!N47 -> 70.7008 | M11: ='📈 PORTEFEUILLE'!O47 -> 0 | N11: ='📈 PORTEFEUILLE'!P47 -> 0 | O11: 0.0092 | P11: 24.073088 | Q11: 2.0060907 | R11: ='📈 PORTEFEUILLE'!Q47 -> ✅ Achat auto $2,500/mois
A12: ='📈 PORTEFEUILLE'!B16 -> GOOG | B12: ='📈 PORTEFEUILLE'!C16 -> Alphabet | C12: ='📈 PORTEFEUILLE'!D16 -> Action | D12: ='📈 PORTEFEUILLE'!E16 -> T1 | E12: ='📈 PORTEFEUILLE'!F16 -> TFSA | F12: ='📈 PORTEFEUILLE'!G16 -> 6 | G12: ='📈 PORTEFEUILLE'!I16 -> 408.74961 | H12: ='📈 PORTEFEUILLE'!K16 -> USD | I12: ='📈 PORTEFEUILLE'!I16 -> 408.74961 | J12: ='📈 PORTEFEUILLE'!L16 -> 2452.4977 | K12: =IFERROR('📈 PORTEFEUILLE'!G16*'📈 PORTEFEUILLE'!H16,0) -> 543.6354 | L12: ='📈 PORTEFEUILLE'!N16 -> 1908.8623 | M12: ='📈 PORTEFEUILLE'!O16 -> 3.5112914 | N12: ='📈 PORTEFEUILLE'!P16 -> 0.028722407 | O12: 0.005 | P12: 12.462868 | Q12: 1.0385724 | R12: ='📈 PORTEFEUILLE'!Q16 -> ✅ Accumuler
A13: ='📈 PORTEFEUILLE'!B30 -> ZLB.TO | B13: ='📈 PORTEFEUILLE'!C30 -> BMO Low Vol | C13: ='📈 PORTEFEUILLE'!D30 -> ETF | D13: ='📈 PORTEFEUILLE'!E30 -> T3 | E13: ='📈 PORTEFEUILLE'!F30 -> TFSA | F13: ='📈 PORTEFEUILLE'!G30 -> 37 | G13: ='📈 PORTEFEUILLE'!I30 -> 59.04 | H13: ='📈 PORTEFEUILLE'!K30 -> CAD | I13: ='📈 PORTEFEUILLE'!I30 -> 59.04 | J13: ='📈 PORTEFEUILLE'!L30 -> 2184.48 | K13: =IFERROR('📈 PORTEFEUILLE'!G30*'📈 PORTEFEUILLE'!H30,0) -> 2151.2392 | L13: ='📈 PORTEFEUILLE'!N30 -> 33.2408 | M13: ='📈 PORTEFEUILLE'!O30 -> 0.015451931 | N13: ='📈 PORTEFEUILLE'!P30 -> 0.02558352 | O13: 0.024 | P13: 52.40088 | Q13: 4.36674 | R13: ='📈 PORTEFEUILLE'!Q30 -> 🔵 Garder
A14: ='📈 PORTEFEUILLE'!B18 -> AMZN | B14: ='📈 PORTEFEUILLE'!C18 -> Amazon | C14: ='📈 PORTEFEUILLE'!D18 -> Action | D14: ='📈 PORTEFEUILLE'!E18 -> T1 | E14: ='📈 PORTEFEUILLE'!F18 -> TFSA | F14: ='📈 PORTEFEUILLE'!G18 -> 7.4817 | G14: ='📈 PORTEFEUILLE'!I18 -> 281.57975 | H14: ='📈 PORTEFEUILLE'!K18 -> USD | I14: ='📈 PORTEFEUILLE'!I18 -> 281.57975 | J14: ='📈 PORTEFEUILLE'!L18 -> 2106.6952 | K14: =IFERROR('📈 PORTEFEUILLE'!G18*'📈 PORTEFEUILLE'!H18,0) -> 850.95135 | L14: ='📈 PORTEFEUILLE'!N18 -> 1255.7439 | M14: ='📈 PORTEFEUILLE'!O18 -> 1.4756941 | N14: ='📈 PORTEFEUILLE'!P18 -> 0.024672545 | O14: 0 | P14: 0 | Q14: 0 | R14: ='📈 PORTEFEUILLE'!Q18 -> ✅ Accumuler
A15: ='📈 PORTEFEUILLE'!B48 -> AMZN | B15: ='📈 PORTEFEUILLE'!C48 -> Amazon | C15: ='📈 PORTEFEUILLE'!D48 -> Action | D15: ='📈 PORTEFEUILLE'!E48 -> T1 | E15: ='📈 PORTEFEUILLE'!F48 -> FHSA | F15: ='📈 PORTEFEUILLE'!G48 -> 7 | G15: ='📈 PORTEFEUILLE'!I48 -> 281.57975 | H15: ='📈 PORTEFEUILLE'!K48 -> USD | I15: ='📈 PORTEFEUILLE'!I48 -> 281.57975 | J15: ='📈 PORTEFEUILLE'!L48 -> 1971.0583 | K15: =IFERROR('📈 PORTEFEUILLE'!G48*'📈 PORTEFEUILLE'!H48,0) -> 1084.5926 | L15: ='📈 PORTEFEUILLE'!N48 -> 886.46567 | M15: ='📈 PORTEFEUILLE'!O48 -> 0.028077051 | N15: ='📈 PORTEFEUILLE'!P48 -> 0.030318711 | O15: 0 | P15: 0 | Q15: 0 | R15: ='📈 PORTEFEUILLE'!Q48 -> ✅ Garder
A16: ='📈 PORTEFEUILLE'!B51 -> TD.TO | B16: ='📈 PORTEFEUILLE'!C51 -> TD Bank | C16: ='📈 PORTEFEUILLE'!D51 -> Action | D16: ='📈 PORTEFEUILLE'!E51 -> T3 | E16: ='📈 PORTEFEUILLE'!F51 -> FHSA | F16: ='📈 PORTEFEUILLE'!G51 -> 15 | G16: ='📈 PORTEFEUILLE'!I51 -> 128.05 | H16: ='📈 PORTEFEUILLE'!K51 -> CAD | I16: ='📈 PORTEFEUILLE'!I51 -> 128.05 | J16: ='📈 PORTEFEUILLE'!L51 -> 1920.75 | K16: =IFERROR('📈 PORTEFEUILLE'!G51*'📈 PORTEFEUILLE'!H51,0) -> 1234.35 | L16: ='📈 PORTEFEUILLE'!N51 -> 686.4 | M16: ='📈 PORTEFEUILLE'!O51 -> -0.0052421368 | N16: ='📈 PORTEFEUILLE'!P51 -> 0.0070005444 | O16: 0.048 | P16: 93.8232 | Q16: 7.8186 | R16: ='📈 PORTEFEUILLE'!Q51 -> 🔵 Garder
A17: ='📈 PORTEFEUILLE'!B37 -> XEI.TO | B17: ='📈 PORTEFEUILLE'!C37 -> iShares High Div | C17: ='📈 PORTEFEUILLE'!D37 -> ETF | D17: ='📈 PORTEFEUILLE'!E37 -> T4 | E17: ='📈 PORTEFEUILLE'!F37 -> TFSA | F17: ='📈 PORTEFEUILLE'!G37 -> 51 | G17: ='📈 PORTEFEUILLE'!I37 -> 35.89 | H17: ='📈 PORTEFEUILLE'!K37 -> CAD | I17: ='📈 PORTEFEUILLE'!I37 -> 35.89 | J17: ='📈 PORTEFEUILLE'!L37 -> 1830.39 | K17: =IFERROR('📈 PORTEFEUILLE'!G37*'📈 PORTEFEUILLE'!H37,0) -> 1564.7361 | L17: ='📈 PORTEFEUILLE'!N37 -> 265.6539 | M17: ='📈 PORTEFEUILLE'!O37 -> 0.16977553 | N17: ='📈 PORTEFEUILLE'!P37 -> 0.021436598 | O17: 0.055 | P17: 100.1385 | Q17: 8.344875 | R17: ='📈 PORTEFEUILLE'!Q37 -> 🔄 Diluer
A18: ='📈 PORTEFEUILLE'!B49 -> QQQM | B18: ='📈 PORTEFEUILLE'!C49 -> Invesco Nasdaq100 | C18: ='📈 PORTEFEUILLE'!D49 -> ETF | D18: ='📈 PORTEFEUILLE'!E49 -> T2 | E18: ='📈 PORTEFEUILLE'!F49 -> FHSA | F18: ='📈 PORTEFEUILLE'!G49 -> 5.311 | G18: ='📈 PORTEFEUILLE'!I49 -> 331.44975 | H18: ='📈 PORTEFEUILLE'!K49 -> USD | I18: ='📈 PORTEFEUILLE'!I49 -> 331.44975 | J18: ='📈 PORTEFEUILLE'!L49 -> 1760.3296 | K18: =IFERROR('📈 PORTEFEUILLE'!G49*'📈 PORTEFEUILLE'!H49,0) -> 1313.9754 | L18: ='📈 PORTEFEUILLE'!N49 -> 446.35426 | M18: ='📈 PORTEFEUILLE'!O49 -> 0.81732594 | N18: ='📈 PORTEFEUILLE'!P49 -> 0.023084033 | O18: 0.006 | P18: 10.750288 | Q18: 0.89585737 | R18: ='📈 PORTEFEUILLE'!Q49 -> ✅ Migration ZQQ ✅
A19: ='📈 PORTEFEUILLE'!B54 -> SRU.UN.TO | B19: ='📈 PORTEFEUILLE'!C54 -> SmartCentres | C19: ='📈 PORTEFEUILLE'!D54 -> REIT | D19: ='📈 PORTEFEUILLE'!E54 -> T4 | E19: ='📈 PORTEFEUILLE'!F54 -> FHSA | F19: ='📈 PORTEFEUILLE'!G54 -> 63 | G19: ='📈 PORTEFEUILLE'!I54 -> 26.84 | H19: ='📈 PORTEFEUILLE'!K54 -> CAD | I19: ='📈 PORTEFEUILLE'!I54 -> 26.84 | J19: ='📈 PORTEFEUILLE'!L54 -> 1690.92 | K19: =IFERROR('📈 PORTEFEUILLE'!G54*'📈 PORTEFEUILLE'!H54,0) -> 1487.43 | L19: ='📈 PORTEFEUILLE'!N54 -> 203.49 | M19: ='📈 PORTEFEUILLE'!O54 -> -0.00045033911 | N19: ='📈 PORTEFEUILLE'!P54 -> 0.0020743395 | O19: 0.072 | P19: 121.338 | Q19: 10.1115 | R19: ='📈 PORTEFEUILLE'!Q54 -> 🔄 Diluer
A20: ='📈 PORTEFEUILLE'!B55 -> REI.UN.TO | B20: ='📈 PORTEFEUILLE'!C55 -> RioCan REIT | C20: ='📈 PORTEFEUILLE'!D55 -> REIT | D20: ='📈 PORTEFEUILLE'!E55 -> T4 | E20: ='📈 PORTEFEUILLE'!F55 -> FHSA | F20: ='📈 PORTEFEUILLE'!G55 -> 80 | G20: ='📈 PORTEFEUILLE'!I55 -> 19.02 | H20: ='📈 PORTEFEUILLE'!K55 -> CAD | I20: ='📈 PORTEFEUILLE'!I55 -> 19.02 | J20: ='📈 PORTEFEUILLE'!L55 -> 1521.6 | K20: =IFERROR('📈 PORTEFEUILLE'!G55*'📈 PORTEFEUILLE'!H55,0) -> 1498.4 | L20: ='📈 PORTEFEUILLE'!N55 -> 23.2 | M20: ='📈 PORTEFEUILLE'!O55 -> 0.13680644 | N20: ='📈 PORTEFEUILLE'!P55 -> 0.019803196 | O20: 0.056 | P20: 85.5232 | Q20: 7.1269333 | R20: ='📈 PORTEFEUILLE'!Q55 -> 🔄 Diluer
A21: ='📈 PORTEFEUILLE'!B38 -> SRU.UN.TO | B21: ='📈 PORTEFEUILLE'!C38 -> SmartCentres | C21: ='📈 PORTEFEUILLE'!D38 -> REIT | D21: ='📈 PORTEFEUILLE'!E38 -> T4 | E21: ='📈 PORTEFEUILLE'!F38 -> TFSA | F21: ='📈 PORTEFEUILLE'!G38 -> 57 | G21: ='📈 PORTEFEUILLE'!I38 -> 26.84 | H21: ='📈 PORTEFEUILLE'!K38 -> CAD | I21: ='📈 PORTEFEUILLE'!I38 -> 26.84 | J21: ='📈 PORTEFEUILLE'!L38 -> 1529.88 | K21: =IFERROR('📈 PORTEFEUILLE'!G38*'📈 PORTEFEUILLE'!H38,0) -> 1439.4951 | L21: ='📈 PORTEFEUILLE'!N38 -> 90.3849 | M21: ='📈 PORTEFEUILLE'!O38 -> 0.062789307 | N21: ='📈 PORTEFEUILLE'!P38 -> 0.017917178 | O21: 0.072 | P21: 109.782 | Q21: 9.1485 | R21: ='📈 PORTEFEUILLE'!Q38 -> 🔄 Diluer
A22: ='📈 PORTEFEUILLE'!B26 -> QQQM | B22: ='📈 PORTEFEUILLE'!C26 -> Invesco Nasdaq100 | C22: ='📈 PORTEFEUILLE'!D26 -> ETF | D22: ='📈 PORTEFEUILLE'!E26 -> T2 | E22: ='📈 PORTEFEUILLE'!F26 -> TFSA | F22: ='📈 PORTEFEUILLE'!G26 -> 4.4515 | G22: ='📈 PORTEFEUILLE'!I26 -> 331.44975 | H22: ='📈 PORTEFEUILLE'!K26 -> USD | I22: ='📈 PORTEFEUILLE'!I26 -> 331.44975 | J22: ='📈 PORTEFEUILLE'!L26 -> 1475.4486 | K22: =IFERROR('📈 PORTEFEUILLE'!G26*'📈 PORTEFEUILLE'!H26,0) -> 1099.9959 | L22: ='📈 PORTEFEUILLE'!N26 -> 375.45266 | M22: ='📈 PORTEFEUILLE'!O26 -> 0.34132187 | N22: ='📈 PORTEFEUILLE'!P26 -> 0.017279704 | O22: 0.006 | P22: 9.010527 | Q22: 0.75087725 | R22: ='📈 PORTEFEUILLE'!Q26 -> ✅ Migration ZQQ ✅
A23: ='📈 PORTEFEUILLE'!B31 -> H.TO | B23: ='📈 PORTEFEUILLE'!C31 -> Hydro One | C23: ='📈 PORTEFEUILLE'!D31 -> Action | D23: ='📈 PORTEFEUILLE'!E31 -> T3 | E23: ='📈 PORTEFEUILLE'!F31 -> TFSA | F23: ='📈 PORTEFEUILLE'!G31 -> 22 | G23: ='📈 PORTEFEUILLE'!I31 -> 60.09 | H23: ='📈 PORTEFEUILLE'!K31 -> CAD | I23: ='📈 PORTEFEUILLE'!I31 -> 60.09 | J23: ='📈 PORTEFEUILLE'!L31 -> 1321.98 | K23: =IFERROR('📈 PORTEFEUILLE'!G31*'📈 PORTEFEUILLE'!H31,0) -> 1163.0586 | L23: ='📈 PORTEFEUILLE'!N31 -> 158.9214 | M23: ='📈 PORTEFEUILLE'!O31 -> 0.13664092 | N23: ='📈 PORTEFEUILLE'!P31 -> 0.015482358 | O23: 0.03 | P23: 38.7222 | Q23: 3.22685 | R23: ='📈 PORTEFEUILLE'!Q31 -> 🔵 Garder
A24: ='📈 PORTEFEUILLE'!B39 -> XIC.TO | B24: ='📈 PORTEFEUILLE'!C39 -> iShares TSX | C24: ='📈 PORTEFEUILLE'!D39 -> ETF | D24: ='📈 PORTEFEUILLE'!E39 -> T4 | E24: ='📈 PORTEFEUILLE'!F39 -> TFSA | F24: ='📈 PORTEFEUILLE'!G39 -> 21 | G24: ='📈 PORTEFEUILLE'!I39 -> 52.08 | H24: ='📈 PORTEFEUILLE'!K39 -> CAD | I24: ='📈 PORTEFEUILLE'!I39 -> 52.08 | J24: ='📈 PORTEFEUILLE'!L39 -> 1093.68 | K24: =IFERROR('📈 PORTEFEUILLE'!G39*'📈 PORTEFEUILLE'!H39,0) -> 848.5386 | L24: ='📈 PORTEFEUILLE'!N39 -> 245.1414 | M24: ='📈 PORTEFEUILLE'!O39 -> 0.28889835 | N24: ='📈 PORTEFEUILLE'!P39 -> 0.012808625 | O24: 0.025 | P24: 27.8355 | Q24: 2.319625 | R24: ='📈 PORTEFEUILLE'!Q39 -> 🔄 Diluer
A25: ='📈 PORTEFEUILLE'!B23 -> MSFT | B25: ='📈 PORTEFEUILLE'!C23 -> Microsoft | C25: ='📈 PORTEFEUILLE'!D23 -> Action | D25: ='📈 PORTEFEUILLE'!E23 -> T2 | E25: ='📈 PORTEFEUILLE'!F23 -> TFSA | F25: ='📈 PORTEFEUILLE'!G23 -> 2 | G25: ='📈 PORTEFEUILLE'!I23 -> 536.32624 | H25: ='📈 PORTEFEUILLE'!K23 -> USD | I25: ='📈 PORTEFEUILLE'!I23 -> 536.32624 | J25: ='📈 PORTEFEUILLE'!L23 -> 1072.6525 | K25: =IFERROR('📈 PORTEFEUILLE'!G23*'📈 PORTEFEUILLE'!H23,0) -> 625.1876 | L25: ='📈 PORTEFEUILLE'!N23 -> 447.46489 | M25: ='📈 PORTEFEUILLE'!O23 -> 0.71572899 | N25: ='📈 PORTEFEUILLE'!P23 -> 0.012562361 | O25: 0.008 | P25: 8.7516451 | Q25: 0.72930375 | R25: ='📈 PORTEFEUILLE'!Q23 -> ✅ Garder
A26: ='📈 PORTEFEUILLE'!B25 -> TSLA | B26: ='📈 PORTEFEUILLE'!C25 -> Tesla | C26: ='📈 PORTEFEUILLE'!D25 -> Action | D26: ='📈 PORTEFEUILLE'!E25 -> T2 | E26: ='📈 PORTEFEUILLE'!F25 -> TFSA | F26: ='📈 PORTEFEUILLE'!G25 -> 1.8645 | G26: ='📈 PORTEFEUILLE'!I25 -> 530.42808 | H26: ='📈 PORTEFEUILLE'!K25 -> USD | I26: ='📈 PORTEFEUILLE'!I25 -> 530.42808 | J26: ='📈 PORTEFEUILLE'!L25 -> 988.98316 | K26: =IFERROR('📈 PORTEFEUILLE'!G25*'📈 PORTEFEUILLE'!H25,0) -> 565.99582 | L26: ='📈 PORTEFEUILLE'!N25 -> 422.98733 | M26: ='📈 PORTEFEUILLE'!O25 -> 0.74733295 | N26: ='📈 PORTEFEUILLE'!P25 -> 0.011582468 | O26: 0 | P26: 0 | Q26: 0 | R26: ='📈 PORTEFEUILLE'!Q25 -> ✅ Garder
A27: ='📈 PORTEFEUILLE'!B27 -> XEQT.TO | B27: ='📈 PORTEFEUILLE'!C27 -> iShares Core Eq | C27: ='📈 PORTEFEUILLE'!D27 -> ETF | D27: ='📈 PORTEFEUILLE'!E27 -> T2 | E27: ='📈 PORTEFEUILLE'!F27 -> TFSA | F27: ='📈 PORTEFEUILLE'!G27 -> 25 | G27: ='📈 PORTEFEUILLE'!I27 -> 39.85 | H27: ='📈 PORTEFEUILLE'!K27 -> CAD | I27: ='📈 PORTEFEUILLE'!I27 -> 39.85 | J27: ='📈 PORTEFEUILLE'!L27 -> 996.25 | K27: =IFERROR('📈 PORTEFEUILLE'!G27*'📈 PORTEFEUILLE'!H27,0) -> 999.25 | L27: ='📈 PORTEFEUILLE'!N27 -> -3 | M27: ='📈 PORTEFEUILLE'!O27 -> -0.0030022517 | N27: ='📈 PORTEFEUILLE'!P27 -> 0.011667574 | O27: 0.02 | P27: 20.23 | Q27: 1.6858333 | R27: ='📈 PORTEFEUILLE'!Q27 -> ✅ Migration ZEQT ✅
A28: ='📈 PORTEFEUILLE'!B56 -> XIC.TO | B28: ='📈 PORTEFEUILLE'!C56 -> iShares TSX | C28: ='📈 PORTEFEUILLE'!D56 -> ETF | D28: ='📈 PORTEFEUILLE'!E56 -> T4 | E28: ='📈 PORTEFEUILLE'!F56 -> FHSA | F28: ='📈 PORTEFEUILLE'!G56 -> 19 | G28: ='📈 PORTEFEUILLE'!I56 -> 52.08 | H28: ='📈 PORTEFEUILLE'!K56 -> CAD | I28: ='📈 PORTEFEUILLE'!I56 -> 52.08 | J28: ='📈 PORTEFEUILLE'!L56 -> 989.52 | K28: =IFERROR('📈 PORTEFEUILLE'!G56*'📈 PORTEFEUILLE'!H56,0) -> 919.0395 | L28: ='📈 PORTEFEUILLE'!N56 -> 70.4805 | M28: ='📈 PORTEFEUILLE'!O56 -> 0.015483182 | N28: ='📈 PORTEFEUILLE'!P56 -> 0.017820206 | O28: 0.025 | P28: 25.1845 | Q28: 2.0987083 | R28: ='📈 PORTEFEUILLE'!Q56 -> 🔄 Diluer
A29: ='📈 PORTEFEUILLE'!B24 -> NVDA | B29: ='📈 PORTEFEUILLE'!C24 -> NVIDIA | C29: ='📈 PORTEFEUILLE'!D24 -> Action | D29: ='📈 PORTEFEUILLE'!E24 -> T2 | E29: ='📈 PORTEFEUILLE'!F24 -> TFSA | F29: ='📈 PORTEFEUILLE'!G24 -> 4 | G29: ='📈 PORTEFEUILLE'!I24 -> 244.40097 | H29: ='📈 PORTEFEUILLE'!K24 -> USD | I29: ='📈 PORTEFEUILLE'!I24 -> 244.40097 | J29: ='📈 PORTEFEUILLE'!L24 -> 977.6039 | K29: =IFERROR('📈 PORTEFEUILLE'!G24*'📈 PORTEFEUILLE'!H24,0) -> 514.36 | L29: ='📈 PORTEFEUILLE'!N24 -> 463.2439 | M29: ='📈 PORTEFEUILLE'!O24 -> 0.90062194 | N29: ='📈 PORTEFEUILLE'!P24 -> 0.0114492 | O29: 0.003 | P29: 3.006365 | Q29: 0.25053042 | R29: ='📈 PORTEFEUILLE'!Q24 -> ✅ Garder
A30: ='📈 PORTEFEUILLE'!B57 -> XEI.TO | B30: ='📈 PORTEFEUILLE'!C57 -> iShares High Div | C30: ='📈 PORTEFEUILLE'!D57 -> ETF | D30: ='📈 PORTEFEUILLE'!E57 -> T4 | E30: ='📈 PORTEFEUILLE'!F57 -> FHSA | F30: ='📈 PORTEFEUILLE'!G57 -> 26 | G30: ='📈 PORTEFEUILLE'!I57 -> 35.89 | H30: ='📈 PORTEFEUILLE'!K57 -> CAD | I30: ='📈 PORTEFEUILLE'!I57 -> 35.89 | J30: ='📈 PORTEFEUILLE'!L57 -> 933.14 | K30: =IFERROR('📈 PORTEFEUILLE'!G57*'📈 PORTEFEUILLE'!H57,0) -> 847.8886 | L30: ='📈 PORTEFEUILLE'!N57 -> 85.2514 | M30: ='📈 PORTEFEUILLE'!O57 -> 0.076689304 | N30: ='📈 PORTEFEUILLE'!P57 -> 0.011588756 | O30: 0.055 | P30: 51.051 | Q30: 4.25425 | R30: ='📈 PORTEFEUILLE'!Q57 -> 🔄 Migration VDY ✅
A31: ='📈 PORTEFEUILLE'!B20 -> META | B31: ='📈 PORTEFEUILLE'!C20 -> Meta Platforms | C31: ='📈 PORTEFEUILLE'!D20 -> Action | D31: ='📈 PORTEFEUILLE'!E20 -> T1 | E31: ='📈 PORTEFEUILLE'!F20 -> TFSA | F31: ='📈 PORTEFEUILLE'!G20 -> 1 | G31: ='📈 PORTEFEUILLE'!I20 -> 832.12939 | H31: ='📈 PORTEFEUILLE'!K20 -> USD | I31: ='📈 PORTEFEUILLE'!I20 -> 832.12939 | J31: ='📈 PORTEFEUILLE'!L20 -> 832.12939 | K31: =IFERROR('📈 PORTEFEUILLE'!G20*'📈 PORTEFEUILLE'!H20,0) -> 637.7698 | L31: ='📈 PORTEFEUILLE'!N20 -> 194.35959 | M31: ='📈 PORTEFEUILLE'!O20 -> 0.30474881 | N31: ='📈 PORTEFEUILLE'!P20 -> 0.0097454768 | O31: 0.004 | P31: 3.5335398 | Q31: 0.29446165 | R31: ='📈 PORTEFEUILLE'!Q20 -> ✅ Accumuler
A32: ='📈 PORTEFEUILLE'!B33 -> QTUM | B32: ='📈 PORTEFEUILLE'!C33 -> Defiance Quantum | C32: ='📈 PORTEFEUILLE'!D33 -> ETF | D32: ='📈 PORTEFEUILLE'!E33 -> T3 | E32: ='📈 PORTEFEUILLE'!F33 -> TFSA | F32: ='📈 PORTEFEUILLE'!G33 -> 5 | G32: ='📈 PORTEFEUILLE'!I33 -> 148.29478 | H32: ='📈 PORTEFEUILLE'!K33 -> USD | I32: ='📈 PORTEFEUILLE'!I33 -> 148.29478 | J32: ='📈 PORTEFEUILLE'!L33 -> 741.47392 | K32: =IFERROR('📈 PORTEFEUILLE'!G33*'📈 PORTEFEUILLE'!H33,0) -> 604.05 | L32: ='📈 PORTEFEUILLE'!N33 -> 137.42391 | M32: ='📈 PORTEFEUILLE'!O33 -> 0.2275042 | N32: ='📈 PORTEFEUILLE'!P33 -> 0.0086837659 | O32: 0.004 | P32: 3.0591369 | Q32: 0.25492808 | R32: ='📈 PORTEFEUILLE'!Q33 -> 🔵 Garder (max 5)
A33: ='📈 PORTEFEUILLE'!B21 -> ENB.TO | B33: ='📈 PORTEFEUILLE'!C21 -> Enbridge | C33: ='📈 PORTEFEUILLE'!D21 -> Action | D33: ='📈 PORTEFEUILLE'!E21 -> T1 | E33: ='📈 PORTEFEUILLE'!F21 -> TFSA | F33: ='📈 PORTEFEUILLE'!G21 -> 9 | G33: ='📈 PORTEFEUILLE'!I21 -> 74.28 | H33: ='📈 PORTEFEUILLE'!K21 -> CAD | I33: ='📈 PORTEFEUILLE'!I21 -> 74.28 | J33: ='📈 PORTEFEUILLE'!L21 -> 668.52 | K33: =IFERROR('📈 PORTEFEUILLE'!G21*'📈 PORTEFEUILLE'!H21,0) -> 446.58 | L33: ='📈 PORTEFEUILLE'!N21 -> 221.94 | M33: ='📈 PORTEFEUILLE'!O21 -> 0.49697703 | N33: ='📈 PORTEFEUILLE'!P21 -> 0.0078293667 | O33: 0.065 | P33: 42.6231 | Q33: 3.551925 | R33: ='📈 PORTEFEUILLE'!Q21 -> ✅ Garder
A34: ='📈 PORTEFEUILLE'!B50 -> XEQT.TO | B34: ='📈 PORTEFEUILLE'!C50 -> iShares Core Eq | C34: ='📈 PORTEFEUILLE'!D50 -> ETF | D34: ='📈 PORTEFEUILLE'!E50 -> T2 | E34: ='📈 PORTEFEUILLE'!F50 -> FHSA | F34: ='📈 PORTEFEUILLE'!G50 -> 15 | G34: ='📈 PORTEFEUILLE'!I50 -> 39.85 | H34: ='📈 PORTEFEUILLE'!K50 -> CAD | I34: ='📈 PORTEFEUILLE'!I50 -> 39.85 | J34: ='📈 PORTEFEUILLE'!L50 -> 597.75 | K34: =IFERROR('📈 PORTEFEUILLE'!G50*'📈 PORTEFEUILLE'!H50,0) -> 600.9 | L34: ='📈 PORTEFEUILLE'!N50 -> -3.15 | M34: ='📈 PORTEFEUILLE'!O50 -> 0.33969758 | N34: ='📈 PORTEFEUILLE'!P50 -> 0.020616087 | O34: 0.02 | P34: 12.138 | Q34: 1.0115 | R34: ='📈 PORTEFEUILLE'!Q50 -> ✅ Migration ZEQT ✅
A35: ='📈 PORTEFEUILLE'!B52 -> H.TO | B35: ='📈 PORTEFEUILLE'!C52 -> Hydro One | C35: ='📈 PORTEFEUILLE'!D52 -> Action | D35: ='📈 PORTEFEUILLE'!E52 -> T3 | E35: ='📈 PORTEFEUILLE'!F52 -> FHSA | F35: ='📈 PORTEFEUILLE'!G52 -> 10 | G35: ='📈 PORTEFEUILLE'!I52 -> 60.09 | H35: ='📈 PORTEFEUILLE'!K52 -> CAD | I35: ='📈 PORTEFEUILLE'!I52 -> 60.09 | J35: ='📈 PORTEFEUILLE'!L52 -> 600.9 | K35: =IFERROR('📈 PORTEFEUILLE'!G52*'📈 PORTEFEUILLE'!H52,0) -> 517.8 | L35: ='📈 PORTEFEUILLE'!N52 -> 83.1 | M35: ='📈 PORTEFEUILLE'!O52 -> 0.55608215 | N35: ='📈 PORTEFEUILLE'!P52 -> 0.022494849 | O35: 0.03 | P35: 17.601 | Q35: 1.46675 | R35: ='📈 PORTEFEUILLE'!Q52 -> 🔵 Garder
A36: ='📈 PORTEFEUILLE'!B28 -> SPGI | B36: ='📈 PORTEFEUILLE'!C28 -> S&P Global | C36: ='📈 PORTEFEUILLE'!D28 -> Action | D36: ='📈 PORTEFEUILLE'!E28 -> T2 | E36: ='📈 PORTEFEUILLE'!F28 -> TFSA | F36: ='📈 PORTEFEUILLE'!G28 -> 0.9996 | G36: ='📈 PORTEFEUILLE'!I28 -> 572.85419 | H36: ='📈 PORTEFEUILLE'!K28 -> USD | I36: ='📈 PORTEFEUILLE'!I28 -> 572.85419 | J36: ='📈 PORTEFEUILLE'!L28 -> 572.62505 | K36: =IFERROR('📈 PORTEFEUILLE'!G28*'📈 PORTEFEUILLE'!H28,0) -> 443.0685 | L36: ='📈 PORTEFEUILLE'!N28 -> 129.55655 | M36: ='📈 PORTEFEUILLE'!O28 -> 0.29240749 | N36: ='📈 PORTEFEUILLE'!P28 -> 0.0067062938 | O36: 0.009 | P36: 5.2158413 | Q36: 0.43465344 | R36: ='📈 PORTEFEUILLE'!Q28 -> ✅ Garder
A37: ='📈 PORTEFEUILLE'!B32 -> T.TO | B37: ='📈 PORTEFEUILLE'!C32 -> TELUS | C37: ='📈 PORTEFEUILLE'!D32 -> Action | D37: ='📈 PORTEFEUILLE'!E32 -> T3 | E37: ='📈 PORTEFEUILLE'!F32 -> TFSA | F37: ='📈 PORTEFEUILLE'!G32 -> 32 | G37: ='📈 PORTEFEUILLE'!I32 -> 18.01 | H37: ='📈 PORTEFEUILLE'!K32 -> CAD | I37: ='📈 PORTEFEUILLE'!I32 -> 18.01 | J37: ='📈 PORTEFEUILLE'!L32 -> 576.32 | K37: =IFERROR('📈 PORTEFEUILLE'!G32*'📈 PORTEFEUILLE'!H32,0) -> 705.28 | L37: ='📈 PORTEFEUILLE'!N32 -> -128.96 | M37: ='📈 PORTEFEUILLE'!O32 -> -0.18284936 | N37: ='📈 PORTEFEUILLE'!P32 -> 0.0067495672 | O37: 0.085 | P37: 49.0688 | Q37: 4.0890667 | R37: ='📈 PORTEFEUILLE'!Q32 -> 👀 Surveiller div Q3
A38: ='📈 PORTEFEUILLE'!B40 -> ZRE.TO | B38: ='📈 PORTEFEUILLE'!C40 -> BMO Equal REITs | C38: ='📈 PORTEFEUILLE'!D40 -> ETF | D38: ='📈 PORTEFEUILLE'!E40 -> T4 | E38: ='📈 PORTEFEUILLE'!F40 -> TFSA | F38: ='📈 PORTEFEUILLE'!G40 -> 19 | G38: ='📈 PORTEFEUILLE'!I40 -> 22.33 | H38: ='📈 PORTEFEUILLE'!K40 -> CAD | I38: ='📈 PORTEFEUILLE'!I40 -> 22.33 | J38: ='📈 PORTEFEUILLE'!L40 -> 424.27 | K38: =IFERROR('📈 PORTEFEUILLE'!G40*'📈 PORTEFEUILLE'!H40,0) -> 395.77 | L38: ='📈 PORTEFEUILLE'!N40 -> 28.5 | M38: ='📈 PORTEFEUILLE'!O40 -> 0.072011522 | N38: ='📈 PORTEFEUILLE'!P40 -> 0.0049688348 | O38: 0.05 | P38: 21.4225 | Q38: 1.7852083 | R38: ='📈 PORTEFEUILLE'!Q40 -> 🔄 Diluer
A39: ='📈 PORTEFEUILLE'!B41 -> MFC.TO | B39: ='📈 PORTEFEUILLE'!C41 -> Manulife | C39: ='📈 PORTEFEUILLE'!D41 -> Action | D39: ='📈 PORTEFEUILLE'!E41 -> T4 | E39: ='📈 PORTEFEUILLE'!F41 -> TFSA | F39: ='📈 PORTEFEUILLE'!G41 -> 8 | G39: ='📈 PORTEFEUILLE'!I41 -> 45.9 | H39: ='📈 PORTEFEUILLE'!K41 -> CAD | I39: ='📈 PORTEFEUILLE'!I41 -> 45.9 | J39: ='📈 PORTEFEUILLE'!L41 -> 367.2 | K39: =IFERROR('📈 PORTEFEUILLE'!G41*'📈 PORTEFEUILLE'!H41,0) -> 413.6 | L39: ='📈 PORTEFEUILLE'!N41 -> -46.4 | M39: ='📈 PORTEFEUILLE'!O41 -> -0.11218569 | N39: ='📈 PORTEFEUILLE'!P41 -> 0.0043004599 | O39: 0.044 | P39: 16.14624 | Q39: 1.34552 | R39: ='📈 PORTEFEUILLE'!Q41 -> 🔄 Diluer
A40: ='📈 PORTEFEUILLE'!B34 -> HURA.TO | B40: ='📈 PORTEFEUILLE'!C34 -> Global X Uranium | C40: ='📈 PORTEFEUILLE'!D34 -> ETF | D40: ='📈 PORTEFEUILLE'!E34 -> T3 | E40: ='📈 PORTEFEUILLE'!F34 -> TFSA | F40: ='📈 PORTEFEUILLE'!G34 -> 6 | G40: ='📈 PORTEFEUILLE'!I34 -> 57.54 | H40: ='📈 PORTEFEUILLE'!K34 -> CAD | I40: ='📈 PORTEFEUILLE'!I34 -> 57.54 | J40: ='📈 PORTEFEUILLE'!L34 -> 345.24 | K40: =IFERROR('📈 PORTEFEUILLE'!G34*'📈 PORTEFEUILLE'!H34,0) -> 331.5 | L40: ='📈 PORTEFEUILLE'!N34 -> 13.74 | M40: ='📈 PORTEFEUILLE'!O34 -> 0.041447964 | N40: ='📈 PORTEFEUILLE'!P34 -> 0.0040432755 | O40: 0.002 | P40: 0.71424 | Q40: 0.05952 | R40: ='📈 PORTEFEUILLE'!Q34 -> 🔵 Garder
A41: ='📈 PORTEFEUILLE'!B42 -> VDU.TO | B41: ='📈 PORTEFEUILLE'!C42 -> Vanguard Dev | C41: ='📈 PORTEFEUILLE'!D42 -> ETF | D41: ='📈 PORTEFEUILLE'!E42 -> T4 | E41: ='📈 PORTEFEUILLE'!F42 -> TFSA | F41: ='📈 PORTEFEUILLE'!G42 -> 6 | G41: ='📈 PORTEFEUILLE'!I42 -> 55.07 | H41: ='📈 PORTEFEUILLE'!K42 -> CAD | I41: ='📈 PORTEFEUILLE'!I42 -> 55.07 | J41: ='📈 PORTEFEUILLE'!L42 -> 330.42 | K41: =IFERROR('📈 PORTEFEUILLE'!G42*'📈 PORTEFEUILLE'!H42,0) -> 262.5 | L41: ='📈 PORTEFEUILLE'!N42 -> 67.92 | M41: ='📈 PORTEFEUILLE'!O42 -> 0.25874286 | N41: ='📈 PORTEFEUILLE'!P42 -> 0.0038697112 | O41: 0.038 | P41: 12.81132 | Q41: 1.06761 | R41: ='📈 PORTEFEUILLE'!Q42 -> 🔄 Diluer
A42: ='📈 PORTEFEUILLE'!B53 -> ZLB.TO | B42: ='📈 PORTEFEUILLE'!C53 -> BMO Low Vol | C42: ='📈 PORTEFEUILLE'!D53 -> ETF | D42: ='📈 PORTEFEUILLE'!E53 -> T3 | E42: ='📈 PORTEFEUILLE'!F53 -> FHSA | F42: ='📈 PORTEFEUILLE'!G53 -> 3 | G42: ='📈 PORTEFEUILLE'!I53 -> 59.04 | H42: ='📈 PORTEFEUILLE'!K53 -> CAD | I42: ='📈 PORTEFEUILLE'!I53 -> 59.04 | J42: ='📈 PORTEFEUILLE'!L53 -> 177.12 | K42: =IFERROR('📈 PORTEFEUILLE'!G53*'📈 PORTEFEUILLE'!H53,0) -> 177.1998 | L42: ='📈 PORTEFEUILLE'!N53 -> -0.0798 | M42: ='📈 PORTEFEUILLE'!O53 -> 0.16048667 | N42: ='📈 PORTEFEUILLE'!P53 -> 0.0070374356 | O42: 0.024 | P42: 4.24872 | Q42: 0.35406 | R42: ='📈 PORTEFEUILLE'!Q53 -> 🔵 Garder
A43: ='📈 PORTEFEUILLE'!B63 -> JEPI | B43: ='📈 PORTEFEUILLE'!C63 -> JPMorgan Income | C43: ='📈 PORTEFEUILLE'!D63 -> ETF | D43: ='📈 PORTEFEUILLE'!E63 -> T2 | E43: ='📈 PORTEFEUILLE'!F63 -> REER | F43: ='📈 PORTEFEUILLE'!G63 -> 1 | G43: ='📈 PORTEFEUILLE'!I63 -> 77.408331 | H43: ='📈 PORTEFEUILLE'!K63 -> USD | I43: ='📈 PORTEFEUILLE'!I63 -> 77.408331 | J43: ='📈 PORTEFEUILLE'!L63 -> 77.408331 | K43: =IFERROR('📈 PORTEFEUILLE'!G63*'📈 PORTEFEUILLE'!H63,0) -> 54.52 | L43: ='📈 PORTEFEUILLE'!N63 -> 22.888331 | M43: ='📈 PORTEFEUILLE'!O63 -> 0 | N43: ='📈 PORTEFEUILLE'!P63 -> 0 | O43: 0.075 | P43: 5.8858327 | Q43: 0.49048606 | R43: ='📈 PORTEFEUILLE'!Q63 -> ✅ Garder
A44: ◼ TOTAL PORTEFEUILLE | J44: =SUM(J5:J43) -> 85139.166 | K44: =SUM(K5:K43) -> 62790.498 | L44: =SUM(L5:L43) -> 22348.669 | M44: 0.20572898 | N44: 1 | P44: 1925.9435 | Q44: 160.49529
A46: 📊 RÉSUMÉ PAR TIER · 12 mars 2026
A47: TIER | B47: NB POS. | C47: VALEUR CAD | D47: % PORT. | E47: GAIN $ | F47: GAIN % | G47: DIV/AN | H47: DESCRIPTION
A48: T1 | B48: 11 | C48: 48010.729 | D48: 0.55394345 | E48: 7733.1229 | F48: 0.19199559 | G48: 475.9095 | H48: Conviction maximale — AVGO, VFV.TO, SMH, GOOG, AMZN, META, ENB, GEV, SCHD — Accumuler agressivement
A49: T2 | B49: 9 | C49: 8691.99 | D49: 0.10028739 | E49: 812.11787 | F49: 0.10306232 | G49: 74.988499 | H49: Accumuler sélectivement — MSFT, NVDA, TSLA, QQQM, XEQT, SPGI, JEPI — En dip seulement
A50: T3 | B50: 9 | C50: 19228.644 | D50: 0.22185836 | E50: 5181.0206 | F50: 0.3688183 | G50: 803.81274 | H50: Garder, ne plus acheter — TD, ZLB, H.TO, T.TO, QTUM, HURA — Diluer naturellement
A51: T4 | B51: 10 | C51: 10739.45 | D51: 0.1239108 | E51: 1062.0521 | F51: 0.10974563 | G51: 571.23276 | H51: Diluer naturellement — REITs, XEI, XIC, ZRE, MFC, VDU — Coussin défensif

Sheet 🏠 DASHBOARD
B1: 🏠 TABLEAU DE BORD · PORTEFEUILLE FI · MAXIMIZE — PAS DE CIBLE, TOUJOURS PLUS
B2: v49-S19 · 12 mars 2026 · Partenaire FI permanent : Claude · Plan $5,000/mois structuré
B4: ① STATUT SESSION · Cocher avant de commencer
B5: VÉRIFICATION | C5: VALEUR / STATUT | E5: CONTEXTE MARCHÉ | G5: INTENTION SESSION
B6: 📎 Wallet uploadé? | C6: ⬜ Confirmer | E6: =IFERROR("S&P "&TEXT(CONFIG!G36,"#,##0")&" ("&TEXT(CONFIG!B49,"+0.0%")&")","S&P: N/A") -> S&P 6,632 (-+4.3%) | G6: ⬜ Dire à Claude
B7: 📋 Questrade dump? | C7: ⬜ Confirmer | E7: =IFERROR("TSX "&TEXT(CONFIG!G37,"#,##0")&" ("&TEXT(CONFIG!B50,"+0.0%")&")","TSX: N/A") -> TSX 32,542 (+2.6%) | G7: BdC 18 mars · Fed 18-19 mars
B8: 💱 USD/CAD | C8: =CONFIG!B3 -> 1.3559 | E8: =IFERROR("USD/CAD "&TEXT(CONFIG!B3,"0.0000"),"N/A") -> USD/CAD 1.3559 | G8: =IFERROR(TEXT(NOW(),"dd mmm yyyy HH:MM")&" HNE","--") -> 15 Mar 2026 01:10 HNE
B9: 💰 Cash TFSA / FHSA | C9: =CONFIG!B37 -> 230.66 | E9: =CONFIG!B38 -> 15.13 | G9: VIX: saisir ⬜
B11: ② PORTFOLIO LIVE · Valeurs en temps réel depuis 📈 PORTEFEUILLE
B12: COMPTE | C12: VALEUR ACTUELLE | D12: DÉPOSÉ | E12: P&L $ | F12: P&L % | G12: ROOM DISPO | H12: NOTE / RÔLE
B13: TFSA 📈 | C13: ='📈 PORTEFEUILLE'!L44 -> 67855.03 | D13: ='📈 PORTEFEUILLE'!M44 -> 50044.273 | E13: ='📈 PORTEFEUILLE'!N44 -> 18727.904 | F13: ='📈 PORTEFEUILLE'!O44 -> 0 | G13: =CONFIG!B6 -> 69600 | H13: Croissance LT · Retraite · Intouchable
B14: FHSA 🏠 | C14: ='📈 PORTEFEUILLE'!L59 -> 14767.018 | D14: ='📈 PORTEFEUILLE'!M59 -> 10890.934 | E14: ='📈 PORTEFEUILLE'!N59 -> 2552.2128 | F14: ='📈 PORTEFEUILLE'!O59 -> 0.17283197 | G14: =CONFIG!B7 -> 13700 | H14: Maison 2030+ · Double exonération fiscale
B15: REER ❄️🔥 | C15: ='📈 PORTEFEUILLE'!L68 -> 2764.1683 | D15: ='📈 PORTEFEUILLE'!M68 -> 2095.7125 | E15: ='📈 PORTEFEUILLE'!N68 -> 1091.44 | F15: ='📈 PORTEFEUILLE'!O68 -> 0.39485295 | G15: =CONFIG!B8 -> 37008 | H15: RAP $60K · Snowball ARC $1,060/mois
B16: ▼ TOTAL PORTFOLIO | C16: ='📈 PORTEFEUILLE'!L70 -> 85386.216 | D16: ='📈 PORTEFEUILLE'!M70 -> 63030.92 | E16: ='📈 PORTEFEUILLE'!N70 -> 22371.557 | F16: ='📈 PORTEFEUILLE'!O70 -> 0.26200431 | G16: SNOWBALL: $1,590/mois | H16: Dividendes est. ~$3,200/an
B18: ③ ACTIONS URGENTES · Statut auto
B19: # | C19: ACTION | F19: STATUT | G19: IMPACT | H19: DÉLAI / NOTE
B20: 🔴 1 | C20: Ouvrir EQ Bank — Fonds urgence $15,000 | F20: =IF(CONFIG!B25>=15000,"✅ FAIT",IF(CONFIG!B25>0,"🟡 EN COURS","🔴 À FAIRE")) -> 🔴 À FAIRE | G20: Risque ×0 | H20: CE MOIS · Risque opérationnel #1
B21: 🔴 2 | C21: Vendre ZRE.TO + XIC.TO + VDU.TO → T1 (~$1,878) | F21: =IF(SUMIF('📈 PORTEFEUILLE'!B14:B64,"ZRE.TO",'📈 PORTEFEUILLE'!G14:G64)=0,"✅ FAIT","🔴 POST-BdC 18 mars") -> 🔴 POST-BdC 18 mars | G21: ~+$80/an | H21: Post-BdC 18 mars · T4→T1
B22: 🟡 3 | C22: Vérifier Mon Dossier ARC — Revenu net 2025 | F22: 🟡 PLANIFIER | G22: $1,500 crédit | H22: Avant déc 2026 · NON ÉLIG. 2026 ($140K > $129,590)
B23: ✅ 4 | C23: PLZ.UN 961u vendus @ $4.26 → AVGO+GEV+SMH | F23: ✅ EXÉCUTÉ 11 mars | G23: +$4,094 CAD | H23: T4→T1 réalisé
B24: ✅ 5 | C24: SCHD $2,000 REER — 64.3053u @ $30.85 USD | F24: ✅ EXÉCUTÉ 12 mars | G24: +$1,060/mois ARC | H24: Snowball fiscal activé
B26: ④ CHECKLIST DÉCISIONS · OUI/NON avant tout achat
B27: QUESTION | F27: STATUT AUTO | H27: CONTEXTE
B28: 💰 EQ Bank $15K ouvert ? | F28: =IF(CONFIG!B25>=15000,"✅ OUI","🔴 NON — Ouvrir cette semaine") -> 🔴 NON — Ouvrir cette semaine | H28: 7 mois dépenses · sécurité de base
B29: 📊 Expo USD dans les seuils ? | F29: =CONFIG!B47 -> 🔴 SUREXPOSÉ USD — Rééquilibrer | H29: Seuil max 65% · auto
B30: 🤖 Expo IA dans les seuils ? | F30: =IF(CONFIG!B31>0.45,"🔴 DÉPASSE 45% — Pause T1 IA","✅ OK — Sous 45%") -> ✅ OK — Sous 45% | H30: Seuil max 45% · auto
B31: 📅 Earnings calendrier vérifié ? | F31: ⬜ Confirmer avant achat T1/T2 | H31: AVGO ~5 déc · GEV ~22 avr · SMH N/A ETF
B32: 🏠 Trade post-BdC 18 mars planifié ? | F32: =IF(DATEVALUE("2026-03-18")>TODAY(),"⏳ BdC dans "&(DATEVALUE("2026-03-18")-TODAY())&" jours","✅ BdC passé") -> ⏳ BdC dans 3 jours | H32: ZRE.TO + XIC.TO + VDU.TO → T1
B33: 💡 Remboursement ARC prévu ? | H33: À réinvestir dès réception avril 2027
B35: ⑤ OBJECTIF MAISON 2030+ · FHSA $40K + RAP REER $60K = $100K · Achat solo
B36: SOURCE | C36: AUJOURD'HUI | D36: OBJECTIF | E36: MANQUANT | F36: PROGRESSION | G36: STATUT
B37: FHSA | C37: ='📈 PORTEFEUILLE'!L59 -> 14767.018 | D37: =CONFIG!B14 -> 40000 | E37: =D37-C37 -> 25232.982 | F37: =IFERROR(C37/D37,0) -> 0.36917545 | G37: =IF(C37/D37>=1,"✅ ATTEINT",IF(C37/D37>=0.8,"🟡 80%+","⏳ En route")) -> ⏳ En route
B38: REER (RAP) | C38: ='📈 PORTEFEUILLE'!L68 -> 2764.1683 | D38: =CONFIG!B15 -> 60000 | E38: =D38-C38 -> 57235.832 | F38: =IFERROR(C38/D38,0) -> 0.046069471 | G38: =IF(C38/D38>=1,"✅ ATTEINT",IF(C38/D38>=0.8,"🟡 80%+","⏳ En route")) -> ⏳ En route
B39: ▼ TOTAL MAISON | C39: ='📈 PORTEFEUILLE'!L59+'📈 PORTEFEUILLE'!L68 -> 17531.186 | D39: =CONFIG!B16 -> 100000 | E39: =D39-C39 -> 82468.814 | F39: =IFERROR(C39/D39,0) -> 0.17531186 | G39: =IF(C39/D39>=1,"✅ ATTEINT",IF(C39/D39>=0.8,"🟡 80%+","⏳ En route")) -> ⏳ En route
B41: ⑥ PROJECTION FI · $2.1M = plancher · pas de plafond · maximiser toujours
B42: SCÉNARIO | C42: @40 ans | D42: @45 ans | E42: @50 ans | F42: @55 ans | G42: @60 ans | H42: NOTE
B43: 6% / an (conservateur) | C43: =IFERROR(CONFIG!B19*(1.06^(40-34))+5000*12*((1.06^(40-34)-1)/0.06),0) -> 0 | D43: $1,063,923 | E43: $1,761,995 | F43: $2,696,172 | G43: $3,946,312 | H43: ⚠️ FI @50 limit
B44: 8% / an (réaliste) | C44: =IFERROR(CONFIG!B19*(1.08^(40-34))+5000*12*((1.08^(40-34)-1)/0.08),0) -> 0 | D44: $1,202,162 | E44: $2,118,367 | F44: $3,464,572 | G44: $5,442,589 | H44: ✅ FI @48 (>$2.1M)
B45: 10% / an (optimiste) | C45: =IFERROR(CONFIG!B19*(1.1^(40-34))+5000*12*((1.1^(40-34)-1)/0.1),0) -> 0 | D45: $1,360,802 | E45: $2,557,891 | F45: $4,485,814 | G45: $7,590,755 | H45: 🚀 FI @46
B47: ⑦ SNOWBALL FISCAL · Chaque dollar REER coûte $0.47 net (52.98% récupéré)
B48: COMPTE | C48: COTISÉ /AN | D48: ÉCONOMIE IMPÔT | E48: COÛT NET | F48: VALEUR @20 ANS | G48: MULTIPLICATEUR | H48: NOTE
B49: 🔥 REER (SCHD) | C49: =2000*12 -> 24000 | D49: =C49*CONFIG!B11 -> 12715.2 | E49: =C49-D49 -> 11284.8 | F49: =E49*(1.08^20)*0.65 -> 34188.68 | G49: =IFERROR(F49/E49,0) -> 3.0296221 | H49: Priorité #1 · Snowball $1,060/mois ARC
B50: FHSA (VFV.TO) | C50: =1000*12 -> 12000 | D50: =C50*CONFIG!B11 -> 6357.6 | E50: =C50-D50 -> 5642.4 | F50: =E50*(1.08^20) -> 26298.985 | G50: =IFERROR(F50/E50,0) -> 4.6609571 | H50: Double exonération fiscale
B51: TFSA (AVGO) | C51: =500*12 -> 6000 | D51: 0 | E51: =C51-D51 -> 6000 | F51: =E51*(1.08^20) -> 27965.743 | G51: =IFERROR(F51/E51,0) -> 4.6609571 | H51: Croissance 100% tax-free
B52: EQ Bank HISA | C52: =1500*12 -> 18000 | D52: 0 | E52: =C52 -> 18000 | F52: =E52*(1.03^20) -> 32510.002 | G52: =IFERROR(F52/E52,0) -> 1.8061112 | H52: 🔴 À OUVRIR · Urgence + liquidités
B54: ⑧ EXPOSITION DEVISES · Seuil max USD 65% · Auto calculé
B55: MÉTRIQUE | C55: VALEUR | D55: SEUIL | E55: STATUT | F55: DÉTAIL
B56: Exposition USD % | C56: =CONFIG!B46 -> 0.96333537 | D56: 65% | E56: =CONFIG!B47 -> 🔴 SUREXPOSÉ USD — Rééquilibrer | F56: =CONFIG!B44&" USD en CAD" -> 2708811.76003001 USD en CAD
B57: Valeur USD (CAD) | C57: =CONFIG!B44 -> 2708811.8 | D57: — | E57: — | F57: Positions USD converties
B58: Valeur CAD (CAD) | C58: =CONFIG!B45 -> 103097.63 | D58: — | E58: — | F58: Positions libellées CAD
B59: Exposition IA % | C59: =CONFIG!B31 -> 0.28 | D59: 45% | E59: =IF(CONFIG!B31>0.45,"🔴 DÉPASSE","✅ OK") -> ✅ OK | F59: AVGO+SMH+NVDA+GOOG+META+GEV
B61: ⑨ BUDGET RÉEL · Basé talon de paie · 26 paies/an · Nunavik (logement + bouffe gratuits)
B62: POSTE | C62: MONTANT /MOIS | E62: DÉTAIL / NOTE
B63: 💰 Revenu net moyen | C63: 7950 | E63: ← $3,000×26÷12 + $1,450 prime · Confirmé S16
B64: 💸 Dépenses fixes | C64: 1182 | E64: Épicerie $400 · Tél $110 · Voiture $375 · Moto $80 · Divers $217
B65: 🎯 Disponible investir | C65: =C63-C64 -> 6768 | E65: ← Revenu − dépenses
B66: 📦 Plan investi /mois | C66: 5000 | E66: REER $2K + FHSA $1K + TFSA $500 + EQ Bank $1,500
B67: 📊 Surplus libre | C67: =C65-C66 -> 1768 | E67: ← Intentionnel · vie / imprévus · ~$1,768/mois
B68: 📈 Taux épargne | C68: =C66/C63 -> 0.62893082 | E68: ← $5,000/$7,950 = 62.9% · Potentiel 70%+ si surplus réinvesti
B70: ⑩ FORMAT SESSION IDÉAL · Protocole de démarrage
B71: (1) Ouvrir Google Sheets live → (2) Upload Wallet v49-S19.xlsx + dump Questrade → (3) Lire ② PORTFOLIO LIVE → (4) Cocher ④ CHECKLIST → (5) Dire intention à Claude → (6) Exécuter

Sheet 💵 BUDGET RÉEL
A1: 💵 BUDGET RÉEL · Portrait financier confirmé · Mars 2026 · v56-S33
A2: Données confirmées session S16 · Cellules en jaune = modifier si changement · Formules = auto
A4: 💰 REVENUS NETS MENSUELS
A5: POSTE | B5: MONTANT CAD | C5: TYPE | D5: NOTE
A6: Paie nette base (aux 2 semaines) | B6: 3000 | C6: Aux 2 sem. | D6: $3,000/paie × 26 ÷ 12 = $6,500/mois · Augmentation annuelle prévue
A7: Prime Nunavik (isolement + zone) | B7: 1450 | C7: Mensuel | D7: Confirmé S16 · Vérifier si change
A8: TOTAL REVENU NET /MOIS | B8: =(B6*26/12)+B7 -> 7950 | C8: AUTO · $3,000×26÷12 + $1,450 = $7,950/mois · Corrigé S18 | D8: ← Revenu mensuel disponible réel confirmé
A10: 💸 DÉPENSES MENSUELLES CONFIRMÉES
A11: POSTE | B11: MONTANT CAD | C11: TYPE | D11: NOTE
A12: Logement | B12: 0 | C12: Gratuit ✅ | D12: 100% payé par employeur Nunavik · Confirmé
A13: Internet | B13: 0 | C13: Gratuit ✅ | D13: Inclus logement employeur · Confirmé
A14: Épicerie / nourriture | B14: 400 | C14: Mensuel | D14: ~$400/mois confirmé S16 · Par rotation aux 2 semaines
A15: Téléphone cellulaire | B15: 110 | C15: Mensuel | D15: $110/mois confirmé
A16: Voiture — paiement/financement | B16: 275 | C16: Mensuel | D16: Milieu $200-350 · À confirmer exactement
A17: Voiture — assurance auto | B17: 100 | C17: Mensuel | D17: Milieu $80-120 · À confirmer exactement
A18: Moto — assurance | B18: 80 | C18: Mensuel/Sais. | D18: Milieu $60-100 · Saisonnière · Peut varier
A19: Essence | B19: 50 | C19: Mensuel | D19: Faible — déplacements limités Nunavik
A20: Abonnements (streaming, etc.) | B20: 25 | C20: Mensuel | D20: Netflix, Spotify, etc. · Milieu $0-50
A21: Loisirs / sorties / restaurants | B21: 50 | C21: Mensuel | D21: Très bas · Nunavik · Milieu $0-100
A22: Voyages / vacances (÷12) | B22: 42 | C22: Mensuel | D22: $500/an ÷ 12 · Budget conservateur confirmé
A23: Vêtements / équipement | B23: 50 | C23: Mensuel | D23: Moto, sport, divers · Milieu $0-100
A24: TOTAL DÉPENSES /MOIS | B24: =SUM(B12:B23) -> 1182 | C24: AUTO | D24: ← Somme toutes dépenses confirmées
A26: 📊 BILAN MENSUEL · Disponible vs Plan structuré
A27: POSTE | B27: MONTANT CAD | C27: TYPE | D27: NOTE
A28: Revenu net total | B28: =B8 -> 7950 | C28: AUTO | D28: ← Depuis section revenus
A29: Total dépenses | B29: =B24 -> 1182 | C29: AUTO | D29: ← Depuis section dépenses
A30: DISPONIBLE RÉEL /MOIS | B30: =B28-B29 -> 6768 | C30: AUTO | D30: ← Ce qui reste vraiment · Confirmé ~$6,768/mois
A32: ─── PLAN STRUCTURÉ $5,000/MOIS ───
A33: → REER (SCHD) | B33: 2000 | C33: Mensuel 🔴 | D33: Priorité #1 · Snowball fiscal $1,060/mois ARC · 52.98%
A34: → FHSA (VFV.TO) | B34: 1000 | C34: Mensuel 🔴 | D34: Priorité #2 · Maison 2030 + déduction fiscale
A35: → TFSA (AVGO fractionnel) | B35: 500 | C35: Mensuel 🔴 | D35: Priorité #3 · Croissance T1 long terme
A36: → EQ Bank HISA | B36: 1500 | C36: Mensuel 🆕 | D36: Priorité #4 · Fonds urgence · $15K en 10 mois
A37: TOTAL STRUCTURÉ | B37: =SUM(B33:B36) -> 5000 | C37: AUTO | D37: ← Doit égaler $5,000
A39: SURPLUS LIBRE (non structuré) | B39: =B30-B37 -> 1768 | C39: AUTO | D39: ← Argent libre · vie / loisirs / imprévus · ~$1,768
A40: Taux épargne structuré | B40: =B37/B28 -> 0.62893082 | C40: AUTO | D40: ← % revenu net investi/épargné · Objectif >60%
A46: 🏦 EQ BANK — TRACKER FONDS URGENCE
A47: POSTE | B47: MONTANT CAD | C47: TYPE | D47: NOTE
A48: Contribution mensuelle EQ Bank | B48: 1500 | C48: Mensuel | D48: ← Modifier si changement de plan
A49: Objectif fonds urgence | B49: 15000 | C49: Cible | D49: 7 mois × $1,182 dépenses = $8,274 min · $15K cible confortable
A50: Mois pour atteindre $15K | B50: =B49/B48 -> 10 | C50: AUTO | D50: ← Au rythme actuel depuis $0
A51: Solde actuel EQ Bank | B51: 0 | C51: MAJ manuellement | D51: ← Mettre à jour après chaque virement
A52: Reste à accumuler | B52: =MAX(0,B49-B51) -> 15000 | C52: AUTO | D52: ← $15,000 − solde actuel
A54: 🛡️ PROTECTION PERSONNELLE · Statut S16
A55: POSTE | B55: MONTANT CAD | C55: TYPE | D55: NOTE
A56: Assurance invalidité | B56: ✅ COMPLÈTE | C56: Employeur | D56: Couverture 100% employeur Nunavik · Confirmé S16
A57: Assurance vie | B57: ✅ DOUBLE | C57: Empl. + Privée | D57: Deux polices actives · Montants à documenter
A58: Régime retraite employeur | B58: ⚠️ EN VÉRIF. | C58: À confirmer | D58: 🔴 APPELER EMPLOYEUR — Impact sur room REER + calcul FI
A59: Bénéficiaires TFSA | B59: 🔴 NON FAIT | C59: URGENT | D59: Questrade.com → Mon compte → Bénéficiaires → 30 min
A60: Bénéficiaires REER | B60: 🔴 NON FAIT | C60: URGENT | D60: Sans désignation → succession → impôt immédiat sur 100%
A61: Bénéficiaires FHSA | B61: 🔴 NON FAIT | C61: URGENT | D61: Même page Questrade · Faire les 3 en même temps
A62: Testament | B62: ⬜ À VÉRIFIER | C62: Non urgent | D62: Pas de dépendants · Recommandé pour clarifier héritiers
A65: 🎯 OBJECTIFS CONFIRMÉS · FI + Maison + Budget
A66: POSTE | B66: MONTANT CAD | C66: TYPE | D66: NOTE
A67: Objectif FI | B67: $2,100,000 CAD | C67: Règle 4% | D67: $7,000/mois × 25 ans = $1.75M min · $2.1M = plancher
A68: Âge FI cible | B68: 55 ans (2047) | C68: 21 ans | D68: Confirmé S16 · FI = liberté · pas retraite obligatoire
A69: Revenu FI mensuel visé | B69: $7,000/mois | C69: Post-impôts | D69: Pouvoir d'achat 2026 · Ajuster inflation 2047
A70: Budget maison | B70: $400K-$500K CAD | C70: 2030+ | D70: Région non décidée · Solo · Achat indépendant
A71: Mise de fonds maison | B71: $100,000 CAD | C71: Cible | D71: FHSA $40K + RAP REER $60K · Sans toucher TFSA
A72: EQ Bank fonds urgence | B72: $15,000 CAD | C72: ~Jan 2027 | D72: $1,500/mois × 10 mois · ~10 mois au rythme actuel
A73: Taux marginal Québec | B73: 52.98% | C73: Confirmé | D73: REER + FHSA = chaque dollar coûte $0.47 réellement
A76: 💡 BILAN : Revenu $7,950 · Dépenses $1,182 · Disponible $6,768 · Structuré $5,000 · Libre $1,768/mois · Taux épargne 63%
A77: 🔑 ACTION #1 CETTE SEMAINE : Ouvrir EQ Bank (eqbank.ca) → Dès que paie rentre → Virer $1,500 AVANT de toucher Questrade
A78: 🔑 ACTION #2 : Questrade → Bénéficiaires TFSA/REER/FHSA → 30 minutes · Protection légale immédiate

Sheet 📊 ANALYSE PRO
A1: ="📊 ANALYSE PROFESSIONNELLE · "&TEXT(TODAY(),"DD MMMM YYYY")&" · CONFIDENTIEL — CONSEILLER FINANCIER" -> 📊 ANALYSE PROFESSIONNELLE · 15 March 2026 · CONFIDENTIEL — CONSEILLER FINANCIER
A4: 🎯 SCORECARD EXÉCUTIF
A5: MÉTRIQUE | B5: VALEUR | C5: CIBLE | D5: STATUT | E5: COMMENTAIRE CONSEILLER
A6: Portfolio Total CAD | B6: =TEXT('📈 PORTEFEUILLE'!C11,"$#,##0") -> $85,386 | C6: $87,252 (ATH) | D6: =IF('📈 PORTEFEUILLE'!C11>87252,"🟢 NOUVEL ATH","🟡 "&TEXT(87252-'📈 PORTEFEUILLE'!C11,"$#,##0")&" de l'ATH") -> 🟡 $1,866 de l'ATH | E6: Correction mineure post-ATH 10 mars. Normale.
A7: Gain total (investi) | B7: =TEXT('📈 PORTEFEUILLE'!N11,"$#,##0")&" / "&TEXT('📈 PORTEFEUILLE'!G11,"0.0%") -> $0 / 35.6% | C7: >15% | D7: =IF('📈 PORTEFEUILLE'!G11>0.15,"✅ SOLIDE","🟡 SOUS CIBLE") -> ✅ SOLIDE | E7: Performance supérieure au benchmark VFV.TO sur même période
A8: Expo USD | B8: =TEXT(CONFIG!B32,"0.0%") -> 96.3% | C8: ≤65% | D8: =CONFIG!B47 -> 🔴 SUREXPOSÉ USD — Rééquilibrer | E8: Bien dans les limites. Marge $17,900 avant alerte.
A9: Expo IA estimée | B9: =TEXT(CONFIG!B31,"0.0%") -> 28.0% | C9: ≤45% | D9: =IF(CONFIG!B31>0.45,"🔴 DÉPASSE 45%",IF(CONFIG!B31>0.4,"🟡 PROCHE","✅ OK")) -> ✅ OK | E9: Inclut SMH, AVGO, NVDA, QQQM, GEV, QTUM
A10: Tier 1 (conviction max) | B10: ="T1: "&TEXT(SUMIF('📋 MON PORTEFEUILLE'!D5:D43,"T1",'📋 MON PORTEFEUILLE'!J5:J43)/'📈 PORTEFEUILLE'!C11,"0.0%")&" / "&TEXT(SUMIF('📋 MON PORTEFEUILLE'!D5:D43,"T1",'📋 MON PORTEFEUILLE'!J5:J43),"$#,##0") -> T1: 54.9% / $46,900 | C10: >50% | D10: =IF(SUMIF('📋 MON PORTEFEUILLE'!D5:D43,"T1",'📋 MON PORTEFEUILLE'!J5:J43)/'📈 PORTEFEUILLE'!C11>0.5,"✅ CIBLE ATTEINTE","🟡 SOUS 50%") -> ✅ CIBLE ATTEINTE | E10: Excellente concentration sur les meilleures idées
A11: Tier 4 (dilution) | B11: ="T4: "&TEXT(SUMIF('📋 MON PORTEFEUILLE'!D5:D43,"T4",'📋 MON PORTEFEUILLE'!J5:J43)/'📈 PORTEFEUILLE'!C11,"0.0%")&" / "&TEXT(SUMIF('📋 MON PORTEFEUILLE'!D5:D43,"T4",'📋 MON PORTEFEUILLE'!J5:J43),"$#,##0") -> T4: 12.5% / $10,711 | C11: <15% | D11: =IF(SUMIF('📋 MON PORTEFEUILLE'!D5:D43,"T4",'📋 MON PORTEFEUILLE'!J5:J43)/'📈 PORTEFEUILLE'!C11<0.15,"✅ BON","🟡 À DILUER") -> ✅ BON | E11: REITs + ETFs défensifs: rôle cushion rempli
A12: Dividendes /an | B12: =TEXT(SUM('📋 MON PORTEFEUILLE'!P5:P43),"$#,##0")&" CAD" -> $1,926 CAD | C12: Croissant | D12: ✅ OK | E12: $160/mois — surtout T.TO, XEI, SRU.UN, ENB, TD
A13: Fonds urgence HISA | B13: =TEXT(CONFIG!B25,"$#,##0") -> $0 | C13: $0 → $1,500/mois planifié | D13: =IF(CONFIG!B25>=15000,"✅ ATTEINT",IF(CONFIG!B25>0,"🟡 EN COURS","🔴 CRITIQUE")) -> 🔴 CRITIQUE | E13: 🟡 EN COURS — Prochaine paie → $1,500 EQ Bank EN PREMIER
A14: FHSA room restant | B14: =TEXT(CONFIG!B7,"$#,##0") -> $13,700 | C14: Maximiser | D14: =IF(CONFIG!B7<1000,"⚠️ QUASI PLEIN",IF(CONFIG!B7<4000,"🟡 ACTION","✅ OK")) -> ✅ OK | E14: BdC 18 mars → opportunité achat VFV.TO pré-baisse taux
A15: Contributions auto | B15: NON | C15: $5,000/mois structuré | D15: 🔴 RISQUE | E15: 🟡 À AUTOMATISER avant 15 avril
A17: ⚠️ ANALYSE CONCENTRATION · Top positions & risques
A18: TICKER | B18: COMPTE | C18: VALEUR CAD | D18: % PORT. | E18: SEUIL ALERTE | F18: VERDICT CONSEILLER
A19: VFV.TO | B19: TFSA | C19: =TEXT('📋 MON PORTEFEUILLE'!J5,"$#,##0") -> $13,591 | D19: =TEXT('📋 MON PORTEFEUILLE'!J5/'📈 PORTEFEUILLE'!C11,"0.0%") -> 15.9% | E19: <25% | F19: ✅ Acceptable. Exposition S&P500 diversifiée par nature.
A20: TD.TO | B20: TFSA | C20: =TEXT('📋 MON PORTEFEUILLE'!J6,"$#,##0") -> $11,140 | D20: =TEXT('📋 MON PORTEFEUILLE'!J6/'📈 PORTEFEUILLE'!C11,"0.0%") -> 13.0% | E20: <10% T3 idéalement | F20: ⚠️ SURPONDÉRÉ pour un T3. Ne plus acheter. Diluer naturellement.
A21: SMH | B21: TFSA | C21: =TEXT('📋 MON PORTEFEUILLE'!J7,"$#,##0") -> $10,097 | D21: =TEXT('📋 MON PORTEFEUILLE'!J7/'📈 PORTEFEUILLE'!C11,"0.0%") -> 11.8% | E21: <15% | F21: ✅ Dans les limites. Semis = conviction validée.
A22: AVGO | B22: TFSA | C22: =TEXT('📋 MON PORTEFEUILLE'!J8,"$#,##0") -> $7,240 | D22: =TEXT('📋 MON PORTEFEUILLE'!J8/'📈 PORTEFEUILLE'!C11,"0.0%") -> 8.5% | E22: <15% | F22: ✅ T1 core. Accumuler si dip >5%.
A23: T3 Total | B23: Tous | C23: =TEXT(SUMIF('📋 MON PORTEFEUILLE'!D5:D43,"T3",'📋 MON PORTEFEUILLE'!J5:J43),"$#,##0") -> $19,009 | D23: =TEXT(SUMIF('📋 MON PORTEFEUILLE'!D5:D43,"T3",'📋 MON PORTEFEUILLE'!J5:J43)/'📈 PORTEFEUILLE'!C11,"0.0%") -> 22.3% | E23: <20% | F23: ⚠️ T3 légèrement surpondéré. Surtout dû à TD.TO.
A24: T.TO | B24: TFSA | C24: =TEXT('📋 MON PORTEFEUILLE'!J37,"$#,##0") -> $576 | D24: =TEXT('📋 MON PORTEFEUILLE'!J37/'📈 PORTEFEUILLE'!C11,"0.0%") -> 0.7% | E24: OK | F24: ⚠️ En perte -18.1%. NE PAS VENDRE (room TFSA). Surveiller dividende Q3.
A25: MFC.TO | B25: TFSA | C25: =TEXT('📋 MON PORTEFEUILLE'!J39,"$#,##0") -> $367 | D25: =TEXT('📋 MON PORTEFEUILLE'!J39/'📈 PORTEFEUILLE'!C11,"0.0%") -> 0.4% | E25: OK | F25: ⚠️ En perte -11.3%. NE PAS VENDRE. Règle absolue TFSA.
A27: ❄️ ANALYSE FISCALE · Optimisation snowball
A28: VÉHICULE | B28: COTISATION 2026 | C28: ÉCONOMIE IMPÔT | D28: COÛT RÉEL NET | E28: VALEUR @2042 (8%) | F28: STATUT
A29: REER SCHD | B29: $2,000 exécuté | C29: $1,060 (52.98%) | D29: $940 net | E29: ~$12,400 | F29: ✅ En cours · $2K/mois
A30: FHSA VFV.TO | B30: =TEXT(CONFIG!B33,"$#,##0")&" YTD" -> $2,300 YTD | C30: $6,357 (52.98%) | D30: $5,643 net | E30: ~$74,500 | F30: =IF(CONFIG!B7<1000,"⚠️ Room quasi plein","Room restant: $"&TEXT(CONFIG!B7,"#,##0")) -> Room restant: $13,700
A31: TFSA AVGO | B31: $500/mois | C31: $0 (exonéré) | D31: $6,000/an | E31: ~$37,200 | F31: 🟡 Pas automatisé
A32: TOTAL 2026 | B32: ~$38,000/an dispo | C32: ~$18,400 économie | D32: ~$19,600 coût réel
A33: FTQ 2026 | B33: NON ÉLIGIBLE | C33: Revenu $140K > $129K | D33: $0 | F33: 🔴 Surveiller 2027
A35: 💼 RECOMMANDATIONS CONSEILLER · Priorité décroissante · 12 mars 2026
A36: PRIORITÉ | B36: TYPE | C36: ACTION | D36: ÉCHÉANCE | E36: RAISONNEMENT CONSEILLER
A37: 🔴 | B37: URGENT | C37: EQ Bank: ouvrir + $1,500/mois dès prochaine paie | D37: Cette semaine | E37: Risque opérationnel #1. Urgence médicale/voiture = zéro coussin. 20 min. eqbank.ca. Taux ~4.0% = $600/an.
A38: 🔴 | B38: URGENT | C38: Automatiser $5,000/mois le 15 de chaque mois | D38: Avant 15 avril | E38: Sans automatisation tu vas timer le marché. Biais documenté en session. Virement auto REER $2K + FHSA $1K + TFSA $500.
A39: 🟡 | B39: STRATÉGIQUE | C39: FHSA $4,000 room restant → VFV.TO avant BdC 18 mars | D39: Avant 18 mars | E39: BdC → probable baisse taux → VFV monte. Acheter avant = meilleur prix. $4K = ~24 unités VFV.TO @ ~$163.
A40: 🟡 | B40: STRATÉGIQUE | C40: ZRE+XIC+VDU TFSA → T1 post-BdC | D40: Semaine du 18 mars | E40: $428+$1,113+$337 = $1,878 à recycler. ZRE→AVGO frac. XIC→VFV. VDU→SMH. Timing post-BdC optimal.
A41: 🟡 | B41: SUIVI | C41: Augmenter REER à $3,000/mois dès que EQ Bank ouvert | D41: Avril 2026 | E41: Ton vrai room est $37K. À $2K/mois tu utilises $24K/an. Tu laisses $13K de déduction sur la table. +$1,590 ARC additionnel.
A42: 🔵 | B42: VEILLE | C42: Surveiller AVGO >20% concentration | D42: Ongoing | E42: Si AVGO dépasse 15% du portfolio → évaluer allègement partiel dans TFSA. Pas encore là (8.8% actuellement).
A43: 🔵 | B43: VEILLE | C43: Verdict J+30 → 11 avril 2026 | D43: 11 avril | E43: Évaluer toutes décisions depuis 11 mars. Benchmark vs VFV.TO. Calculer alpha réel.
A45: 📈 PROJECTION FI · $86,670 + $3,500/mois · Objectif $2.1M+ (plancher)
A46: SCÉNARIO | B46: @36 ans | C46: @40 ans | D46: @45 ans | E46: @50 ans | F46: @55 ans | G46: @60 ans
A47: Pessimiste 6% | B47: $183,902 | C47: $415,906 | D47: $793,335 | E47: $1,298,418 | F47: $1,974,335 | G47: $2,878,863
A48: Réaliste 8% | B48: $188,452 | C48: $445,643 | D48: $901,194 | E48: $1,570,546 | F48: $2,554,045 | G48: $3,999,127
A49: Optimiste 10% | B49: $193,071 | C49: $477,597 | D49: $1,025,589 | E49: $1,908,135 | F49: $3,329,485 | G49: $5,618,583
A50: → FI à Pessimiste 6% | B50: Âge 56 (2048) | C50: $2,134,795 CAD
A51: → FI à Réaliste 8% | B51: Âge 53 (2045) | C51: $2,114,785 CAD
A52: → FI à Optimiste 10% | B52: Âge 51 (2043) | C52: $2,140,948 CAD
A54: 🛡️ RISQUES IDENTIFIÉS · Matrice conseiller
A55: RISQUE | B55: PROBABILITÉ | C55: IMPACT | D55: EXPOSITION PORTFOLIO | E55: MITIGATION
A56: Récession US / bear market | B56: Moyenne | C56: 🔴 Élevé | D56: 44.8% USD exposé | E56: DCA accéléré en dip (force psychologique documentée)
A57: Tarifs Trump / guerre commerciale | B57: Haute | C57: 🟡 Modéré | D57: SMH, AVGO, NVDA | E57: Semis = stratégiques, tarifs limités historiquement
A58: USD/CAD hausse | B58: Moyenne | C58: ✅ Positif | D58: Boost 44.8% USD | E58: Favorable pour toi actuellement
A59: Urgence personnelle sans HISA | B59: 🔴 Réelle | C59: 🔴 Critique | D59: Forcerait vente TFSA | E59: EQ Bank ce soir — risque éliminable en 20 min
A60: Concentration TD.TO >13% | B60: Faible | C60: 🟡 Modéré | D60: $11,337 T3 | E60: Diluer naturellement, ne plus acheter
A61: Absence de régime retraite | B61: Confirmée | C61: 🟡 Modéré | D61: Long terme | E61: Compense avec REER maximal — déjà en cours
A62: Biais timing contributions | B62: 🔴 Documenté | C62: 🟡 Modéré | D62: Réduction DCA efficace | E62: Automatiser $3,500/mois — action immédiate requise
A64: 📝 NOTE CONSEILLER · Évaluation globale S18
A65: SCORE GLOBAL | B65: 8.5→9.0 / 10 | C65: Toutes corrections rapport S18 appliquées · 29 corrections · Onglets dynamiques
A66: FORCE PRINCIPALE | B66: Discipline long terme | C66: T1 = 55%, philosophie FI claire, aucune vente panique documentée
A67: FAIBLESSE PRINCIPALE | B67: Exécution opérationnelle | C67: EQ Bank non ouvert depuis 3 sessions. Contributions non automatisées.
A68: AMÉLIORATION S14→S15 | B68: PLZ.UN+REI.UN TFSA vendus ✅ · SCHD $2K/mois ✅ · Rapport analyse complet ✅ · 29 corrections v46-S18 | C68: Deux actions majeures exécutées — momentum positif
A69: OBJECTIF S16 | B69: OBJECTIF S19 | C69: EQ Bank ouvert + $1,500 viré · Automatisation contributions · Scorecard titres T1
A70: MESSAGE DIRECT | B70: Tu as le meilleur plan possible. | C70: Revenu réel $7,950/mois · Dépenses $1,182 · Disponible $6,768 · Structuré $5,000 · Libre $1,768. EQ Bank $1,500/mois = $15K en 10 mois sans changer REER/FHSA/TFSA.

Sheet 📈 PORTEFEUILLE
B1: 📈 PORTEFEUILLE — TFSA · FHSA · REER
B2: 📈 PORTEFEUILLE · TFSA · FHSA · REER · 12 mars 2026
B3: Cellules jaunes = saisir manuellement · Taux USD/CAD depuis CONFIG!B3
B4: Taux USD/CAD → | C4: =CONFIG!B3 -> 1.3559 | D4: ← Taux lu depuis CONFIG!B3
B7: COMPTE | C7: VALEUR CAD | D7: VALEUR USD | E7: INVESTI CAD | F7: GAIN $CAD | G7: GAIN % | H7: NB POS. | I7: ROOM RESTANT | J7: STATUT
B8: TFSA | C8: =L44 -> 67855.03 | D8: =M44 -> 50044.273 | E8: =SUMPRODUCT((F15:F42="TFSA")*G15:G42*H15:H42) -> 48896.466 | F8: =N44 -> 18727.904 | G8: =IF(L44>0,N44/L44,0) -> 0.27599876 | H8: =COUNTIF(F15:F42,"TFSA") -> 28 | I8: =CONFIG!B6 -> 69600 | J8: =IF(C8/F10>=1,"ATTEINT","EN COURS") -> ATTEINT
B9: FHSA | C9: =L59 -> 14767.018 | D9: =M59 -> 10890.934 | E9: =SUMPRODUCT((F47:F57="FHSA")*G47:G57*H47:H57) -> 12199.675 | F9: =N59 -> 2552.2128 | G9: =IF(L59>0,N59/L59,0) -> 0.17283197 | H9: =COUNTIF(F47:F57,"FHSA") -> 11 | I9: =CONFIG!B7 -> 13700 | J9: =IF(C9/F11>=1,"ATTEINT","EN COURS") -> EN COURS
B10: REER | C10: =L68 -> 2764.1683 | D10: =M68 -> 2095.7125 | E10: =SUMPRODUCT((F60:F64="REER")*G60:G64*H60:H64) -> 1694.3566 | F10: =N68 -> 1091.44 | G10: =IF(L68>0,N68/L68,0) -> 0.39485295 | H10: =COUNTIF(F60:F64,"REER") -> 3 | I10: =CONFIG!B8 -> 37008 | J10: =IF(C10/F10>=1,"ATTEINT","EN COURS") -> ATTEINT
B11: TOTAL | C11: =L70 -> 85386.216 | D11: =M70 -> 63030.92 | E11: =E8+E9+E10 -> 62790.498 | F11: =N70 -> 22371.557 | G11: =IF(E11>0,F11/E11,0) -> 0.35628889 | H11: =H8+H9+H10 -> 42
B13: TICKER | C13: NOM COMPLET | D13: TYPE | E13: TIER | F13: CTE | G13: QTÉ | H13: PRIX MOY CAD | I13: PRIX ACT CAD | J13: PRIX ACT USD | K13: DEV | L13: VALEUR CAD | M13: VALEUR USD | N13: GAIN $CAD | O13: GAIN % | P13: % PORT. | Q13: ACTION
B14: 🟦 TFSA — Croissance long terme IA
B15: VFV.TO | C15: Vanguard S&P 500 | D15: ETF | E15: T1 | F15: TFSA | G15: 84 | H15: 119.9246 | I15: =CONFIG!G6 -> 161.8 | J15: =IFERROR(I15/C$4,0) -> 119.33033 | K15: CAD | L15: =IF(G15=0,"-",G15*I15) -> 13591.2 | M15: =IF(G15=0,"-",G15*J15) -> 10023.748 | N15: =IF(G15=0,"-",(I15-H15)*G15) -> 3517.5336 | O15: =IF(H15>0,(I15-H15)/H15,0) -> 0.34918107 | P15: =IF(AND(ISNUMBER(L15),L15>0),L15/L$70,0) -> 0.15917323 | Q15: ✅ Accumuler
B16: GOOG | C16: Alphabet | D16: Action | E16: T1 | F16: TFSA | G16: 6 | H16: 90.6059 | I16: =J16*$C$4 -> 408.74961 | J16: =CONFIG!G7 -> 301.46 | K16: USD | L16: =IF(G16=0,"-",G16*I16) -> 2452.4977 | M16: =IF(G16=0,"-",G16*J16) -> 1808.76 | N16: =IF(G16=0,"-",(I16-H16)*G16) -> 1908.8623 | O16: =IF(H16>0,(I16-H16)/H16,0) -> 3.5112914 | P16: =IF(AND(ISNUMBER(L16),L16>0),L16/L$70,0) -> 0.028722407 | Q16: ✅ Accumuler
B17: AVGO | C17: Broadcom | D17: Action | E17: T1 | F17: TFSA | G17: 16.5743 | H17: 342.1593 | I17: =J17*$C$4 -> 436.81674 | J17: =CONFIG!G8 -> 322.16 | K17: USD | L17: =IF(G17=0,"-",G17*I17) -> 7239.9318 | M17: =IF(G17=0,"-",G17*J17) -> 5339.5765 | N17: =IF(G17=0,"-",(I17-H17)*G17) -> 1568.8809 | O17: =IF(H17>0,(I17-H17)/H17,0) -> 0.27664729 | P17: =IF(AND(ISNUMBER(L17),L17>0),L17/L$70,0) -> 0.084790404 | Q17: ✅ Accumuler
B18: AMZN | C18: Amazon | D18: Action | E18: T1 | F18: TFSA | G18: 7.4817 | H18: 113.7377 | I18: =J18*$C$4 -> 281.57975 | J18: =CONFIG!G9 -> 207.67 | K18: USD | L18: =IF(G18=0,"-",G18*I18) -> 2106.6952 | M18: =IF(G18=0,"-",G18*J18) -> 1553.7246 | N18: =IF(G18=0,"-",(I18-H18)*G18) -> 1255.7439 | O18: =IF(H18>0,(I18-H18)/H18,0) -> 1.4756941 | P18: =IF(AND(ISNUMBER(L18),L18>0),L18/L$70,0) -> 0.024672545 | Q18: ✅ Accumuler
B19: SMH | C19: VanEck Semis | D19: ETF | E19: T1 | F19: TFSA | G19: 19.2266 | H19: 393.5653 | I19: =J19*$C$4 -> 525.18075 | J19: =CONFIG!G10 -> 387.33 | K19: USD | L19: =IF(G19=0,"-",G19*I19) -> 10097.44 | M19: =IF(G19=0,"-",G19*J19) -> 7447.039 | N19: =IF(G19=0,"-",(I19-H19)*G19) -> 2530.5176 | O19: =IF(H19>0,(I19-H19)/H19,0) -> 0.33441832 | P19: =IF(AND(ISNUMBER(L19),L19>0),L19/L$70,0) -> 0.11825609 | Q19: ✅ Accumuler
B20: META | C20: Meta Platforms | D20: Action | E20: T1 | F20: TFSA | G20: 1 | H20: 637.7698 | I20: =J20*$C$4 -> 832.12939 | J20: =CONFIG!G11 -> 613.71 | K20: USD | L20: =IF(G20=0,"-",G20*I20) -> 832.12939 | M20: =IF(G20=0,"-",G20*J20) -> 613.71 | N20: =IF(G20=0,"-",(I20-H20)*G20) -> 194.35959 | O20: =IF(H20>0,(I20-H20)/H20,0) -> 0.30474881 | P20: =IF(AND(ISNUMBER(L20),L20>0),L20/L$70,0) -> 0.0097454768 | Q20: ✅ Accumuler
B21: ENB.TO | C21: Enbridge | D21: Action | E21: T1 | F21: TFSA | G21: 9 | H21: 49.62 | I21: =CONFIG!G12 -> 74.28 | J21: =IFERROR(I21/C$4,0) -> 54.782801 | K21: CAD | L21: =IF(G21=0,"-",G21*I21) -> 668.52 | M21: =IF(G21=0,"-",G21*J21) -> 493.04521 | N21: =IF(G21=0,"-",(I21-H21)*G21) -> 221.94 | O21: =IF(H21>0,(I21-H21)/H21,0) -> 0.49697703 | P21: =IF(AND(ISNUMBER(L21),L21>0),L21/L$70,0) -> 0.0078293667 | Q21: ✅ Garder
B22: GEV | C22: GE Vernova | D22: Action | E22: T1 | F22: TFSA | G22: 2.4431 | H22: 831.9907 | I22: =J22*$C$4 -> 1091.5266 | J22: =CONFIG!G13 -> 805.02 | K22: USD | L22: =IF(G22=0,"-",G22*I22) -> 2666.7087 | M22: =IF(G22=0,"-",G22*J22) -> 1966.7444 | N22: =IF(G22=0,"-",(I22-H22)*G22) -> 634.0722 | O22: =IF(H22>0,(I22-H22)/H22,0) -> 0.3119457 | P22: =IF(AND(ISNUMBER(L22),L22>0),L22/L$70,0) -> 0.031231138 | Q22: ✅ Accumuler
B23: MSFT | C23: Microsoft | D23: Action | E23: T2 | F23: TFSA | G23: 2 | H23: 312.5938 | I23: =J23*$C$4 -> 536.32624 | J23: =CONFIG!G15 -> 395.55 | K23: USD | L23: =IF(G23=0,"-",G23*I23) -> 1072.6525 | M23: =IF(G23=0,"-",G23*J23) -> 791.1 | N23: =IF(G23=0,"-",(I23-H23)*G23) -> 447.46489 | O23: =IF(H23>0,(I23-H23)/H23,0) -> 0.71572899 | P23: =IF(AND(ISNUMBER(L23),L23>0),L23/L$70,0) -> 0.012562361 | Q23: ✅ Garder
B24: NVDA | C24: NVIDIA | D24: Action | E24: T2 | F24: TFSA | G24: 4 | H24: 128.59 | I24: =J24*$C$4 -> 244.40097 | J24: =CONFIG!G16 -> 180.25 | K24: USD | L24: =IF(G24=0,"-",G24*I24) -> 977.6039 | M24: =IF(G24=0,"-",G24*J24) -> 721 | N24: =IF(G24=0,"-",(I24-H24)*G24) -> 463.2439 | O24: =IF(H24>0,(I24-H24)/H24,0) -> 0.90062194 | P24: =IF(AND(ISNUMBER(L24),L24>0),L24/L$70,0) -> 0.0114492 | Q24: ✅ Garder
B25: TSLA | C25: Tesla | D25: Action | E25: T2 | F25: TFSA | G25: 1.8645 | H25: 303.5644 | I25: =J25*$C$4 -> 530.42808 | J25: =CONFIG!G17 -> 391.2 | K25: USD | L25: =IF(G25=0,"-",G25*I25) -> 988.98316 | M25: =IF(G25=0,"-",G25*J25) -> 729.3924 | N25: =IF(G25=0,"-",(I25-H25)*G25) -> 422.98733 | O25: =IF(H25>0,(I25-H25)/H25,0) -> 0.74733295 | P25: =IF(AND(ISNUMBER(L25),L25>0),L25/L$70,0) -> 0.011582468 | Q25: ✅ Garder
B26: QQQM | C26: Invesco Nasdaq100 | D26: ETF | E26: T2 | F26: TFSA | G26: 4.4515 | H26: 247.1068 | I26: =J26*$C$4 -> 331.44975 | J26: =CONFIG!G18 -> 244.45 | K26: USD | L26: =IF(G26=0,"-",G26*I26) -> 1475.4486 | M26: =IF(G26=0,"-",G26*J26) -> 1088.1692 | N26: =IF(G26=0,"-",(I26-H26)*G26) -> 375.45266 | O26: =IF(H26>0,(I26-H26)/H26,0) -> 0.34132187 | P26: =IF(AND(ISNUMBER(L26),L26>0),L26/L$70,0) -> 0.017279704 | Q26: ✅ Migration ZQQ ✅
B27: XEQT.TO | C27: iShares Core Eq | D27: ETF | E27: T2 | F27: TFSA | G27: 25 | H27: 39.97 | I27: =CONFIG!G19 -> 39.85 | J27: =IFERROR(I27/C$4,0) -> 29.390073 | K27: CAD | L27: =IF(G27=0,"-",G27*I27) -> 996.25 | M27: =IF(G27=0,"-",G27*J27) -> 734.75183 | N27: =IF(G27=0,"-",(I27-H27)*G27) -> -3 | O27: =IF(H27>0,(I27-H27)/H27,0) -> -0.0030022517 | P27: =IF(AND(ISNUMBER(L27),L27>0),L27/L$70,0) -> 0.011667574 | Q27: ✅ Migration ZEQT ✅
B28: SPGI | C28: S&P Global | D28: Action | E28: T2 | F28: TFSA | G28: 0.9996 | H28: 443.2458 | I28: =J28*$C$4 -> 572.85419 | J28: =CONFIG!G14 -> 422.49 | K28: USD | L28: =IF(G28=0,"-",G28*I28) -> 572.62505 | M28: =IF(G28=0,"-",G28*J28) -> 422.321 | N28: =IF(G28=0,"-",(I28-H28)*G28) -> 129.55655 | O28: =IF(H28>0,(I28-H28)/H28,0) -> 0.29240749 | P28: =IF(AND(ISNUMBER(L28),L28>0),L28/L$70,0) -> 0.0067062938 | Q28: ✅ Garder
B29: TD.TO | C29: TD Bank | D29: Action | E29: T3 | F29: TFSA | G29: 87 | H29: 79.8348 | I29: =CONFIG!G20 -> 128.05 | J29: =IFERROR(I29/C$4,0) -> 94.439118 | K29: CAD | L29: =IF(G29=0,"-",G29*I29) -> 11140.35 | M29: =IF(G29=0,"-",G29*J29) -> 8216.2033 | N29: =IF(G29=0,"-",(I29-H29)*G29) -> 4194.7224 | O29: =IF(H29>0,(I29-H29)/H29,0) -> 0.60393713 | P29: =IF(AND(ISNUMBER(L29),L29>0),L29/L$70,0) -> 0.13047012 | Q29: 🔵 Diluer — ne plus acheter
B30: ZLB.TO | C30: BMO Low Vol | D30: ETF | E30: T3 | F30: TFSA | G30: 37 | H30: 58.1416 | I30: =CONFIG!G21 -> 59.04 | J30: =IFERROR(I30/C$4,0) -> 43.543034 | K30: CAD | L30: =IF(G30=0,"-",G30*I30) -> 2184.48 | M30: =IF(G30=0,"-",G30*J30) -> 1611.0923 | N30: =IF(G30=0,"-",(I30-H30)*G30) -> 33.2408 | O30: =IF(H30>0,(I30-H30)/H30,0) -> 0.015451931 | P30: =IF(AND(ISNUMBER(L30),L30>0),L30/L$70,0) -> 0.02558352 | Q30: 🔵 Garder
B31: H.TO | C31: Hydro One | D31: Action | E31: T3 | F31: TFSA | G31: 22 | H31: 52.8663 | I31: =CONFIG!G22 -> 60.09 | J31: =IFERROR(I31/C$4,0) -> 44.317428 | K31: CAD | L31: =IF(G31=0,"-",G31*I31) -> 1321.98 | M31: =IF(G31=0,"-",G31*J31) -> 974.98341 | N31: =IF(G31=0,"-",(I31-H31)*G31) -> 158.9214 | O31: =IF(H31>0,(I31-H31)/H31,0) -> 0.13664092 | P31: =IF(AND(ISNUMBER(L31),L31>0),L31/L$70,0) -> 0.015482358 | Q31: 🔵 Garder
B32: T.TO | C32: TELUS | D32: Action | E32: T3 | F32: TFSA | G32: 32 | H32: 22.04 | I32: =CONFIG!G23 -> 18.01 | J32: =IFERROR(I32/C$4,0) -> 13.28269 | K32: CAD | L32: =IF(G32=0,"-",G32*I32) -> 576.32 | M32: =IF(G32=0,"-",G32*J32) -> 425.04609 | N32: =IF(G32=0,"-",(I32-H32)*G32) -> -128.96 | O32: =IF(H32>0,(I32-H32)/H32,0) -> -0.18284936 | P32: =IF(AND(ISNUMBER(L32),L32>0),L32/L$70,0) -> 0.0067495672 | Q32: 👀 Surveiller div Q3
B33: QTUM | C33: Defiance Quantum | D33: ETF | E33: T3 | F33: TFSA | G33: 5 | H33: 120.81 | I33: =J33*$C$4 -> 148.29478 | J33: =CONFIG!G24 -> 109.37 | K33: USD | L33: =IF(G33=0,"-",G33*I33) -> 741.47392 | M33: =IF(G33=0,"-",G33*J33) -> 546.85 | N33: =IF(G33=0,"-",(I33-H33)*G33) -> 137.42391 | O33: =IF(H33>0,(I33-H33)/H33,0) -> 0.2275042 | P33: =IF(AND(ISNUMBER(L33),L33>0),L33/L$70,0) -> 0.0086837659 | Q33: 🔵 Garder (max 5)
B34: HURA.TO | C34: Global X Uranium | D34: ETF | E34: T3 | F34: TFSA | G34: 6 | H34: 55.25 | I34: =CONFIG!G25 -> 57.54 | J34: =IFERROR(I34/C$4,0) -> 42.436758 | K34: CAD | L34: =IF(G34=0,"-",G34*I34) -> 345.24 | M34: =IF(G34=0,"-",G34*J34) -> 254.62055 | N34: =IF(G34=0,"-",(I34-H34)*G34) -> 13.74 | O34: =IF(H34>0,(I34-H34)/H34,0) -> 0.041447964 | P34: =IF(AND(ISNUMBER(L34),L34>0),L34/L$70,0) -> 0.0040432755 | Q34: 🔵 Garder
B35: REI.UN.TO | C35: RioCan REIT | D35: REIT | E35: T4 | F35: TFSA | G35: 0 | H35: 0 | I35: =CONFIG!G26 -> 19.02 | J35: =IFERROR(I35/C$4,0) -> 14.027583 | K35: CAD | L35: =IF(G35=0,"-",G35*I35) -> - | M35: =IF(G35=0,"-",G35*J35) -> - | N35: =IF(G35=0,"-",(I35-H35)*G35) -> - | O35: =IF(H35>0,(I35-H35)/H35,0) -> 0 | P35: =IF(AND(ISNUMBER(L35),L35>0),L35/L$70,0) -> 0 | Q35: 🔄 Diluer
B36: PLZ.UN.TO | C36: Plaza Retail | D36: REIT | E36: T4 | F36: TFSA | G36: 0 | H36: 0 | I36: =CONFIG!G27 -> 4.26 | J36: =IFERROR(I36/C$4,0) -> 3.1418246 | K36: CAD | L36: =IF(G36=0,"-",G36*I36) -> - | M36: =IF(G36=0,"-",G36*J36) -> - | N36: =IF(G36=0,"-",(I36-H36)*G36) -> - | O36: =IF(H36>0,(I36-H36)/H36,0) -> 0 | P36: =IF(AND(ISNUMBER(L36),L36>0),L36/L$70,0) -> 0 | Q36: 🔄 Diluer
B37: XEI.TO | C37: iShares High Div | D37: ETF | E37: T4 | F37: TFSA | G37: 51 | H37: 30.6811 | I37: =CONFIG!G28 -> 35.89 | J37: =IFERROR(I37/C$4,0) -> 26.469504 | K37: CAD | L37: =IF(G37=0,"-",G37*I37) -> 1830.39 | M37: =IF(G37=0,"-",G37*J37) -> 1349.9447 | N37: =IF(G37=0,"-",(I37-H37)*G37) -> 265.6539 | O37: =IF(H37>0,(I37-H37)/H37,0) -> 0.16977553 | P37: =IF(AND(ISNUMBER(L37),L37>0),L37/L$70,0) -> 0.021436598 | Q37: 🔄 Diluer
B38: SRU.UN.TO | C38: SmartCentres | D38: REIT | E38: T4 | F38: TFSA | G38: 57 | H38: 25.2543 | I38: =CONFIG!G29 -> 26.84 | J38: =IFERROR(I38/C$4,0) -> 19.79497 | K38: CAD | L38: =IF(G38=0,"-",G38*I38) -> 1529.88 | M38: =IF(G38=0,"-",G38*J38) -> 1128.3133 | N38: =IF(G38=0,"-",(I38-H38)*G38) -> 90.3849 | O38: =IF(H38>0,(I38-H38)/H38,0) -> 0.062789307 | P38: =IF(AND(ISNUMBER(L38),L38>0),L38/L$70,0) -> 0.017917178 | Q38: 🔄 Diluer
B39: XIC.TO | C39: iShares TSX | D39: ETF | E39: T4 | F39: TFSA | G39: 21 | H39: 40.4066 | I39: =CONFIG!G30 -> 52.08 | J39: =IFERROR(I39/C$4,0) -> 38.409912 | K39: CAD | L39: =IF(G39=0,"-",G39*I39) -> 1093.68 | M39: =IF(G39=0,"-",G39*J39) -> 806.60816 | N39: =IF(G39=0,"-",(I39-H39)*G39) -> 245.1414 | O39: =IF(H39>0,(I39-H39)/H39,0) -> 0.28889835 | P39: =IF(AND(ISNUMBER(L39),L39>0),L39/L$70,0) -> 0.012808625 | Q39: 🔄 Diluer
B40: ZRE.TO | C40: BMO Equal REITs | D40: ETF | E40: T4 | F40: TFSA | G40: 19 | H40: 20.83 | I40: =CONFIG!G31 -> 22.33 | J40: =IFERROR(I40/C$4,0) -> 16.468766 | K40: CAD | L40: =IF(G40=0,"-",G40*I40) -> 424.27 | M40: =IF(G40=0,"-",G40*J40) -> 312.90656 | N40: =IF(G40=0,"-",(I40-H40)*G40) -> 28.5 | O40: =IF(H40>0,(I40-H40)/H40,0) -> 0.072011522 | P40: =IF(AND(ISNUMBER(L40),L40>0),L40/L$70,0) -> 0.0049688348 | Q40: 🔄 Diluer
B41: MFC.TO | C41: Manulife | D41: Action | E41: T4 | F41: TFSA | G41: 8 | H41: 51.7 | I41: =CONFIG!G32 -> 45.9 | J41: =IFERROR(I41/C$4,0) -> 33.852054 | K41: CAD | L41: =IF(G41=0,"-",G41*I41) -> 367.2 | M41: =IF(G41=0,"-",G41*J41) -> 270.81643 | N41: =IF(G41=0,"-",(I41-H41)*G41) -> -46.4 | O41: =IF(H41>0,(I41-H41)/H41,0) -> -0.11218569 | P41: =IF(AND(ISNUMBER(L41),L41>0),L41/L$70,0) -> 0.0043004599 | Q41: 🔄 Diluer
B42: VDU.TO | C42: Vanguard Dev | D42: ETF | E42: T4 | F42: TFSA | G42: 6 | H42: 43.75 | I42: =CONFIG!G33 -> 55.07 | J42: =IFERROR(I42/C$4,0) -> 40.61509 | K42: CAD | L42: =IF(G42=0,"-",G42*I42) -> 330.42 | M42: =IF(G42=0,"-",G42*J42) -> 243.69054 | N42: =IF(G42=0,"-",(I42-H42)*G42) -> 67.92 | O42: =IF(H42>0,(I42-H42)/H42,0) -> 0.25874286 | P42: =IF(AND(ISNUMBER(L42),L42>0),L42/L$70,0) -> 0.0038697112 | Q42: 🔄 Diluer
B43: 💵 CASH TFSA | L43: =CONFIG!B37 -> 230.66 | M43: =CONFIG!B37/CONFIG!B3 -> 170.11579 | N43: 0 | O43: 0
B44: SOUS-TOTAL TFSA | L44: =SUM(L15:L43) -> 67855.03 | M44: =SUM(M15:M43) -> 50044.273 | N44: =SUM(N15:N43) -> 18727.904 | O44: =IF(L43>0,N43/L43,0) -> 0
B46: 🟩 FHSA — Maison 2028
B47: VFV.TO | C47: Vanguard S&P 500 | D47: ETF | E47: T1 | F47: FHSA | G47: 16 | H47: 157.3812 | I47: =CONFIG!G6 -> 161.8 | J47: =IFERROR(I47/C$4,0) -> 119.33033 | K47: CAD | L47: =IF(G47=0,"-",G47*I47) -> 2588.8 | M47: =IF(G47=0,"-",G47*J47) -> 1909.2853 | N47: =IF(G47=0,"-",(I47-H47)*G47) -> 70.7008 | O47: =IF(H46>0,(I46-H46)/H46,0) -> 0 | P47: =IF(AND(ISNUMBER(L46),L46>0),L46/L$70,0) -> 0 | Q47: ✅ Achat auto $2,500/mois
B48: AMZN | C48: Amazon | D48: Action | E48: T1 | F48: FHSA | G48: 7 | H48: 154.9418 | I48: =J48*$C$4 -> 281.57975 | J48: =CONFIG!G9 -> 207.67 | K48: USD | L48: =IF(G48=0,"-",G48*I48) -> 1971.0583 | M48: =IF(G48=0,"-",G48*J48) -> 1453.69 | N48: =IF(G48=0,"-",(I48-H48)*G48) -> 886.46567 | O48: =IF(H47>0,(I47-H47)/H47,0) -> 0.028077051 | P48: =IF(AND(ISNUMBER(L47),L47>0),L47/L$70,0) -> 0.030318711 | Q48: ✅ Garder
B49: QQQM | C49: Invesco Nasdaq100 | D49: ETF | E49: T2 | F49: FHSA | G49: 5.311 | H49: 247.4064 | I49: =J49*$C$4 -> 331.44975 | J49: =CONFIG!G18 -> 244.45 | K49: USD | L49: =IF(G49=0,"-",G49*I49) -> 1760.3296 | M49: =IF(G49=0,"-",G49*J49) -> 1298.274 | N49: =IF(G49=0,"-",(I49-H49)*G49) -> 446.35426 | O49: =IF(H48>0,(I48-H48)/H48,0) -> 0.81732594 | P49: =IF(AND(ISNUMBER(L48),L48>0),L48/L$70,0) -> 0.023084033 | Q49: ✅ Migration ZQQ ✅
B50: XEQT.TO | C50: iShares Core Eq | D50: ETF | E50: T2 | F50: FHSA | G50: 15 | H50: 40.06 | I50: =CONFIG!G19 -> 39.85 | J50: =IFERROR(I50/C$4,0) -> 29.390073 | K50: CAD | L50: =IF(G50=0,"-",G50*I50) -> 597.75 | M50: =IF(G50=0,"-",G50*J50) -> 440.8511 | N50: =IF(G50=0,"-",(I50-H50)*G50) -> -3.15 | O50: =IF(H49>0,(I49-H49)/H49,0) -> 0.33969758 | P50: =IF(AND(ISNUMBER(L49),L49>0),L49/L$70,0) -> 0.020616087 | Q50: ✅ Migration ZEQT ✅
B51: TD.TO | C51: TD Bank | D51: Action | E51: T3 | F51: FHSA | G51: 15 | H51: 82.29 | I51: =CONFIG!G20 -> 128.05 | J51: =IFERROR(I51/C$4,0) -> 94.439118 | K51: CAD | L51: =IF(G51=0,"-",G51*I51) -> 1920.75 | M51: =IF(G51=0,"-",G51*J51) -> 1416.5868 | N51: =IF(G51=0,"-",(I51-H51)*G51) -> 686.4 | O51: =IF(H50>0,(I50-H50)/H50,0) -> -0.0052421368 | P51: =IF(AND(ISNUMBER(L50),L50>0),L50/L$70,0) -> 0.0070005444 | Q51: 🔵 Garder
B52: H.TO | C52: Hydro One | D52: Action | E52: T3 | F52: FHSA | G52: 10 | H52: 51.78 | I52: =CONFIG!G22 -> 60.09 | J52: =IFERROR(I52/C$4,0) -> 44.317428 | K52: CAD | L52: =IF(G52=0,"-",G52*I52) -> 600.9 | M52: =IF(G52=0,"-",G52*J52) -> 443.17428 | N52: =IF(G52=0,"-",(I52-H52)*G52) -> 83.1 | O52: =IF(H51>0,(I51-H51)/H51,0) -> 0.55608215 | P52: =IF(AND(ISNUMBER(L51),L51>0),L51/L$70,0) -> 0.022494849 | Q52: 🔵 Garder
B53: ZLB.TO | C53: BMO Low Vol | D53: ETF | E53: T3 | F53: FHSA | G53: 3 | H53: 59.0666 | I53: =CONFIG!G21 -> 59.04 | J53: =IFERROR(I53/C$4,0) -> 43.543034 | K53: CAD | L53: =IF(G53=0,"-",G53*I53) -> 177.12 | M53: =IF(G53=0,"-",G53*J53) -> 130.6291 | N53: =IF(G53=0,"-",(I53-H53)*G53) -> -0.0798 | O53: =IF(H52>0,(I52-H52)/H52,0) -> 0.16048667 | P53: =IF(AND(ISNUMBER(L52),L52>0),L52/L$70,0) -> 0.0070374356 | Q53: 🔵 Garder
B54: SRU.UN.TO | C54: SmartCentres | D54: REIT | E54: T4 | F54: FHSA | G54: 63 | H54: 23.61 | I54: =CONFIG!G29 -> 26.84 | J54: =IFERROR(I54/C$4,0) -> 19.79497 | K54: CAD | L54: =IF(G54=0,"-",G54*I54) -> 1690.92 | M54: =IF(G54=0,"-",G54*J54) -> 1247.0831 | N54: =IF(G54=0,"-",(I54-H54)*G54) -> 203.49 | O54: =IF(H53>0,(I53-H53)/H53,0) -> -0.00045033911 | P54: =IF(AND(ISNUMBER(L53),L53>0),L53/L$70,0) -> 0.0020743395 | Q54: 🔄 Diluer
B55: REI.UN.TO | C55: RioCan REIT | D55: REIT | E55: T4 | F55: FHSA | G55: 80 | H55: 18.73 | I55: =CONFIG!G26 -> 19.02 | J55: =IFERROR(I55/C$4,0) -> 14.027583 | K55: CAD | L55: =IF(G55=0,"-",G55*I55) -> 1521.6 | M55: =IF(G55=0,"-",G55*J55) -> 1122.2067 | N55: =IF(G55=0,"-",(I55-H55)*G55) -> 23.2 | O55: =IF(H54>0,(I54-H54)/H54,0) -> 0.13680644 | P55: =IF(AND(ISNUMBER(L54),L54>0),L54/L$70,0) -> 0.019803196 | Q55: 🔄 Diluer
B56: XIC.TO | C56: iShares TSX | D56: ETF | E56: T4 | F56: FHSA | G56: 19 | H56: 48.3705 | I56: =CONFIG!G30 -> 52.08 | J56: =IFERROR(I56/C$4,0) -> 38.409912 | K56: CAD | L56: =IF(G56=0,"-",G56*I56) -> 989.52 | M56: =IF(G56=0,"-",G56*J56) -> 729.78833 | N56: =IF(G56=0,"-",(I56-H56)*G56) -> 70.4805 | O56: =IF(H55>0,(I55-H55)/H55,0) -> 0.015483182 | P56: =IF(AND(ISNUMBER(L55),L55>0),L55/L$70,0) -> 0.017820206 | Q56: 🔄 Diluer
B57: XEI.TO | C57: iShares High Div | D57: ETF | E57: T4 | F57: FHSA | G57: 26 | H57: 32.6111 | I57: =CONFIG!G28 -> 35.89 | J57: =IFERROR(I57/C$4,0) -> 26.469504 | K57: CAD | L57: =IF(G57=0,"-",G57*I57) -> 933.14 | M57: =IF(G57=0,"-",G57*J57) -> 688.20709 | N57: =IF(G57=0,"-",(I57-H57)*G57) -> 85.2514 | O57: =IF(H56>0,(I56-H56)/H56,0) -> 0.076689304 | P57: =IF(AND(ISNUMBER(L56),L56>0),L56/L$70,0) -> 0.011588756 | Q57: 🔄 Migration VDY ✅
B58: 💵 CASH FHSA | C58: Cash CAD | D58: Cash | E58: — | F58: FHSA | G58: 1 | H58: 0 | I58: =CONFIG!B38 -> 15.13 | K58: CAD | L58: =CONFIG!B38 -> 15.13 | M58: =CONFIG!B38/CONFIG!B3 -> 11.15864 | N58: 0 | O58: 0
B59: SOUS-TOTAL FHSA | L59: =SUM(L47:L58) -> 14767.018 | M59: =SUM(M47:M58) -> 10890.934 | N59: =SUM(N47:N58) -> 2552.2128 | O59: =IF(L59>0,N59/L59,0) -> 0.17283197
B61: 🟧 REER — Retraite + Snowball
B62: SCHD | C62: Schwab US Div | D62: ETF | E62: T1 | F62: REER | G62: 64.3053 | H62: 25.5008 | I62: =J62*$C$4 -> 41.76172 | J62: =CONFIG!G34 -> 30.8 | K62: USD | L62: =IF(G62=0,"-",G62*I62) -> 2685.4999 | M62: =IF(G62=0,"-",G62*J62) -> 1980.6032 | N62: =IF(G62=0,"-",(I62-H62)*G62) -> 1045.6633 | O62: =IF(H60>0,(I60-H60)/H60,0) -> 0 | P62: =IF(AND(ISNUMBER(L60),L60>0),L60/L$70,0) -> 0 | Q62: ✅ REER débloqué · accumuler $2,000/mois · snowball ARC +$1,060
B63: JEPI | C63: JPMorgan Income | D63: ETF | E63: T2 | F63: REER | G63: 1 | H63: 54.52 | I63: =J63*$C$4 -> 77.408331 | J63: =CONFIG!G35 -> 57.09 | K63: USD | L63: =IF(G63=0,"-",G63*I63) -> 77.408331 | M63: =IF(G63=0,"-",G63*J63) -> 57.09 | N63: =IF(G63=0,"-",(I63-H63)*G63) -> 22.888331 | O63: =IF(H61>0,(I61-H61)/H61,0) -> 0 | P63: =IF(AND(ISNUMBER(L61),L61>0),L61/L$70,0) -> 0 | Q63: ✅ Garder
B64: XEI.TO | C64: iShares High Div | D64: ETF | E64: T3 | F64: REER | G64: 0 | H64: 24.65 | I64: =CONFIG!G28 -> 35.89 | J64: =IFERROR(I64/C$4,0) -> 26.469504 | K64: CAD | L64: =IF(G64=0,"-",G64*I64) -> - | M64: =IF(G64=0,"-",G64*J64) -> - | N64: =IF(G64=0,"-",(I64-H64)*G64) -> - | O64: =IF(H62>0,(I62-H62)/H62,0) -> 0.63766313 | P64: =IF(AND(ISNUMBER(L62),L62>0),L62/L$70,0) -> 0.031451211 | Q64: VENDU ✅
B65: ZEQT.TO | L65: =IF(G65=0,"-",G65*I65) -> - | M65: =IF(G63=0,"-",G63*J63) -> 57.09 | N65: =IF(G63=0,"-",(I63-H63)*G63) -> 22.888331 | O65: =IF(H63>0,(I63-H63)/H63,0) -> 0.41981532 | P65: =IF(AND(ISNUMBER(L63),L63>0),L63/L$70,0) -> 0.00090656706 | Q65: VENDU ✅
B66: XRE.TO | C66: iShares REIT | D66: ETF | E66: T4 | F66: REER | G66: 0 | H66: 15.86 | I66: 0 | J66: =IFERROR(I64/$C$4,0) -> 26.469504 | K66: CAD | L66: =IF(G66=0,"-",G66*I66) -> - | M66: =IF(G64=0,"-",G64*J64) -> - | N66: =IF(G64=0,"-",(I64-H64)*G64) -> - | O66: =IF(H64>0,(I64-H64)/H64,0) -> 0.45598377 | P66: =IF(AND(ISNUMBER(L64),L64>0),L64/L$70,0) -> 0 | Q66: VENDU ✅
B67: 💵 CASH REER | C67: Cash USD (CAD) | D67: Cash | E67: — | F67: REER | G67: 1 | H67: 0 | I67: =CONFIG!B39 -> 1.26 | K67: CAD | L67: =CONFIG!B39 -> 1.26 | M67: =CONFIG!B39/CONFIG!B3 -> 0.92927207 | N67: 0 | O67: 0
B68: SOUS-TOTAL REER | L68: =SUM(L62:L67) -> 2764.1683 | M68: =SUM(M62:M67) -> 2095.7125 | N68: =SUM(N62:N67) -> 1091.44 | O68: =IF(L68>0,N68/L68,0) -> 0.39485295
B70: ◼ GRAND TOTAL · TFSA + FHSA + REER | L70: =L44+L59+L68 -> 85386.216 | M70: =M44+M59+M68 -> 63030.92 | N70: =N44+N59+N68 -> 22371.557 | O70: =IF(L70>0,N70/L70,0) -> 0.26200431
B73: ΣTIER — Résumé par niveau de conviction | L73: =SUMIF(E14:E64,"T1",L14:L64) -> 46900.481 | M73: =SUMIF(E14:E64,"T1",M14:M64) -> 34589.926
B74: ΣT2 | L74: =SUMIF(E14:E64,"T2",L14:L64) -> 8519.0512 | M74: =SUMIF(E14:E64,"T2",M14:M64) -> 6282.9495
B75: ΣT3 | L75: =SUMIF(E14:E64,"T3",L14:L64) -> 19008.614 | M75: =SUMIF(E14:E64,"T3",M14:M64) -> 14019.186
B76: ΣT4 | L76: =SUMIF(E14:E64,"T4",L14:L64) -> 10711.02 | M76: =SUMIF(E14:E64,"T4",M14:M64) -> 7899.5649
B77: ΣT5 | L77: =SUMIF(E14:E64,"T5",L14:L64) -> 0 | M77: =SUMIF(E14:E64,"T5",M14:M64) -> 0

Sheet 🔍 ANALYSE TRIABLE
B1: 🔍 ANALYSE TRIABLE — Toutes les positions consolidées
B2: 🔍 ANALYSE TRIABLE · Recherche 9 mars 2026 · Cliquer ▼ pour trier/filtrer
B3: Sources: stockanalysis · koyfin · stockevents · digrin · yahoo finance · 9 mars 2026
B5: Taux USD/CAD → | C5: =CONFIG!$B$3 -> 1.3559 | D5: ← modifier ici (se propage partout)
B6: ='📈 PORTEFEUILLE'!L67 -> 1.26 | C6: ='📈 PORTEFEUILLE'!M67 -> 0.92927207 | D6: ='📈 PORTEFEUILLE'!N67 -> 0 | E6: ='📈 PORTEFEUILLE'!O67 -> 0 | F6: =IFERROR(('📈 PORTEFEUILLE'!L70+'📈 PORTEFEUILLE'!L71)/'📈 PORTEFEUILLE'!L67,0) -> 67766.838 | G6: =IFERROR(SUMPRODUCT(L8:L48,R8:R48)/SUM(L8:L48),0) -> 1.3310582 | H6: =IF(G6>1.4,"⚠️ BETA ÉLEVÉ",IF(G6>1.2,"🟡 MODÉRÉ","✅ BETA OK")) -> 🟡 MODÉRÉ
B7: TICKER | C7: NOM | D7: TYPE | E7: TIER | F7: CTE | G7: QTÉ | H7: PRIX MOY | I7: PRIX ACT CAD | J7: PRIX ACT USD | K7: DEV | L7: VALEUR CAD | M7: GAIN $ | N7: GAIN % | O7: % PORT. | P7: YIELD | Q7: DIV CAD/AN | R7: BETA | S7: EXPO IA% | T7: OBJ. CAD | U7: DERNIER ACH. | V7: ACTION / SIGNAL | W7: CORE / SATELLITE | X7: TAG (formule) | Y7: IS_CORE | Z7: IS_CAN_REIT | AB7: 🤖 EXPOSITION IA % | AC7: P/E RATIO | AD7: DATE ACHAT | AE7: PRIX CIBLE CAD | AF7: PROCHAIN EARNINGS | AG7: POTENTIEL %
B8: VFV.TO | C8: Vanguard S&P 500 | D8: ETF | E8: T1 | F8: 84 | G8: 119.9246 | H8: 119.9246 | I8: =IFERROR(VLOOKUP(B8,CONFIG!$F$6:$G$35,2,0),0) -> 161.8 | J8: =IFERROR(I8/CONFIG!B3,0) -> 119.33033 | K8: CAD | L8: =IF(G8>0,G8*I8,0) -> 19403.8 | M8: =IF(H8>0,(I8-H8)*G8,0) -> 5021.8906 | N8: =IF(H8>0,(I8-H8)/H8,0) -> 0.34918107 | O8: =IF(L8>0,L8/SUM(L8:L48),0) -> 0.0069005781 | P8: 0.0092 | Q8: =IF(G8>0,G8*I8*P8,0) -> 178.51496 | R8: 1 | S8: 0.3 | T8: 20000 | U8: 2026-03-09 | V8: ✅ Accumuler — FHSA auto $2,500/mois | W8: Core 🌍 | X8: ETF | Y8: 1 | Z8: 0 | AB8: 0.35 | AC8: 22.5 | AD8: 2026-03-09 | AE8: $185 | AF8: — | AG8: =IFERROR((185-I8)/I8,0) -> 0.1433869
B9: GOOG | C9: Alphabet | D9: Action | E9: T1 | F9: 6 | G9: 90.6059 | H9: 90.6059 | I9: =IFERROR(J9*CONFIG!B3,0) -> 408.74961 | J9: =IFERROR(VLOOKUP(B9,CONFIG!$F$6:$G$35,2,0),0) -> 301.46 | K9: USD | L9: =IF(G9>0,G9*I9,0) -> 37035.127 | M9: =IF(H9>0,(I9-H9)*G9,0) -> 28825.698 | N9: =IF(H9>0,(I9-H9)/H9,0) -> 3.5112914 | O9: =IF(L9>0,L9/SUM(L8:L48),0) -> 0.013170811 | P9: 0.005 | Q9: =IF(G9>0,G9*I9*P9,0) -> 185.17563 | R9: 1.06 | S9: 0.85 | T9: 5000 | U9: 2025 | V9: ✅ Garder — +232%, ne pas vendre | W9: Core 🚀 | X9: GROWTH | Y9: 1 | Z9: 0 | AB9: 0.9 | AC9: 21.0 | AD9: 2025 | AE9: $400 | AF9: Apr 2026 | AG9: =IFERROR((400-I9)/I9,0) -> -0.021405804
B10: AVGO | C10: Broadcom | D10: Action | E10: T1 | F10: 16.5743 | G10: 342.1593 | H10: 342.1593 | I10: =IFERROR(J10*CONFIG!B3,0) -> 436.81674 | J10: =IFERROR(VLOOKUP(B10,CONFIG!$F$6:$G$35,2,0),0) -> 322.16 | K10: USD | L10: =IF(G10>0,G10*I10,0) -> 149460.91 | M10: =IF(H10>0,(I10-H10)*G10,0) -> 32387.925 | N10: =IF(H10>0,(I10-H10)/H10,0) -> 0.27664729 | O10: =IF(L10>0,L10/SUM(L8:L48),0) -> 0.053152819 | P10: 0.0079 | Q10: =IF(G10>0,G10*I10*P10,0) -> 1180.7412 | R10: 1.3 | S10: 0.9 | T10: 10000 | U10: 2026-03-09 | V10: ✅ Accumuler — IA custom chips T1 | W10: Core 🚀 | X10: GROWTH | Y10: 1 | Z10: 0 | AB10: 1 | AC10: 35.0 | AD10: 2026-03-09 | AE10: $450 | AF10: Jun 2026 | AG10: =IFERROR((450-I10)/I10,0) -> 0.03018029
B11: AMZN | C11: Amazon | D11: Action | E11: T1 | F11: 7.4817 | G11: 113.7377 | H11: 113.7377 | I11: =IFERROR(J11*CONFIG!B3,0) -> 281.57975 | J11: =IFERROR(VLOOKUP(B11,CONFIG!$F$6:$G$35,2,0),0) -> 207.67 | K11: USD | L11: =IF(G11>0,G11*I11,0) -> 32026.233 | M11: =IF(H11>0,(I11-H11)*G11,0) -> 19089.969 | N11: =IF(H11>0,(I11-H11)/H11,0) -> 1.4756941 | O11: =IF(L11>0,L11/SUM(L8:L48),0) -> 0.011389497 | P11: 0.001 | Q11: =IF(G11>0,G11*I11*P11,0) -> 32.026233 | R11: 1.22 | S11: 0.7 | T11: 4000 | U11: 2025 | V11: ✅ Garder — AWS cloud IA | W11: Core 🚀 | X11: GROWTH | Y11: 1 | Z11: 0 | AB11: 0.7 | AC11: 40.0 | AD11: 2025 | AE11: $280 | AF11: May 2026 | AG11: =IFERROR((280-I11)/I11,0) -> -0.0056103217
B12: SMH | C12: VanEck Semis | D12: ETF | E12: T1 | F12: 19.2266 | G12: 393.5653 | H12: 393.5653 | I12: =IFERROR(J12*CONFIG!B3,0) -> 525.18075 | J12: =IFERROR(VLOOKUP(B12,CONFIG!$F$6:$G$35,2,0),0) -> 387.33 | K12: USD | L12: =IF(G12>0,G12*I12,0) -> 206692.92 | M12: =IF(H12>0,(I12-H12)*G12,0) -> 51799.273 | N12: =IF(H12>0,(I12-H12)/H12,0) -> 0.33441832 | O12: =IF(L12>0,L12/SUM(L8:L48),0) -> 0.073506251 | P12: 0.007 | Q12: =IF(G12>0,G12*I12*P12,0) -> 1446.8504 | R12: 1.55 | S12: 0.95 | T12: 8000 | U12: 2026-03-09 | V12: ✅ Accumuler — diversif semis IA | W12: Core 🌍 | X12: ETF | Y12: 1 | Z12: 0 | AB12: 1 | AC12: 28.0 | AD12: 2026-03-09 | AE12: $500 | AF12: — | AG12: =IFERROR((500-I12)/I12,0) -> -0.04794682
B13: META | C13: Meta Platforms | D13: Action | E13: T1 | F13: 1 | G13: 637.7698 | H13: 637.7698 | I13: =IFERROR(J13*CONFIG!B3,0) -> 832.12939 | J13: =IFERROR(VLOOKUP(B13,CONFIG!$F$6:$G$35,2,0),0) -> 613.71 | K13: USD | L13: =IF(G13>0,G13*I13,0) -> 530706.99 | M13: =IF(H13>0,(I13-H13)*G13,0) -> 123956.68 | N13: =IF(H13>0,(I13-H13)/H13,0) -> 0.30474881 | O13: =IF(L13>0,L13/SUM(L8:L48),0) -> 0.18873545 | P13: 0.0038 | Q13: =IF(G13>0,G13*I13*P13,0) -> 2016.6866 | R13: 1.25 | S13: 0.8 | T13: 3000 | U13: 2026-03-09 | V13: ⭐ Surveiller — Earnings 28 avr | W13: Core 🚀 | X13: GROWTH | Y13: 1 | Z13: 0 | AB13: 0.8 | AC13: 28.5 | AD13: 2026-03-09 | AE13: $800 | AF13: 28 avr 2026 | AG13: =IFERROR((800-I13)/I13,0) -> -0.038611049
B14: ENB.TO | C14: Enbridge | D14: Action | E14: T1 | F14: 9 | G14: 49.62 | H14: 49.62 | I14: =IFERROR(VLOOKUP(B14,CONFIG!$F$6:$G$35,2,0),0) -> 74.28 | J14: =IFERROR(I14/CONFIG!B3,0) -> 54.782801 | K14: CAD | L14: =IF(G14>0,G14*I14,0) -> 3685.7736 | M14: =IF(H14>0,(I14-H14)*G14,0) -> 1223.6292 | N14: =IF(H14>0,(I14-H14)/H14,0) -> 0.49697703 | O14: =IF(L14>0,L14/SUM(L8:L48),0) -> 0.0013107725 | P14: 0.0535 | Q14: =IF(G14>0,G14*I14*P14,0) -> 197.18889 | R14: 0.65 | S14: 0.05 | T14: 2000 | U14: 2025 | V14: ✅ Garder — 30 ans div, faible beta | W14: Core 🇨🇦 | X14: CAN | Y14: 1 | Z14: 0 | AB14: 0.2 | AC14: 18.0 | AD14: 2025 | AE14: $80 | AF14: Aug 2026 | AG14: =IFERROR((80-I14)/I14,0) -> 0.077005924
B15: GEV | C15: GE Vernova | D15: Action | E15: T1 | F15: 2.4431 | G15: 831.9907 | H15: 831.9907 | I15: =IFERROR(J15*CONFIG!B3,0) -> 1091.5266 | J15: =IFERROR(VLOOKUP(B15,CONFIG!$F$6:$G$35,2,0),0) -> 805.02 | K15: USD | L15: =IF(G15>0,G15*I15,0) -> 908139.99 | M15: =IF(H15>0,(I15-H15)*G15,0) -> 215931.47 | N15: =IF(H15>0,(I15-H15)/H15,0) -> 0.3119457 | O15: =IF(L15>0,L15/SUM(L8:L48),0) -> 0.32296204 | P15: 0.002 | Q15: =IF(G15>0,G15*I15*P15,0) -> 1816.28 | R15: 1.45 | S15: 0.6 | T15: 3000 | U15: 2026-03-09 | V15: ⭐ Surveiller — infra data centers | W15: Core 🔋 | X15: INFRA | Y15: 1 | Z15: 0 | AB15: 0.9 | AC15: 55.0 | AD15: 2026-03-09 | AE15: $1000 | AF15: May 2026 | AG15: =IFERROR((1000-I15)/I15,0) -> -0.083851934
B16: MSFT | C16: Microsoft | D16: Action | E16: T2 | F16: 2 | G16: 312.5938 | H16: 312.5938 | I16: =IFERROR(J16*CONFIG!B3,0) -> 536.32624 | J16: =IFERROR(VLOOKUP(B16,CONFIG!$F$6:$G$35,2,0),0) -> 395.55 | K16: USD | L16: =IF(G16>0,G16*I16,0) -> 167652.26 | M16: =IF(H16>0,(I16-H16)*G16,0) -> 69937.375 | N16: =IF(H16>0,(I16-H16)/H16,0) -> 0.71572899 | O16: =IF(L16>0,L16/SUM(L8:L48),0) -> 0.059622212 | P16: 0.0082 | Q16: =IF(G16>0,G16*I16*P16,0) -> 1374.7485 | R16: 0.9 | S16: 0.85 | T16: 3000 | U16: 2025 | V16: ✅ Garder — Copilot + Azure stable | W16: Core 🚀 | X16: GROWTH | Y16: 1 | Z16: 0 | AB16: 0.8 | AC16: 33.0 | AD16: 2025 | AE16: $500 | AF16: Apr 2026 | AG16: =IFERROR((500-I16)/I16,0) -> -0.067731619
B17: NVDA | C17: NVIDIA | D17: Action | E17: T2 | F17: 4 | G17: 128.59 | H17: 128.59 | I17: =IFERROR(J17*CONFIG!B3,0) -> 244.40097 | J17: =IFERROR(VLOOKUP(B17,CONFIG!$F$6:$G$35,2,0),0) -> 180.25 | K17: USD | L17: =IF(G17>0,G17*I17,0) -> 31427.521 | M17: =IF(H17>0,(I17-H17)*G17,0) -> 14892.133 | N17: =IF(H17>0,(I17-H17)/H17,0) -> 0.90062194 | O17: =IF(L17>0,L17/SUM(L8:L48),0) -> 0.011176577 | P17: 0.0003 | Q17: =IF(G17>0,G17*I17*P17,0) -> 9.4282564 | R17: 1.7 | S17: 0.99 | T17: 3000 | U17: 2025 | V17: ✅ Garder — beta 1.7, déjà exposé SMH | W17: Core 🚀 | X17: GROWTH | Y17: 1 | Z17: 0 | AB17: 1 | AC17: 45.0 | AD17: 2025 | AE17: $250 | AF17: May 2026 | AG17: =IFERROR((250-I17)/I17,0) -> 0.022909176
B18: TSLA | C18: Tesla | D18: Action | E18: T2 | F18: 1.8645 | G18: 303.5644 | H18: 303.5644 | I18: =IFERROR(J18*CONFIG!B3,0) -> 530.42808 | J18: =IFERROR(VLOOKUP(B18,CONFIG!$F$6:$G$35,2,0),0) -> 391.2 | K18: USD | L18: =IF(G18>0,G18*I18,0) -> 161019.08 | M18: =IF(H18>0,(I18-H18)*G18,0) -> 68867.737 | N18: =IF(H18>0,(I18-H18)/H18,0) -> 0.74733295 | O18: =IF(L18>0,L18/SUM(L8:L48),0) -> 0.057263254 | P18: 0 | Q18: =IF(G18>0,G18*I18*P18,0) -> 0 | R18: 2.1 | S18: 0.5 | T18: 2000 | U18: 2026-03-09 | V18: ⭐ Garder — spéculatif, beta 2.1 | W18: Satellite ⚡ | X18: SPEC | Y18: 0 | Z18: 0 | AB18: 0.4 | AC18: 120.0 | AD18: 2026-03-09 | AE18: $400 | AF18: Apr 2026 | AG18: =IFERROR((400-I18)/I18,0) -> -0.24589211
B19: QQQM | C19: Nasdaq 100 | D19: ETF | E19: T2 | F19: 4.4515 | G19: 247.1068 | H19: 247.1068 | I19: =IFERROR(J19*CONFIG!B3,0) -> 331.44975 | J19: =IFERROR(VLOOKUP(B19,CONFIG!$F$6:$G$35,2,0),0) -> 244.45 | K19: USD | L19: =IF(G19>0,G19*I19,0) -> 81903.488 | M19: =IF(H19>0,(I19-H19)*G19,0) -> 20841.718 | N19: =IF(H19>0,(I19-H19)/H19,0) -> 0.34132187 | O19: =IF(L19>0,L19/SUM(L8:L48),0) -> 0.029127357 | P19: 0.0065 | Q19: =IF(G19>0,G19*I19*P19,0) -> 532.37267 | R19: 1.15 | S19: 0.6 | T19: 3000 | U19: 2026-03-09 | V19: ✅ Garder — overlap NVDA/META/AMZN | W19: Core 🌍 | X19: ETF | Y19: 1 | Z19: 0 | AB19: 0.6 | AC19: 30.0 | AD19: 2026-03-09 | AE19: $280 | AF19: — | AG19: =IFERROR((280-I19)/I19,0) -> -0.15522641
B20: XEQT.TO | C20: iShares Core Eq | D20: ETF | E20: T2 | F20: 25 | G20: 39.97 | H20: 39.97 | I20: =IFERROR(VLOOKUP(B20,CONFIG!$F$6:$G$35,2,0),0) -> 39.85 | J20: =IFERROR(I20/CONFIG!B3,0) -> 29.390073 | K20: CAD | L20: =IF(G20>0,G20*I20,0) -> 1592.8045 | M20: =IF(H20>0,(I20-H20)*G20,0) -> -4.7964 | N20: =IF(H20>0,(I20-H20)/H20,0) -> -0.0030022517 | O20: =IF(L20>0,L20/SUM(L8:L48),0) -> 0.00056644944 | P20: 0.021 | Q20: =IF(G20>0,G20*I20*P20,0) -> 33.448895 | R20: 0.95 | S20: 0.2 | T20: 2000 | U20: 2026-03-09 | V20: ✅ Garder — diversif mondiale | W20: Core 🌍 | X20: ETF | Y20: 1 | Z20: 0 | AB20: 0.3 | AC20: 18.0 | AD20: 2026-03-09 | AE20: $45 | AF20: — | AG20: =IFERROR((45-I20)/I20,0) -> 0.12923463
B21: SPGI | C21: S&P Global | D21: Action | E21: T2 | F21: 0.9996 | G21: 443.2458 | H21: 443.2458 | I21: =IFERROR(J21*CONFIG!B3,0) -> 572.85419 | J21: =IFERROR(VLOOKUP(B21,CONFIG!$F$6:$G$35,2,0),0) -> 422.49 | K21: USD | L21: =IF(G21>0,G21*I21,0) -> 253915.21 | M21: =IF(H21>0,(I21-H21)*G21,0) -> 57448.375 | N21: =IF(H21>0,(I21-H21)/H21,0) -> 0.29240749 | O21: =IF(L21>0,L21/SUM(L8:L48),0) -> 0.090299928 | P21: 0.0088 | Q21: =IF(G21>0,G21*I21*P21,0) -> 2234.4539 | R21: 1.05 | S21: 0.15 | T21: 2000 | U21: 2026-03-09 | V21: ✅ Garder — moat monopolistique | W21: Core 🚀 | X21: GROWTH | Y21: 1 | Z21: 0 | AB21: 0.3 | AC21: 40.0 | AD21: 2026-03-09 | AE21: $550 | AF21: May 2026 | AG21: =IFERROR((550-I21)/I21,0) -> -0.039895302
B22: TD.TO | C22: TD Bank | D22: Action | E22: T3 | F22: 87 | G22: 79.8348 | H22: 79.8348 | I22: =IFERROR(VLOOKUP(B22,CONFIG!$F$6:$G$35,2,0),0) -> 128.05 | J22: =IFERROR(I22/CONFIG!B3,0) -> 94.439118 | K22: CAD | L22: =IF(G22>0,G22*I22,0) -> 10222.846 | M22: =IF(H22>0,(I22-H22)*G22,0) -> 3849.2508 | N22: =IF(H22>0,(I22-H22)/H22,0) -> 0.60393713 | O22: =IF(L22>0,L22/SUM(L8:L48),0) -> 0.0036355532 | P22: 0.048 | Q22: =IF(G22>0,G22*I22*P22,0) -> 490.69661 | R22: 0.85 | S22: 0.05 | T22: 0 | U22: 2025 | V22: 🔵 Diluer — AML risque, ne plus acheter | W22: Satellite 🇨🇦 | X22: CAN_SAT | Y22: 0 | Z22: 1 | AB22: 0.05 | AC22: 12.0 | AD22: 2025 | AE22: $85 | AF22: May 2026 | AG22: =IFERROR((85-I22)/I22,0) -> -0.3361968
B23: ZLB.TO | C23: BMO Low Vol | D23: ETF | E23: T3 | F23: 37 | G23: 58.1416 | H23: 58.1416 | I23: =IFERROR(VLOOKUP(B23,CONFIG!$F$6:$G$35,2,0),0) -> 59.04 | J23: =IFERROR(I23/CONFIG!B3,0) -> 43.543034 | K23: CAD | L23: =IF(G23>0,G23*I23,0) -> 3432.6801 | M23: =IF(H23>0,(I23-H23)*G23,0) -> 52.234413 | N23: =IF(H23>0,(I23-H23)/H23,0) -> 0.015451931 | O23: =IF(L23>0,L23/SUM(L8:L48),0) -> 0.0012207648 | P23: 0.025 | Q23: =IF(G23>0,G23*I23*P23,0) -> 85.817002 | R23: 0.6 | S23: 0.05 | T23: 2500 | U23: 2025 | V23: 🔵 Garder — coussin défensif beta 0.6 | W23: Satellite 🇨🇦 | X23: CAN_SAT | Y23: 0 | Z23: 1 | AB23: 0.05 | AC23: 16.0 | AD23: 2025 | AE23: $62 | AF23: — | AG23: =IFERROR((62-I23)/I23,0) -> 0.050135501
B24: H.TO | C24: Hydro One | D24: Action | E24: T3 | F24: 22 | G24: 52.8663 | H24: 52.8663 | I24: =IFERROR(VLOOKUP(B24,CONFIG!$F$6:$G$35,2,0),0) -> 60.09 | J24: =IFERROR(I24/CONFIG!B3,0) -> 44.317428 | K24: CAD | L24: =IF(G24>0,G24*I24,0) -> 3176.736 | M24: =IF(H24>0,(I24-H24)*G24,0) -> 381.89029 | N24: =IF(H24>0,(I24-H24)/H24,0) -> 0.13664092 | O24: =IF(L24>0,L24/SUM(L8:L48),0) -> 0.0011297434 | P24: 0.032 | Q24: =IF(G24>0,G24*I24*P24,0) -> 101.65555 | R24: 0.35 | S24: 0 | T24: 2000 | U24: 2025 | V24: 🔵 Garder — utilité, beta 0.35 | W24: Satellite 🇨🇦 | X24: CAN_SAT | Y24: 0 | Z24: 1 | AB24: 0.05 | AC24: 22.0 | AD24: 2025 | AE24: $65 | AF24: May 2026 | AG24: =IFERROR((65-I24)/I24,0) -> 0.081710767
B25: T.TO | C25: TELUS | D25: Action | E25: T3 | F25: 32 | G25: 22.04 | H25: 22.04 | I25: =IFERROR(VLOOKUP(B25,CONFIG!$F$6:$G$35,2,0),0) -> 18.01 | J25: =IFERROR(I25/CONFIG!B3,0) -> 13.28269 | K25: CAD | L25: =IF(G25>0,G25*I25,0) -> 396.9404 | M25: =IF(H25>0,(I25-H25)*G25,0) -> -88.8212 | N25: =IF(H25>0,(I25-H25)/H25,0) -> -0.18284936 | O25: =IF(L25>0,L25/SUM(L8:L48),0) -> 0.00014116401 | P25: 0.078 | Q25: =IF(G25>0,G25*I25*P25,0) -> 30.961351 | R25: 0.55 | S25: 0 | T25: 0 | U25: 2025 | V25: 👀 Q3 2026 — surveiller décision div | W25: Satellite 🇨🇦 | X25: CAN_SAT | Y25: 0 | Z25: 1 | AB25: 0.02 | AC25: 9.0 | AD25: 2025 | AE25: — | AF25: Aug 2026
B26: QTUM | C26: Defiance Quantum | D26: ETF | E26: T3 | F26: 5 | G26: 120.81 | H26: 120.81 | I26: =IFERROR(J26*CONFIG!B3,0) -> 148.29478 | J26: =IFERROR(VLOOKUP(B26,CONFIG!$F$6:$G$35,2,0),0) -> 109.37 | K26: USD | L26: =IF(G26>0,G26*I26,0) -> 17915.493 | M26: =IF(H26>0,(I26-H26)*G26,0) -> 3320.4366 | N26: =IF(H26>0,(I26-H26)/H26,0) -> 0.2275042 | O26: =IF(L26>0,L26/SUM(L8:L48),0) -> 0.0063712909 | P26: 0.005 | Q26: =IF(G26>0,G26*I26*P26,0) -> 89.577464 | R26: 1.4 | S26: 0.7 | T26: 1000 | U26: 2025 | V26: 🔵 Garder — thèse 10 ans, position petite | W26: Satellite ⚡ | X26: SPEC | Y26: 0 | Z26: 0 | AB26: 0.8 | AC26: — | AD26: 2025 | AE26: $130 | AF26: — | AG26: =IFERROR((130-I26)/I26,0) -> -0.12336768
B27: HURA.TO | C27: Global X Uranium | D27: ETF | E27: T3 | F27: 6 | G27: 55.25 | H27: 55.25 | I27: =IFERROR(VLOOKUP(B27,CONFIG!$F$6:$G$35,2,0),0) -> 57.54 | J27: =IFERROR(I27/CONFIG!B3,0) -> 42.436758 | K27: CAD | L27: =IF(G27>0,G27*I27,0) -> 3179.085 | M27: =IF(H27>0,(I27-H27)*G27,0) -> 126.5225 | N27: =IF(H27>0,(I27-H27)/H27,0) -> 0.041447964 | O27: =IF(L27>0,L27/SUM(L8:L48),0) -> 0.0011305787 | P27: 0.012 | Q27: =IF(G27>0,G27*I27*P27,0) -> 38.14902 | R27: 1.1 | S27: 0 | T27: 1500 | U27: 2025 | V27: 🔵 Garder — énergie IA data centers | W27: Satellite 🔬 | X27: SPEC | Y27: 0 | Z27: 0 | AB27: 0.4 | AC27: — | AD27: 2025 | AE27: $70 | AF27: — | AG27: =IFERROR((70-I27)/I27,0) -> 0.21654501
B28: REI.UN.TO | C28: RioCan REIT | D28: REIT | E28: T4 | F28: 0 | G28: 0 | H28: 0 | I28: =IFERROR(VLOOKUP(B28,CONFIG!$F$6:$G$35,2,0),0) -> 19.02 | J28: =IFERROR(I28/CONFIG!B3,0) -> 14.027583 | K28: CAD | L28: =IF(G28>0,G28*I28,0) -> 0 | M28: =IF(H28>0,(I28-H28)*G28,0) -> 0 | N28: =IF(H28>0,(I28-H28)/H28,0) -> 0 | O28: =IF(L28>0,L28/SUM(L8:L48),0) -> 0 | P28: 0.0587 | Q28: =IF(G28>0,G28*I28*P28,0) -> 0 | R28: 0.85 | S28: 0 | T28: 7000 | U28: 2025 | V28: 🔄 Coussin défensif — div mensuel 5.9% | W28: Satellite 🏢 | X28: REIT | Y28: 0 | Z28: 1 | AB28: 0 | AC28: — | AD28: 2025 | AE28: $22 | AF28: — | AG28: =IFERROR((22-I28)/I28,0) -> 0.15667718
B29: PLZ.UN.TO | C29: Plaza Retail | D29: REIT | E29: T4 | F29: 0 | G29: 0 | H29: 0 | I29: =IFERROR(VLOOKUP(B29,CONFIG!$F$6:$G$35,2,0),0) -> 4.26 | J29: =IFERROR(I29/CONFIG!B3,0) -> 3.1418246 | K29: CAD | L29: =IF(G29>0,G29*I29,0) -> 0 | M29: =IF(H29>0,(I29-H29)*G29,0) -> 0 | N29: =IF(H29>0,(I29-H29)/H29,0) -> 0 | O29: =IF(L29>0,L29/SUM(L8:L48),0) -> 0 | P29: 0.0667 | Q29: =IF(G29>0,G29*I29*P29,0) -> 0 | R29: 0.7 | S29: 0 | T29: 0 | U29: 2025 | V29: 🔄 Diluer — croissance div nulle 5 ans | W29: Satellite 🏢 | X29: REIT | Y29: 0 | Z29: 1 | AB29: 0 | AC29: — | AD29: 2025 | AE29: $5 | AF29: — | AG29: =IFERROR((5-I29)/I29,0) -> 0.17370892
B30: XEI.TO | C30: iShares High Div | D30: ETF | E30: T4 | F30: 51 | G30: 30.6811 | H30: 30.6811 | I30: =IFERROR(VLOOKUP(B30,CONFIG!$F$6:$G$35,2,0),0) -> 35.89 | J30: =IFERROR(I30/CONFIG!B3,0) -> 26.469504 | K30: CAD | L30: =IF(G30>0,G30*I30,0) -> 1101.1447 | M30: =IF(H30>0,(I30-H30)*G30,0) -> 159.81478 | N30: =IF(H30>0,(I30-H30)/H30,0) -> 0.16977553 | O30: =IF(L30>0,L30/SUM(L8:L48),0) -> 0.00039160034 | P30: 0.049 | Q30: =IF(G30>0,G30*I30*P30,0) -> 53.956089 | R30: 0.8 | S30: 0 | T30: 0 | U30: 2026-03-09 | V30: 🔄 Diluer — redondant avec ENB/TD | W30: Satellite 🏢 | X30: REIT | Y30: 0 | Z30: 1 | AB30: 0.05 | AC30: — | AD30: 2026-03-09 | AE30: $38 | AF30: — | AG30: =IFERROR((38-I30)/I30,0) -> 0.05879075
B31: SRU.UN.TO | C31: SmartCentres | D31: REIT | E31: T4 | F31: 57 | G31: 25.2543 | H31: 25.2543 | I31: =IFERROR(VLOOKUP(B31,CONFIG!$F$6:$G$35,2,0),0) -> 26.84 | J31: =IFERROR(I31/CONFIG!B3,0) -> 19.79497 | K31: CAD | L31: =IF(G31>0,G31*I31,0) -> 677.82541 | M31: =IF(H31>0,(I31-H31)*G31,0) -> 40.045744 | N31: =IF(H31>0,(I31-H31)/H31,0) -> 0.062789307 | O31: =IF(L31>0,L31/SUM(L8:L48),0) -> 0.00024105521 | P31: 0.0718 | Q31: =IF(G31>0,G31*I31*P31,0) -> 48.667865 | R31: 0.9 | S31: 0 | T31: 3000 | U31: 2025 | V31: 🔄 Coussin défensif — Walmart anchor | W31: Satellite 🏢 | X31: REIT | Y31: 0 | Z31: 1 | AB31: 0 | AC31: — | AD31: 2025 | AE31: $30 | AF31: — | AG31: =IFERROR((30-I31)/I31,0) -> 0.11773472
B32: XIC.TO | C32: iShares TSX | D32: ETF | E32: T4 | F32: 21 | G32: 40.4066 | H32: 40.4066 | I32: =IFERROR(VLOOKUP(B32,CONFIG!$F$6:$G$35,2,0),0) -> 52.08 | J32: =IFERROR(I32/CONFIG!B3,0) -> 38.409912 | K32: CAD | L32: =IF(G32>0,G32*I32,0) -> 2104.3757 | M32: =IF(H32>0,(I32-H32)*G32,0) -> 471.6824 | N32: =IF(H32>0,(I32-H32)/H32,0) -> 0.28889835 | O32: =IF(L32>0,L32/SUM(L8:L48),0) -> 0.00074837964 | P32: 0.028 | Q32: =IF(G32>0,G32*I32*P32,0) -> 58.92252 | R32: 0.95 | S32: 0.1 | T32: 0 | U32: 2025 | V32: 🔄 Diluer — redondant titres individ. | W32: Satellite 🇨🇦 | X32: CAN_SAT | Y32: 0 | Z32: 1 | AB32: 0.2 | AC32: — | AD32: 2026-03-09 | AE32: $58 | AF32: — | AG32: =IFERROR((58-I32)/I32,0) -> 0.11367128
B33: ZRE.TO | C33: BMO REITs | D33: ETF | E33: T4 | F33: 19 | G33: 20.83 | H33: 20.83 | I33: =IFERROR(VLOOKUP(B33,CONFIG!$F$6:$G$35,2,0),0) -> 22.33 | J33: =IFERROR(I33/CONFIG!B3,0) -> 16.468766 | K33: CAD | L33: =IF(G33>0,G33*I33,0) -> 465.1339 | M33: =IF(H33>0,(I33-H33)*G33,0) -> 31.245 | N33: =IF(H33>0,(I33-H33)/H33,0) -> 0.072011522 | O33: =IF(L33>0,L33/SUM(L8:L48),0) -> 0.00016541568 | P33: 0.045 | Q33: =IF(G33>0,G33*I33*P33,0) -> 20.931026 | R33: 0.8 | S33: 0 | T33: 0 | U33: 2025 | V33: 🔄 Diluer — redondant SRU/REI | W33: Satellite 🏢 | X33: REIT | Y33: 0 | Z33: 1 | AB33: 0
B34: MFC.TO | C34: Manulife | D34: Action | E34: T4 | F34: 8 | G34: 51.7 | H34: 51.7 | I34: =IFERROR(VLOOKUP(B34,CONFIG!$F$6:$G$35,2,0),0) -> 45.9 | J34: =IFERROR(I34/CONFIG!B3,0) -> 33.852054 | K34: CAD | L34: =IF(G34>0,G34*I34,0) -> 2373.03 | M34: =IF(H34>0,(I34-H34)*G34,0) -> -299.86 | N34: =IF(H34>0,(I34-H34)/H34,0) -> -0.11218569 | O34: =IF(L34>0,L34/SUM(L8:L48),0) -> 0.00084392122 | P34: 0.052 | Q34: =IF(G34>0,G34*I34*P34,0) -> 123.39756 | R34: 1.1 | S34: 0.05 | T34: 0 | U34: 2025 | V34: 🔄 Diluer — perte -13.5%, ne pas vendre | W34: Satellite 🇨🇦 | X34: CAN_SAT | Y34: 0 | Z34: 1 | AB34: 0.05
B35: VDU.TO | C35: Vanguard Dev | D35: ETF | E35: T4 | F35: 6 | G35: 43.75 | H35: 43.75 | I35: =IFERROR(VLOOKUP(B35,CONFIG!$F$6:$G$35,2,0),0) -> 55.07 | J35: =IFERROR(I35/CONFIG!B3,0) -> 40.61509 | K35: CAD | L35: =IF(G35>0,G35*I35,0) -> 2409.3125 | M35: =IF(H35>0,(I35-H35)*G35,0) -> 495.25 | N35: =IF(H35>0,(I35-H35)/H35,0) -> 0.25874286 | O35: =IF(L35>0,L35/SUM(L8:L48),0) -> 0.00085682437 | P35: 0.031 | Q35: =IF(G35>0,G35*I35*P35,0) -> 74.688688 | R35: 0.9 | S35: 0.15 | T35: 0 | U35: 2025 | V35: 🔄 Diluer — international, petite position | W35: Satellite 🌍 | X35: ETF_SAT | Y35: 0 | Z35: 0 | AB35: 0.1
B36: VFV.TO | C36: Vanguard S&P 500 | D36: ETF | E36: T1 | F36: 16 | G36: 157.3812 | H36: 157.3812 | I36: =IFERROR(VLOOKUP(B36,CONFIG!$F$6:$G$35,2,0),0) -> 161.8 | J36: =IFERROR(I36/CONFIG!B3,0) -> 119.33033 | K36: CAD | L36: =IF(G36>0,G36*I36,0) -> 25464.278 | M36: =IF(H36>0,(I36-H36)*G36,0) -> 695.43605 | N36: =IF(H36>0,(I36-H36)/H36,0) -> 0.028077051 | O36: =IF(L36>0,L36/SUM(L8:L48),0) -> 0.0090558673 | P36: 0.0092 | Q36: =IF(G36>0,G36*I36*P36,0) -> 234.27136 | R36: 1 | S36: 0.3 | T36: 20000 | U36: 2026-03-09 | V36: ✅ Auto $2,500/mois — FHSA maison 2028 | W36: Core 🌍 | X36: ETF | Y36: 1 | Z36: 0 | AB36: 0.35 | AC36: 22.5 | AD36: 2026-03-09 | AE36: $185 | AF36: — | AG36: =IFERROR((185-I36)/I36,0) -> 0.1433869
B37: AMZN | C37: Amazon | D37: Action | E37: T1 | F37: 7 | G37: 154.9418 | H37: 154.9418 | I37: =IFERROR(J37*CONFIG!B3,0) -> 281.57975 | J37: =IFERROR(VLOOKUP(B37,CONFIG!$F$6:$G$35,2,0),0) -> 207.67 | K37: USD | L37: =IF(G37>0,G37*I37,0) -> 43628.474 | M37: =IF(H37>0,(I37-H37)*G37,0) -> 19621.512 | N37: =IF(H37>0,(I37-H37)/H37,0) -> 0.81732594 | O37: =IF(L37>0,L37/SUM(L8:L48),0) -> 0.015515604 | P37: 0.001 | Q37: =IF(G37>0,G37*I37*P37,0) -> 43.628474 | R37: 1.22 | S37: 0.7 | T37: 4000 | U37: 2025 | V37: ✅ Garder — FHSA | W37: Core 🚀 | X37: GROWTH | Y37: 1 | Z37: 0 | AB37: 0.7 | AC37: 40.0 | AD37: 2025 | AE37: $280 | AF37: May 2026 | AG37: =IFERROR((280-I37)/I37,0) -> -0.0056103217
B38: QQQM | C38: Nasdaq 100 | D38: ETF | E38: T2 | F38: 5.311 | G38: 247.4064 | H38: 247.4064 | I38: =IFERROR(J38*CONFIG!B3,0) -> 331.44975 | J38: =IFERROR(VLOOKUP(B38,CONFIG!$F$6:$G$35,2,0),0) -> 244.45 | K38: USD | L38: =IF(G38>0,G38*I38,0) -> 82002.791 | M38: =IF(H38>0,(I38-H38)*G38,0) -> 20792.864 | N38: =IF(H38>0,(I38-H38)/H38,0) -> 0.33969758 | O38: =IF(L38>0,L38/SUM(L8:L48),0) -> 0.029162672 | P38: 0.0065 | Q38: =IF(G38>0,G38*I38*P38,0) -> 533.01814 | R38: 1.15 | S38: 0.6 | T38: 3000 | U38: 2026-03-09 | V38: ✅ Garder — FHSA | W38: Core 🌍 | X38: ETF | Y38: 1 | Z38: 0 | AB38: 0.6 | AC38: 30.0 | AD38: 2026-03-09 | AE38: $280 | AF38: — | AG38: =IFERROR((280-I38)/I38,0) -> -0.15522641
B39: XEQT.TO | C39: iShares Core Eq | D39: ETF | E39: T2 | F39: 15 | G39: 40.06 | H39: 40.06 | I39: =IFERROR(VLOOKUP(B39,CONFIG!$F$6:$G$35,2,0),0) -> 39.85 | J39: =IFERROR(I39/CONFIG!B3,0) -> 29.390073 | K39: CAD | L39: =IF(G39>0,G39*I39,0) -> 1596.391 | M39: =IF(H39>0,(I39-H39)*G39,0) -> -8.4126 | N39: =IF(H39>0,(I39-H39)/H39,0) -> -0.0052421368 | O39: =IF(L39>0,L39/SUM(L8:L48),0) -> 0.00056772491 | P39: 0.021 | Q39: =IF(G39>0,G39*I39*P39,0) -> 33.524211 | R39: 0.95 | S39: 0.2 | T39: 2000 | U39: 2026-03-09 | V39: ✅ Garder — FHSA | W39: Core 🌍 | X39: ETF | Y39: 1 | Z39: 0 | AB39: 0.3 | AC39: 18.0 | AD39: 2026-03-09 | AE39: $45 | AF39: — | AG39: =IFERROR((45-I39)/I39,0) -> 0.12923463
B40: TD.TO | C40: TD Bank | D40: Action | E40: T3 | F40: 15 | G40: 82.29 | H40: 82.29 | I40: =IFERROR(VLOOKUP(B40,CONFIG!$F$6:$G$35,2,0),0) -> 128.05 | J40: =IFERROR(I40/CONFIG!B3,0) -> 94.439118 | K40: CAD | L40: =IF(G40>0,G40*I40,0) -> 10537.235 | M40: =IF(H40>0,(I40-H40)*G40,0) -> 3765.5904 | N40: =IF(H40>0,(I40-H40)/H40,0) -> 0.55608215 | O40: =IF(L40>0,L40/SUM(L8:L48),0) -> 0.0037473592 | P40: 0.048 | Q40: =IF(G40>0,G40*I40*P40,0) -> 505.78726 | R40: 0.85 | S40: 0.05 | T40: 0 | U40: 2025 | V40: 🔵 Ne plus acheter — FHSA | W40: Satellite 🇨🇦 | X40: CAN_SAT | Y40: 0 | Z40: 1 | AB40: 0.05 | AC40: 12.0 | AD40: 2025 | AE40: $85 | AF40: May 2026 | AG40: =IFERROR((85-I40)/I40,0) -> -0.3361968
B41: H.TO | C41: Hydro One | D41: Action | E41: T3 | F41: 10 | G41: 51.78 | H41: 51.78 | I41: =IFERROR(VLOOKUP(B41,CONFIG!$F$6:$G$35,2,0),0) -> 60.09 | J41: =IFERROR(I41/CONFIG!B3,0) -> 44.317428 | K41: CAD | L41: =IF(G41>0,G41*I41,0) -> 3111.4602 | M41: =IF(H41>0,(I41-H41)*G41,0) -> 430.2918 | N41: =IF(H41>0,(I41-H41)/H41,0) -> 0.16048667 | O41: =IF(L41>0,L41/SUM(L8:L48),0) -> 0.0011065293 | P41: 0.032 | Q41: =IF(G41>0,G41*I41*P41,0) -> 99.566726 | R41: 0.35 | S41: 0 | T41: 2000 | U41: 2025 | V41: 🔵 Garder — FHSA | W41: Satellite 🇨🇦 | X41: CAN_SAT | Y41: 0 | Z41: 1 | AB41: 0.05 | AC41: 22.0 | AD41: 2025 | AE41: $65 | AF41: May 2026 | AG41: =IFERROR((65-I41)/I41,0) -> 0.081710767
B42: ZLB.TO | C42: BMO Low Vol | D42: ETF | E42: T3 | F42: 3 | G42: 59.0666 | H42: 59.0666 | I42: =IFERROR(VLOOKUP(B42,CONFIG!$F$6:$G$35,2,0),0) -> 59.04 | J42: =IFERROR(I42/CONFIG!B3,0) -> 43.543034 | K42: CAD | L42: =IF(G42>0,G42*I42,0) -> 3487.2921 | M42: =IF(H42>0,(I42-H42)*G42,0) -> -1.5711716 | N42: =IF(H42>0,(I42-H42)/H42,0) -> -0.00045033911 | O42: =IF(L42>0,L42/SUM(L8:L48),0) -> 0.0012401865 | P42: 0.025 | Q42: =IF(G42>0,G42*I42*P42,0) -> 87.182302 | R42: 0.6 | S42: 0.05 | T42: 2500 | U42: 2025 | V42: 🔵 Garder — FHSA | W42: Satellite 🇨🇦 | X42: CAN_SAT | Y42: 0 | Z42: 1 | AB42: 0.05 | AC42: 16.0 | AD42: 2025 | AE42: $62 | AF42: — | AG42: =IFERROR((62-I42)/I42,0) -> 0.050135501
B43: SRU.UN.TO | C43: SmartCentres | D43: REIT | E43: T4 | F43: 63 | G43: 23.61 | H43: 23.61 | I43: =IFERROR(VLOOKUP(B43,CONFIG!$F$6:$G$35,2,0),0) -> 26.84 | J43: =IFERROR(I43/CONFIG!B3,0) -> 19.79497 | K43: CAD | L43: =IF(G43>0,G43*I43,0) -> 633.6924 | M43: =IF(H43>0,(I43-H43)*G43,0) -> 76.2603 | N43: =IF(H43>0,(I43-H43)/H43,0) -> 0.13680644 | O43: =IF(L43>0,L43/SUM(L8:L48),0) -> 0.00022536018 | P43: 0.0718 | Q43: =IF(G43>0,G43*I43*P43,0) -> 45.499114 | R43: 0.9 | S43: 0 | T43: 3000 | U43: 2025 | V43: 🔄 Diluer — FHSA | W43: Satellite 🏢 | X43: REIT | Y43: 0 | Z43: 1 | AB43: 0 | AC43: — | AD43: 2025 | AE43: $30 | AF43: — | AG43: =IFERROR((30-I43)/I43,0) -> 0.11773472
B44: REI.UN.TO | C44: RioCan REIT | D44: REIT | E44: T4 | F44: 80 | G44: 18.73 | H44: 18.73 | I44: =IFERROR(VLOOKUP(B44,CONFIG!$F$6:$G$35,2,0),0) -> 19.02 | J44: =IFERROR(I44/CONFIG!B3,0) -> 14.027583 | K44: CAD | L44: =IF(G44>0,G44*I44,0) -> 356.2446 | M44: =IF(H44>0,(I44-H44)*G44,0) -> 5.4317 | N44: =IF(H44>0,(I44-H44)/H44,0) -> 0.015483182 | O44: =IF(L44>0,L44/SUM(L8:L48),0) -> 0.00012669135 | P44: 0.0587 | Q44: =IF(G44>0,G44*I44*P44,0) -> 20.911558 | R44: 0.85 | S44: 0 | T44: 7000 | U44: 2025 | V44: 🔄 Diluer — FHSA | W44: Satellite 🏢 | X44: REIT | Y44: 0 | Z44: 1 | AB44: 0 | AC44: — | AD44: 2025 | AE44: $22 | AF44: — | AG44: =IFERROR((22-I44)/I44,0) -> 0.15667718
B45: XIC.TO | C45: iShares TSX | D45: ETF | E45: T4 | F45: 19 | G45: 48.3705 | H45: 48.3705 | I45: =IFERROR(VLOOKUP(B45,CONFIG!$F$6:$G$35,2,0),0) -> 52.08 | J45: =IFERROR(I45/CONFIG!B3,0) -> 38.409912 | K45: CAD | L45: =IF(G45>0,G45*I45,0) -> 2519.1356 | M45: =IF(H45>0,(I45-H45)*G45,0) -> 179.43037 | N45: =IF(H45>0,(I45-H45)/H45,0) -> 0.076689304 | O45: =IF(L45>0,L45/SUM(L8:L48),0) -> 0.0008958808 | P45: 0.028 | Q45: =IF(G45>0,G45*I45*P45,0) -> 70.535798 | R45: 0.95 | S45: 0.1 | T45: 0 | U45: 2025 | V45: 🔄 Diluer — FHSA | W45: Satellite 🇨🇦 | X45: CAN_SAT | Y45: 0 | Z45: 1 | AB45: 0.2 | AC45: — | AD45: 2026-03-09 | AE45: $58 | AF45: — | AG45: =IFERROR((58-I45)/I45,0) -> 0.11367128
B46: XEI.TO | C46: iShares High Div | D46: ETF | E46: T4 | F46: 26 | G46: 32.6111 | H46: 32.6111 | I46: =IFERROR(VLOOKUP(B46,CONFIG!$F$6:$G$35,2,0),0) -> 35.89 | J46: =IFERROR(I46/CONFIG!B3,0) -> 26.469504 | K46: CAD | L46: =IF(G46>0,G46*I46,0) -> 1170.4124 | M46: =IF(H46>0,(I46-H46)*G46,0) -> 106.92854 | N46: =IF(H46>0,(I46-H46)/H46,0) -> 0.10054552 | O46: =IF(L46>0,L46/SUM(L8:L48),0) -> 0.00041623403 | P46: 0.049 | Q46: =IF(G46>0,G46*I46*P46,0) -> 57.350207 | R46: 0.8 | S46: 0 | T46: 0 | U46: 2025 | V46: 🔄 Diluer — FHSA | W46: Satellite 🏢 | X46: REIT | Y46: 0 | Z46: 1 | AB46: 0.05 | AC46: — | AD46: 2026-03-09 | AE46: $38 | AF46: — | AG46: =IFERROR((38-I46)/I46,0) -> 0.05879075
B47: SCHD | C47: Schwab US Div | D47: ETF | E47: T1 | F47: 64.3053 | G47: 25.5008 | H47: 25.5008 | I47: =IFERROR(J47*CONFIG!B3,0) -> 41.76172 | J47: =IFERROR(VLOOKUP(B47,CONFIG!$F$6:$G$35,2,0),0) -> 30.8 | K47: USD | L47: =IF(G47>0,G47*I47,0) -> 1064.9573 | M47: =IF(H47>0,(I47-H47)*G47,0) -> 414.66647 | N47: =IF(H47>0,(I47-H47)/H47,0) -> 0.63766313 | O47: =IF(L47>0,L47/SUM(L8:L48),0) -> 0.00037873101 | P47: 0.0352 | Q47: =IF(G47>0,G47*I47*P47,0) -> 37.486496 | R47: 0.75 | S47: 0.1 | T47: 15000 | U47: 2026-03-09 | V47: ✅ Auto $2,000/mois — snowball fiscal | W47: Core 💰 | X47: INCOME | Y47: 1 | Z47: 0 | AB47: 0.15
B48: JEPI | C48: JPMorgan Income | D48: ETF | E48: T2 | F48: 1 | G48: 54.52 | H48: 54.52 | I48: =IFERROR(J48*CONFIG!B3,0) -> 77.408331 | J48: =IFERROR(VLOOKUP(B48,CONFIG!$F$6:$G$35,2,0),0) -> 57.09 | K48: USD | L48: =IF(G48>0,G48*I48,0) -> 4220.3022 | M48: =IF(H48>0,(I48-H48)*G48,0) -> 1247.8718 | N48: =IF(H48>0,(I48-H48)/H48,0) -> 0.41981532 | O48: =IF(L48>0,L48/SUM(L8:L48),0) -> 0.0015008671 | P48: 0.0812 | Q48: =IF(G48>0,G48*I48*P48,0) -> 342.68854 | R48: 0.5 | S48: 0.2 | T48: 2000 | U48: 2025 | V48: ✅ Garder — revenu mensuel REER | W48: Core 💰 | X48: INCOME | Y48: 1 | Z48: 0 | AB48: 0.1
B50: ◼ GRAND TOTAL — SUBTOTAL s'adapte aux filtres | L50: =SUBTOTAL(9,L8:L48) -> 2811909.4 | M50: =SUBTOTAL(9,M8:M48) -> 766085.06 | O50: =1 -> 1 | Q50: =SUBTOTAL(9,Q8:Q48) -> 14566.787 | AB50: 0
B52: ⚡ EXPOSITION IA PONDÉRÉE | S52: =IFERROR(SUMPRODUCT(L8:L48,S8:S48)/SUBTOTAL(9,L8:L48),0) -> 0.64206174 | AB52: 0
B53: 📊 BETA MOYEN PONDÉRÉ | R53: =IFERROR(SUMPRODUCT(L8:L48,R8:R48)/SUBTOTAL(9,L8:L48),0) -> 1.3310582 | AB53: 0
B54: 💰 DIVIDENDES ESTIMÉS /AN CAD | Q54: =Q50 -> 14566.787 | AB54: 0
B55: TIER | C55: VALEUR CAD | D55: VALEUR USD | E55: % PORTFOLIO | F55: NB POS. | G55: REV.DIV/AN CAD | AB55: 0
B56: 💡 COLONNES JAUNES = saisir · BLEUES = calculées · Yields/Beta à jour 9 mars 2026 | AB56: 0
B57: T2 | C57: ='📈 PORTEFEUILLE'!L71 | D57: ='📈 PORTEFEUILLE'!M71 | E57: =IF('📈 PORTEFEUILLE'!L67>0,'📈 PORTEFEUILLE'!L71/'📈 PORTEFEUILLE'!L67,0) -> 0 | F57: =COUNTIFS('📈 PORTEFEUILLE'!E14:E64,"T2",'📈 PORTEFEUILLE'!G14:G64,">0") -> 9 | G57: =SUMIF(E9:E50,"T2",R9:R50) -> 10.45 | AB57: 0
B58: T3 | C58: ='📈 PORTEFEUILLE'!L72 | D58: ='📈 PORTEFEUILLE'!M72 | E58: =IF('📈 PORTEFEUILLE'!L67>0,'📈 PORTEFEUILLE'!L72/'📈 PORTEFEUILLE'!L67,0) -> 0 | F58: =COUNTIFS('📈 PORTEFEUILLE'!E14:E64,"T3",'📈 PORTEFEUILLE'!G14:G64,">0") -> 9 | G58: =SUMIF(E9:E50,"T3",R9:R50) -> 6.65 | AB58: 0
B59: T4 | C59: ='📈 PORTEFEUILLE'!L73 -> 46900.481 | D59: ='📈 PORTEFEUILLE'!M73 -> 34589.926 | E59: =IF('📈 PORTEFEUILLE'!L67>0,'📈 PORTEFEUILLE'!L73/'📈 PORTEFEUILLE'!L67,0) -> 37222.604 | F59: =COUNTIFS('📈 PORTEFEUILLE'!E14:E64,"T4",'📈 PORTEFEUILLE'!G14:G64,">0") -> 10 | G59: =SUMIF(E9:E50,"T4",R9:R50) -> 10.5 | AB59: 0
B60: T5 | C60: ='📈 PORTEFEUILLE'!L74 -> 8519.0512 | D60: ='📈 PORTEFEUILLE'!M74 -> 6282.9495 | E60: =IF('📈 PORTEFEUILLE'!L67>0,'📈 PORTEFEUILLE'!L74/'📈 PORTEFEUILLE'!L67,0) -> 6761.1517 | F60: =COUNTIFS('📈 PORTEFEUILLE'!E14:E64,"T5",'📈 PORTEFEUILLE'!G14:G64,">0") -> 0 | G60: =SUMIF(E9:E50,"T5",R9:R50) -> 0 | AB60: 0
B63: 💰 REVENUS PASSIFS DIVIDENDES | AB63: 0
B64: Revenu total /an (CAD) | C64: =SUM(R9:R50) -> 39.05 | AB64: 0
B65: Revenu total /mois (CAD) | C65: =IFERROR(C64/12,0) -> 3.2541667 | AB65: 0
B66: Yield moyen du portfolio | C66: =IF('📈 PORTEFEUILLE'!L67>0,C64/'📈 PORTEFEUILLE'!L67,0) -> 30.992063 | AB66: 0
B67: Cible revenu /an (retraite $7K/mois) | C67: 84000 | AB67: 0
B68: Manquant pour cible | C68: =MAX(0,C67-C64) -> 83960.95 | AB68: 0
B71: 📖 GUIDE DE TRI ET FILTRAGE | AB71: 0
B72: Trier par valeur CAD ↑↓ | C72: Colonne L → ▼ → Tri décroissant → voir top positions par poids | AB72: 0
B73: Trier par gain % ↑↓ | C73: Colonne N → ▼ → Tri décroissant → meilleurs/pires performers | AB73: 0
B74: Trier par Tier A→Z | C74: Colonne E → ▼ → Tri A→Z → regroupe T1/T2/T3/T4 automatiquement | AB74: 0
B75: Filtrer par compte | C75: Colonne F → ▼ → Cocher seulement TFSA ou FHSA ou REER | AB75: 0
B76: Trier par dividende/an | C76: Colonne R → ▼ → Tri décroissant → voir meilleurs payeurs de div. | AB76: 0
B77: Filtrer par action | C77: Colonne S → ▼ → Cocher ACCUMULER pour voir uniquement vos convictions | AB77: 0
B78: ⚠️ Note importante | C78: Le tri/filtre ici ne modifie PAS l'onglet PORTEFEUILLE — données sources sécurisées | AB78: 0
B80: 🏗️ ANALYSE TFSA — CORE vs SATELLITE · Cible: Core ≥ 80% · Satellite ≤ 20% (T3+T4) | AB80: 0
B81: MÉTRIQUE | C81: VALEUR CAD | D81: % PORT TFSA | E81: CIBLE | F81: ÉCART | G81: STATUT | AB81: 0
B82: TFSA Total (valeur CAD) | C82: =SUMPRODUCT((F8:F48="TFSA")*L8:L48) -> 0 | D82: — | E82: — | F82: — | G82: 📊 Référence | AB82: 0
B83: TFSA Core (T1+T2 non-REIT) | C83: =SUMPRODUCT((F8:F48="TFSA")*Y8:Y48*L8:L48) -> 0 | D83: =IF(SUMPRODUCT((F8:F48="TFSA")*L8:L48)>0,SUMPRODUCT((F8:F48="TFSA")*Y8:Y48*L8:L48)/SUMPRODUCT((F8:F48="TFSA")*L8:L48),0) -> 0 | E83: ≥ 80% | F83: =IF(SUMPRODUCT((F8:F48="TFSA")*L8:L48)>0,SUMPRODUCT((F8:F48="TFSA")*Y8:Y48*L8:L48)/SUMPRODUCT((F8:F48="TFSA")*L8:L48)-0.8,"") | G83: =IF(SUMPRODUCT((F8:F48="TFSA")*L8:L48)>0,IF(SUMPRODUCT((F8:F48="TFSA")*Y8:Y48*L8:L48)/SUMPRODUCT((F8:F48="TFSA")*L8:L48)>=0.8,"OK","REVOIR"),"") | AB83: 0
B84: TFSA Satellite (T3+T4) | C84: =SUMPRODUCT((F8:F48="TFSA")*(1-Y8:Y48)*L8:L48) -> 0 | D84: =IF(SUMPRODUCT((F8:F48="TFSA")*L8:L48)>0,SUMPRODUCT((F8:F48="TFSA")*(1-Y8:Y48)*L8:L48)/SUMPRODUCT((F8:F48="TFSA")*L8:L48),0) -> 0 | E84: ≤ 20% | F84: =IF(SUMPRODUCT((F8:F48="TFSA")*L8:L48)>0,SUMPRODUCT((F8:F48="TFSA")*(1-Y8:Y48)*L8:L48)/SUMPRODUCT((F8:F48="TFSA")*L8:L48)-0.2,"") | G84: =IF(SUMPRODUCT((F8:F48="TFSA")*L8:L48)>0,IF(SUMPRODUCT((F8:F48="TFSA")*(1-Y8:Y48)*L8:L48)/SUMPRODUCT((F8:F48="TFSA")*L8:L48)<=0.2,"OK","TROP HAUT"),"") | AB84: 0
B85: TFSA CAN financials + REITs | C85: =SUMPRODUCT((F8:F48="TFSA")*Z8:Z48*L8:L48) -> 0 | D85: =IF(SUMPRODUCT((F8:F48="TFSA")*L8:L48)>0,SUMPRODUCT((F8:F48="TFSA")*Z8:Z48*L8:L48)/SUMPRODUCT((F8:F48="TFSA")*L8:L48),0) -> 0 | E85: ≤ 25% | F85: =IF(SUMPRODUCT((F8:F48="TFSA")*L8:L48)>0,SUMPRODUCT((F8:F48="TFSA")*Z8:Z48*L8:L48)/SUMPRODUCT((F8:F48="TFSA")*L8:L48)-0.25,"") | G85: =IF(SUMPRODUCT((F8:F48="TFSA")*L8:L48)>0,IF(SUMPRODUCT((F8:F48="TFSA")*Z8:Z48*L8:L48)/SUMPRODUCT((F8:F48="TFSA")*L8:L48)<=0.25,"OK","SURVEILLER"),"") | AB85: 0
B87: 🏠 ANALYSE FHSA — GLIDE PATH 2026→2028 · Point 3 — De-risking progressif avant RAP | AB87: 0
B88: MÉTRIQUE | C88: VALEUR / % | D88: CIBLE 2026 | E88: CIBLE 2027 | F88: CIBLE 2028 | G88: STATUT 2026 | AB88: 0
B89: FHSA Total (CAD) | C89: =SUMPRODUCT((F8:F48="FHSA")*L8:L48) -> 0 | D89: — | E89: — | F89: — | G89: — | AB89: 0
B90: FHSA Actions/ETF % (Core) | C90: =IF(SUMPRODUCT((F8:F48="FHSA")*L8:L48)>0,SUMPRODUCT((F8:F48="FHSA")*Y8:Y48*L8:L48)/SUMPRODUCT((F8:F48="FHSA")*L8:L48),0) -> 0 | D90: ≤ 70% | E90: ≤ 50% | F90: ≤ 30% | G90: =IF(SUMPRODUCT((F8:F48="FHSA")*L8:L48)>0,IF(SUMPRODUCT((F8:F48="FHSA")*Y8:Y48*L8:L48)/SUMPRODUCT((F8:F48="FHSA")*L8:L48)<=0.7,"OK","TROP ELEVE"),"") | AB90: 0
B91: FHSA REITs/Satellites % | C91: =IF(SUMPRODUCT((F8:F48="FHSA")*L8:L48)>0,SUMPRODUCT((F8:F48="FHSA")*(1-Y8:Y48)*L8:L48)/SUMPRODUCT((F8:F48="FHSA")*L8:L48),0) -> 0 | D91: ≤ 30% | E91: ≤ 50% | F91: ≤ 70% | G91: =IF(SUMPRODUCT((F8:F48="FHSA")*L8:L48)>0,IF(SUMPRODUCT((F8:F48="FHSA")*(1-Y8:Y48)*L8:L48)/SUMPRODUCT((F8:F48="FHSA")*L8:L48)<=0.3,"OK","A DILUER"),"") | AB91: 0
B92: → Nvx $ FHSA: Core seulement | C92: Tout → VFV.TO | D92: VFV.TO | E92: VFV + GIC | F92: GIC + bonds | G92: — | AB92: 0
B93: 🎯 RECOMMANDATION: FHSA → VFV.TO seul. Vendre SRU+REI+TD+ZLB+XEI → VFV.TO. RAP 2028 = $40K propre, zéro gestion, zéro risque de concentration. | AB93: 0
B95: 💼 ANALYSE REER — RAP vs RETRAITE · Point 5 — Split intentionnel | AB95: 0
B96: COMPOSANTE | C96: VALEUR ACT. CAD | D96: OBJECTIF CAD | E96: MANQUANT | F96: % ATTEINT | G96: STRATÉGIE | AB96: 0
B97: REER Total (CAD) | C97: =SUMPRODUCT((F8:F48="REER")*L8:L48) -> 0 | G97: SCHD $3K/mois + TDVG + VYM à ajouter | AB97: 0
B98: Part RAP (maison) | C98: =MIN(SUMPRODUCT((F8:F48="REER")*L8:L48),60000) -> 0 | D98: 60000 | E98: =MAX(0,D98-C98) -> 60000 | F98: =IF(D98>0,C98/D98,0) -> 0 | G98: Objectif 2028 · De-risquer progressivement | AB98: 0
B99: Part retraite long terme | C99: =MAX(0,SUMPRODUCT((F8:F48="REER")*L8:L48)-60000) -> 0 | D99: ∞ | E99: — | F99: — | G99: SCHD+TDVG+VYM · Actions 100% jusquʼà 2040 | AB99: 0
B100: Glide path RAP 2028 | C100: — | D100: — | E100: — | F100: — | G100: 2026: 100% SCHD · 2027: 80% SCHD+20% GIC · 2028: 50/50 | AB100: 0
B102: 💊 SCORE DE SANTÉ 4 DIMENSIONS · Point 6 — Mise à jour trimestrielle | AB102: 0
B103: DIMENSION | C103: SCORE /MAX | D103: % DIM. | E103: FORMULE AUTO | F103: RÈGLE | G103: Q1 2026 | H103: Q2 2026 | I103: Q3 2026 | J103: Q4 2026 | K103: TENDANCE | AB103: 0
B104: 🏠 Objectifs (maison+retraite) | C104: /30 | D104: =IFERROR(E104/30,0) -> 0.33333333 | E104: =IF('🏠 DASHBOARD'!C24<=25000,25,IF('🏠 DASHBOARD'!C24<=50000,18,10)) -> 10 | F104: FHSA+REER ≥ $50K = 18pt | Cotisation OK = +7pt | G104: — | H104: — | I104: — | J104: — | K104: =IF(H104>G104,"UP","STABLE") -> STABLE | AB104: 0
B105: ⚖️ Risque vs horizon (par cte) | C105: /25 | D105: =IFERROR(E105/25,0) -> 1 | E105: =MAX(15,25-IF(SUMPRODUCT((F8:F48="FHSA")*Y8:Y48*L8:L48)/MAX(1,SUMPRODUCT((F8:F48="FHSA")*L8:L48))>0.7,10,0)) -> 25 | F105: FHSA equity ≤70% = OK · TFSA satellite ≤20% = OK | G105: — | H105: — | I105: — | J105: — | K105: =IF(H105>G105,"UP","STABLE") -> STABLE | AB105: 0
B106: 🌍 Diversification (pays/sect.) | C106: /25 | D106: =IFERROR(E106/25,0) -> 0.8 | E106: =MAX(12,25-IF(SUMPRODUCT((F8:F48="TFSA")*Z8:Z48*L8:L48)/MAX(1,SUMPRODUCT((F8:F48="TFSA")*L8:L48))>0.25,8,0)-IF(SUMPRODUCT(T8:T48*L8:L48)/MAX(1,SUMPRODUCT(L8:L48))>0.45,5,0)) -> 20 | F106: IA < 45% = OK · CAN+REIT TFSA < 25% = OK | G106: — | H106: — | I106: — | J106: — | K106: =IF(H106>G106,"UP","STABLE") -> STABLE | AB106: 0
B107: ⚙️ Implémentation (cotisations) | C107: /20 | D107: =IFERROR(E107/20,0) -> 0.7 | E107: =IF('🏠 DASHBOARD'!J29="OK",20,IF('🏠 DASHBOARD'!J29="EXCES",8,14)) -> 14 | F107: FHSA ≤ plafond + REER cotisé + pas satellite TFSA en surplus | G107: — | H107: — | I107: — | J107: — | K107: =IF(H107>G107,"UP","STABLE") -> STABLE | AB107: 0
B108: 🏆 SCORE TOTAL AUTO | C108: — | E108: =E104+E105+E106+E107 -> 69 | F108: /100 | G108: =IF(E108>=80,"EXCELLENT",IF(E108>=65,"BON",IF(E108>=50,"EN PROGRES","ACTION REQUISE"))) -> BON | H108: Mis à jour auto · Mise à jour trim. = col G-J | AB108: 0

Sheet 📊 ANALYSE TITRES
A1: 📊 ANALYSE TITRES · Scorecard /10 par titre · Grille 8 critères · Sources documentées · Verdicts traçables
A2: Chaque analyse = web search systématique · 8 critères objectifs · Score /10 auto · Verdict daté · Revu à chaque session
A4: 🎯 CRITÈRES OBJECTIFS DE CLASSIFICATION PAR TIER · Gravés S16 · Immuables sauf révision formelle
A5: CRITÈRE | C5: T1 — CONVICTION MAX | E5: T2 — ACCUMULER SÉLECTIF | G5: T3 — HOLD SANS ACHAT | J5: T4 — DILUER NATURELLEMENT
A6: Croissance revenus/an | C6: >15%/an | E6: 5-15%/an | G6: 0-5%/an | J6: <0% ou N/A
A7: Avantage compétitif | C7: Fort + durable (moat) | E7: Modéré ou en construction | G7: Faible ou cyclique | J7: Aucun ou déclinant
A8: Potentiel 10 ans | C8: ×5 à ×20 possible | E8: ×2 à ×5 réaliste | G8: ×1 à ×2 stable | J8: <×1 ou incertain
A9: Qualité du bilan | C9: Excellent · Faible dette | E9: Bon · Dette maîtrisée | G9: Correct · Dette notable | J9: Faible · Dette élevée
A10: Conviction personnelle | C10: Maximum · Acheter les dips | E10: Haute · DCA régulier | G10: Moyenne · Garder seulement | J10: Basse · Ne plus acheter
A11: Rôle dans portfolio | C11: Moteur FI principal | E11: Support + diversification | G11: Défense / stabilité | J11: Erreur passée · diluer
A12: Dividende rôle | C12: Croissance dividende T1 | E12: Dividende croissant utile | G12: Dividende stable ok | J12: Dividende piège possible
A13: Exemple portefeuille | C13: AVGO VFV GOOG AMZN META | E13: MSFT NVDA QQQM SCHD SPGI | G13: H.TO ZLB.TO HURA.TO TD.TO | J13: XIC XEI ZRE MFC VDU REITs
A15: 📋 GRILLE SCORECARD /10 · 8 CRITÈRES PONDÉRÉS · Score auto · Tier suggéré automatique
A16: CRITÈRE | B16: DESCRIPTION | D16: POIDS | E16: SCORE /5 | F16: PONDÉRÉ | G16: GUIDE SCORING
A17: C1 | B17: Valorisation | C17: P/E vs secteur · P/S · EV/EBITDA · pas trop cher | D17: 0.15 | E17: ⬜ /5 | F17: =IF(ISNUMBER(E17),E17*D17,0) -> 0 | G17: Score 1=très cher · 3=juste prix · 5=sous-évalué vs croissance
A18: C2 | B18: Momentum | C18: Perf 1M · 3M · 1AN · 5ANS · tendance vs indice | D18: 0.1 | E18: ⬜ /5 | F18: =IF(ISNUMBER(E18),E18*D18,0) -> 0 | G18: Score 1=baisse forte · 3=neutre · 5=surperformance constante
A19: C3 | B19: Fondamentaux | C19: Revenus · Marges · FCF · Dette/EBITDA · ROE | D19: 0.2 | E19: ⬜ /5 | F19: =IF(ISNUMBER(E19),E19*D19,0) -> 0 | G19: Score 1=faible · 3=correct · 5=excellent bilan + croissance
A20: C4 | B20: Dividende | C20: Yield · Croissance 5 ans · Payout ratio · Durabilité | D20: 0.1 | E20: ⬜ /5 | F20: =IF(ISNUMBER(E20),E20*D20,0) -> 0 | G20: Score 1=insoutenable · 3=stable · 5=croissance forte + couverte
A21: C5 | B21: Moat / Avantage | C21: Barrières entrée · Pricing power · Part de marché | D21: 0.2 | E21: ⬜ /5 | F21: =IF(ISNUMBER(E21),E21*D21,0) -> 0 | G21: Score 1=aucun · 3=modéré · 5=dominant + durable + irrempla
A22: C6 | B22: Catalyseurs | C22: Earnings prochains · Annonces · Expansion · IA/Tech | D22: 0.1 | E22: ⬜ /5 | F22: =IF(ISNUMBER(E22),E22*D22,0) -> 0 | G22: Score 1=risques seuls · 3=neutre · 5=fort pipeline 12-24 mois
A23: C7 | B23: Risques | C23: Régulation · Concurrence · Concentration · Macro | D23: 0.1 | E23: ⬜ /5 | F23: =IF(ISNUMBER(E23),E23*D23,0) -> 0 | G23: Score 1=risques majeurs · 3=gérables · 5=bien protégé
A24: C8 | B24: Fit Portfolio FI | C24: Tier approprié · Expo USD/IA · Conviction · Horizon | D24: 0.05 | E24: ⬜ /5 | F24: =IF(ISNUMBER(E24),E24*D24,0) -> 0 | G24: Score 1=mauvais fit · 3=acceptable · 5=parfait pour ton FI
A25: SCORE TOTAL | D25: 100% | E25: =SUM(F17:F24) -> 0
A26: TIER SUGGÉRÉ | D26: =IF(F25>=4,"🟢 T1 — Conviction max · Accumuler agressivement",IF(F25>=3,"🟡 T2 — Accumuler sélectivement",IF(F25>=2,"🟠 T3 — Hold sans accumulation","🔴 T4 — Diluer naturellement"))) -> 🔴 T4 — Diluer naturellement
A29: 📈 ANALYSES COMPLÈTES PAR TITRE · Scorecard rempli à chaque analyse · Sources + Date + Verdict
A30: TICKER | B30: NOM | C30: TIER | D30: DATE | E30: C1-VAL | F30: SC | G30: C3-FUND | H30: SC | I30: C5-MOAT | J30: SC | K30: SCORE /5 | L30: TIER SUG. | M30: VERDICT
A31: VFV.TO | B31: Vanguard S&P 500 | C31: T1 | D31: Mar 2026 | E31: P/E S&P ~21x — historique | F31: 4 | G31: 500 cies · croissance bénéfices ~10%/an | H31: 4.5 | I31: Indice = moat ultime · 500 entreprises | J31: 5 | K31: 4.2 | L31: T1 | M31: ✅ ACCUMULER — DCA mensuel FHSA+TFSA. Pilier de la stratégie FI.
A32: AVGO | B32: Broadcom Inc. | C32: T1 | D32: Mar 2026 | E32: P/E ~35x — premium justifié IA | F32: 4 | G32: Revenus +51% · marges EBITDA 62% | H32: 5 | I32: Switch semis IA quasi-monopole | J32: 5 | K32: 4.2 | L32: T1 | M32: ✅ ACCUMULER AGRESSIVEMENT — Dip >5% = achat immédiat. No-buy 28 mai→4 juin.
A33: SMH | B33: VanEck Semis ETF | C33: T1 | D33: Mar 2026 | E33: P/E ~28x · prime semis justifiée | F33: 3.5 | G33: Top holdings NVDA AVGO TSM ASML | H33: 4.5 | I33: Semis = infrastructure IA incontournable | J33: 5 | K33: 3.8 | L33: T1 | M33: ✅ ACCUMULER — Proche seuil 15%. Prochain achat si dip >5% seulement.
A34: GOOG | B34: Alphabet Inc. | C34: T1 | D34: Mar 2026 | E34: P/E ~21x — sous-évalué vs pairs IA | F34: 4.5 | G34: Revenus +12% · marges 32% · FCF $70B | H34: 4.5 | I34: Search 92% + Cloud #3 + YouTube #1 | J34: 5 | K34: 3.8 | L34: T1 | M34: ✅ ACCUMULER — Sous-valorisé vs Meta/MSFT. Position trop petite. Dip >8% = achat.
A35: AMZN | B35: Amazon.com | C35: T1 | D35: Mar 2026 | E35: P/E ~35x · AWS premium | F35: 4 | G35: AWS 70% profits · e-commerce rentable | H35: 4.5 | I35: AWS #1 cloud · Prime moat conso | J35: 5 | K35: 3.8 | L35: T1 | M35: ✅ ACCUMULER — AWS = infrastructure IA incontournable. Accumulation progressive.
A36: META | B36: Meta Platforms | C36: T1 | D36: Mar 2026 | E36: P/E ~27x — raisonnable | F36: 4 | G36: Revenus +21% · marges 41% · FCF $50B | H36: 5 | I36: Réseaux sociaux 3.3B users · moat pub | J36: 5 | K36: 3.9 | L36: T1 | M36: ✅ ACCUMULER — Après earnings Q1 (fin avril). No-buy 21→28 avr.
A37: GEV | B37: GE Vernova | C37: T1 | D37: Mar 2026 | E37: P/E ~55x — growth premium élevé | F37: 3 | G37: Revenus +14% · marge en amélioration | H37: 4 | I37: Turbines gaz + éolien + grid = moat infra | J37: 4.5 | K37: 3.7 | L37: T1 | M37: ✅ ACCUMULER — Infrastructure IA indispensable. Dip >10% = achat fort.
A38: ENB.TO | B38: Enbridge Inc. | C38: T1 | D38: Mar 2026 | E38: P/E ~18x · yield play | F38: 4 | G38: Revenus stables · FCF $5B · régulé | H38: 4 | I38: Pipelines = infrastructure réglementée | J38: 4.5 | K38: 3.8 | L38: T1 | M38: ✅ GARDER + ACCUMULER pour dividende. Pilier revenus passifs $39/an.
A39: SCHD | B39: Schwab US Div ETF | C39: T1 | D39: Mar 2026 | E39: P/E ~17x — value screen | F39: 4.5 | G39: Quality screen · profitabilité filtrée | H39: 4.5 | I39: 100 titres quality dividend — moat sélection | J39: 4.5 | K39: 4.4 | L39: T1 | M39: ✅ ACCUMULER REER $2K/mois — Meilleur véhicule snowball fiscal. Priorité #1 REER.
A40: MSFT | B40: Microsoft Corp. | C40: T2 | D40: ⬜ À analyser | M40: =IF(ISNUMBER(E40),SUM(E40:L40)/8*5,"⬜") -> ⬜
A41: NVDA | B41: NVIDIA Corp. | C41: T2 | D41: ⬜ À analyser | M41: =IF(ISNUMBER(E41),SUM(E41:L41)/8*5,"⬜") -> ⬜
A42: QQQM | B42: Invesco Nasdaq ETF | C42: T2 | D42: ⬜ À analyser | M42: =IF(ISNUMBER(E42),SUM(E42:L42)/8*5,"⬜") -> ⬜
A43: SPGI | B43: S&P Global Inc. | C43: T2 | D43: ⬜ À analyser | M43: =IF(ISNUMBER(E43),SUM(E43:L43)/8*5,"⬜") -> ⬜
A44: JEPI | B44: JPMorgan Equity Premium | C44: T2 | D44: ⬜ À analyser | M44: =IF(ISNUMBER(E44),SUM(E44:L44)/8*5,"⬜") -> ⬜
A45: TSLA | B45: Tesla Inc. | C45: T2 | D45: ⬜ À analyser | M45: =IF(ISNUMBER(E45),SUM(E45:L45)/8*5,"⬜") -> ⬜
A46: XEQT.TO | B46: iShares All-Equity ETF | C46: T2 | D46: ⬜ À analyser | M46: =IF(ISNUMBER(E46),SUM(E46:L46)/8*5,"⬜") -> ⬜
A47: TD.TO | B47: TD Bank | C47: T3 | D47: ⬜ À analyser | M47: =IF(ISNUMBER(E47),SUM(E47:L47)/8*5,"⬜") -> ⬜
A48: H.TO | B48: Hydro One | C48: T3 | D48: ⬜ À analyser | M48: =IF(ISNUMBER(E48),SUM(E48:L48)/8*5,"⬜") -> ⬜
A49: T.TO | B49: TELUS Corp. | C49: T3 | D49: ⬜ À analyser | M49: =IF(ISNUMBER(E49),SUM(E49:L49)/8*5,"⬜") -> ⬜
A50: ZLB.TO | B50: BMO Low Volatility ETF | C50: T3 | D50: ⬜ À analyser | M50: =IF(ISNUMBER(E50),SUM(E50:L50)/8*5,"⬜") -> ⬜
A51: HURA.TO | B51: Horizons Uranium ETF | C51: T3 | D51: ⬜ À analyser | M51: =IF(ISNUMBER(E51),SUM(E51:L51)/8*5,"⬜") -> ⬜
... A59: REI.UN.TO | B59: RioCan REIT | C59: VENDU ✅ | D59: ✅ VENDU 11 mars 2026 | M59: =IF(ISNUMBER(E59),SUM(E59:L59)/8*5,"⬜") -> ⬜
A61: 🔬 PROTOCOLE D'ANALYSE · 8 étapes · Exécuter dans l'ordre · Ne jamais sauter une étape
A62: Étape 1 | B62: Web search prix live | E62: StockAnalysis.com + Morningstar — prix actuel · P/E · P/S · 52-week range
A63: Étape 2 | B63: Fondamentaux | E63: Simply Wall St + Koyfin — revenus 3 ans · marges · FCF · dette · ROE
A64: Étape 3 | B64: Dividende | E64: Digrin + Simply Wall St — yield actuel · croissance 5 ans · payout ratio
A65: Étape 4 | B65: Earnings calendar | E65: StockEvents — date prochain earnings · no-buy zone si <7 jours
A66: Étape 5 | B66: Comparaison sectorielle | E66: Morningstar — P/E vs secteur · performance relative 1 an
A67: Étape 6 | B67: Catalyseurs & risques | E67: Seeking Alpha / news récentes — pipeline produits · régulation · macro
A68: Étape 7 | B68: Fit portfolio | E68: Expo USD · IA · tier suggéré · conviction · objectif CAD dans portfolio
A69: Étape 8 | B69: Verdict final | E69: Score /10 · Tier confirmé ou changement · Action: Acheter/Attendre/Éviter + raison
A71: 📅 VERDICTS J+30 · Mesurer fiabilité des analyses · 11 avril 2026 = premier verdict
A72: DATE ANALYSE | B72: TICKER | C72: VERDICT INITIAL | D72: PRIX ENTRÉE | E72: TICKER | F72: PRIX J+30 | G72: PERF % | H72: VERDICT CORRECT? | I72: LEÇON APPRISE
A73: 2026-03-11 | B73: Ex: AVGO | C73: Ex: Acheter T1 | D73: Ex: $340 USD | E73: → J+30: | F73: ⬜ 11 avril | G73: =IF(ISNUMBER(F73),(F73-D73)/D73,"-") -> - | H73: ⬜ OUI/NON | I73: ⬜ À remplir

Sheet 🎯 DÉCISIONS
B1: 🎯 DÉCISIONS & ACTIONS · Achat du mois · Plan de vente · Rééquilibrage · Simulation
B3: 💰 ACHAT DU MOIS · $5,000 · Ordre fiscal optimal
B4: 5000 | C4: 3500 | D4: Mars 2026 | E4: Mars 2026
B5: # | C5: COMPTE | D5: TICKER | E5: MONTANT | F5: RATIONALE | G5: ROOM RESTANT | H5: STATUT
B6: 🔥1 | C6: REER | D6: SCHD | E6: 52.98%×$2K = +$1,060/mois ARC | F6: 52.98%×$2K = +$1,060/mois ARC | G6: =CONFIG!B8 -> 37008 | H6: ✅ EXÉCUTÉ 12 mars · 64.3053u confirmé Questrade
B7: 🔥2 | C7: FHSA | D7: VFV.TO | E7: $1,000 | F7: Double exonération fiscale | G7: =CONFIG!B7 -> 13700 | H7: ✅ ACTIF
B8: ⭐3 | C8: TFSA | D8: AVGO fract. | E8: $500 | F8: 100% tax-free · QUASI PLEIN | G8: =CONFIG!B6 -> 69600 | H8: ⚠️ ~$1,423 room
A9: 🏦4 | B9: EQ Bank | C9: HISA | D9: $1,500 | E9: Fonds urgence · $15K en 10 mois · ~4.0% garanti · PRIORITÉ CETTE SEMAINE
B10: 🔴 PLAN DE VENTE T4→T1 · PLZ.UN ✅ + REI.UN ✅ exécutés 11 mars · Restant: ~$1,878
B11: # | C11: TICKER | D11: COMPTE | E11: QTÉ | F11: VALEUR | G11: RÉINVEST → | H11: NOTE
B12: ✅ X | C12: PLZ.UN.TO | D12: TFSA | E12: 0u (vendu) | F12: $4,094 réalisés | G12: → AVGO+GEV+SMH | H12: ✅ EXÉCUTÉ 11 mars @ $4.26 · gain +17%
B13: 🔴2 | C13: ZRE.TO | D13: TFSA | E13: 19u | F13: ~$430 | G13: → VFV.TO | H13: ✅ EXÉCUTER LUNDI 16 mars
B14: 🔴3 | C14: XIC.TO | D14: TFSA | E14: 21u | F14: ~$1,118 | G14: → SMH | H14: ✅ EXÉCUTER LUNDI 16 mars
B15: 🔴4 | C15: VDU.TO | D15: TFSA | E15: 6u | F15: ~$338 | G15: → GOOG | H15: ✅ EXÉCUTER LUNDI 16 mars
B17: ⚖️ RÈGLE DE RÉÉQUILIBRAGE · Quand et quoi
B18: 🚫 JAMAIS vendre à perte TFSA | D18: T.TO + MFC.TO → room TFSA perdu définitivement
B19: ✅ Trigger vente T3/T4 | D19: Position en gain >5% + meilleure opportunité T1 identifiée
B20: 🔥 Trigger achat T1 | D20: Dip >5% = DCA accéléré · dip >15% = maximiser · COVID mindset
B21: 📊 Seuil tiers | D21: T1 cible 55-60% · T2 <15% · T3 <15% · T4 <5% · Actuel T1=44%
B22: 🤖 IA plafond | D22: Expo IA ≤ 45% · Actuel ~45% → AU SEUIL MAX · ne pas dépasser
B24: 🎲 SIMULATEUR CRASH · Psychologie : COVID ✅ · Buy the dip agressif
B25: SCÉNARIO | D25: AUJOURD'HUI | E25: VALEUR APRÈS | F25: ACTION OPTIMALE | G25: RÉSULTAT
B26: 📉 Correction -20% | D26: $87,603 | E26: ~$70,082 | F26: → DCA accéléré T1 | G26: P&L +30% en 18 mois
B27: 📉 Bear market -30% | D27: $87,603 | E27: ~$61,322 | F27: → Max AVGO+SMH+VFV | G27: Opportunité générationnelle
B28: 📉 Crash -50% | D28: $87,603 | E28: ~$43,800 | F28: → REER+TFSA max | G28: COVID playbook
B29: 📈 Rally +20% | D29: $87,603 | E29: ~$105,124 | F29: → DCA normal | G29: Ne pas chaser · rester le plan

Sheet 🚨 ALERTES
B1: 🚨 ALERTES & SURVEILLANCE · Risques · Prix cibles · Santé · Devise
B3: ⚠️ TABLEAU DE BORD DES RISQUES · Recalcul automatique
B4: ALERTE | D4: STATUT AUTO | F4: DÉTAIL
B5: 🔥 REER non cotisé | D5: =IF(CONFIG!B34<1000,"🔴 CRITIQUE","✅ OK") -> ✅ OK | F5: Chaque mois sans SCHD = -$1,590 ARC
B6: 🏦 Fonds urgence | D6: Plan: $1,500/mois dès prochaine paie cette semaine · $15K en 10 mois · AVANT Questrade | F6: Cible $15,000 EQ Bank · Actuel $0
B7: 💱 Expo USD | D7: =IF(CONFIG!B32>0.65,"🔴 >65%",IF(CONFIG!B32>0.6,"🟡 SURVEILLER","✅ OK")) -> 🔴 >65% | F7: Actuel ~44% ✅ (post-trades 11 mars · seuil 65%)
B8: 🤖 Expo IA | D8: =IF(CONFIG!B31>0.45,"🔴 >45%",IF(CONFIG!B31>0.4,"🟡 PROCHE","✅ OK")) -> ✅ OK | F8: Actuel ~28% ✅ (AVGO+SMH+GEV+NVDA+GOOG · seuil 45%)
B9: 🏠 FHSA room 2026 | D9: =IF(CONFIG!B7<500,"⚠️ QUASI PLEIN","✅ OK") -> ✅ OK | F9: =" Room: $"&TEXT(CONFIG!B7,"#,##0") -> Room: $13,700
B10: 🔴 T.TO + MFC.TO | D10: 🔴 NE PAS VENDRE | F10: Room TFSA perdu définitivement si vendu en perte
B12: 🔔 PRIX CIBLES · GOOGLEFINANCE auto · Signaux d'achat T1/T2
B13: TIER | C13: TICKER | D13: PRIX ACTUEL | E13: PRIX CIBLE | F13: ACTION | G13: EARNINGS | H13: NOTE
B14: T1 | C14: AVGO | D14: =IFERROR(__xludf.DUMMYFUNCTION("IFERROR(googlefinance(""AVGO""),CONFIG!G8)"),322.16) -> 322.16 | E14: 320 | F14: =IF(ISNUMBER(D14),IF(D14<E14,"🟢 ACHETER","⏳ ATTENDRE"),"—") -> ⏳ ATTENDRE | G14: 4 juin · no-buy 28 mai→4 juin | H14: Core IA · DCA mensuel
B15: T1 | C15: SMH | D15: =IFERROR(__xludf.DUMMYFUNCTION("IFERROR(googlefinance(""SMH""),CONFIG!G10)"),387.33) -> 387.33 | E15: 350 | F15: =IF(ISNUMBER(D15),IF(D15<E15,"🟢 ACHETER","⏳ ATTENDRE"),"—") -> ⏳ ATTENDRE | G15: — | H15: ETF semis
B16: T1 | C16: GOOG | D16: =IFERROR(__xludf.DUMMYFUNCTION("IFERROR(googlefinance(""GOOG""),CONFIG!G7)"),301.46) -> 301.46 | E16: 280 | F16: =IF(ISNUMBER(D16),IF(D16<E16,"🟢 ACHETER","⏳ ATTENDRE"),"—") -> ⏳ ATTENDRE | G16: — | H16: Dip >10%
B17: T1 | C17: META | D17: =IFERROR(__xludf.DUMMYFUNCTION("IFERROR(googlefinance(""META""),CONFIG!G11)"),613.71) -> 613.71 | E17: 580 | F17: =IF(ISNUMBER(D17),IF(D17<E17,"🟢 ACHETER","⏳ ATTENDRE"),"—") -> ⏳ ATTENDRE | G17: 28 avr · no-buy 21→28 avr | H17: Earnings watch
B18: T1 | C18: VFV.TO | D18: =IFERROR(__xludf.DUMMYFUNCTION("IFERROR(googlefinance(""TSE:VFV""),CONFIG!G6)"),161.8) -> 161.8 | E18: 155 | F18: =IF(ISNUMBER(D18),IF(D18<E18,"🟢 ACHETER","⏳ ATTENDRE"),"—") -> ⏳ ATTENDRE | G18: — | H18: DCA FHSA
B19: T2 | C19: NVDA | D19: =IFERROR(__xludf.DUMMYFUNCTION("IFERROR(googlefinance(""NVDA""),CONFIG!G16)"),180.25) -> 180.25 | E19: 160 | F19: =IF(ISNUMBER(D19),IF(D19<E19,"🔵 T2 DIP","⏳ TENIR"),"—") -> ⏳ TENIR | G19: 28 mai · no-buy 21→28 mai | H19: T2 seulement
B20: T2 | C20: MSFT | D20: =IFERROR(__xludf.DUMMYFUNCTION("IFERROR(googlefinance(""MSFT""),CONFIG!G15)"),395.55) -> 395.55 | E20: 370 | F20: =IF(ISNUMBER(D20),IF(D20<E20,"🔵 T2 DIP","⏳ TENIR"),"—") -> ⏳ TENIR | G20: — | H20: Dip >15%
B21: T1 | C21: GEV | D21: =IFERROR(__xludf.DUMMYFUNCTION("IFERROR(googlefinance(""GEV""),CONFIG!G13)"),805.02) -> 805.02 | E21: 750 | F21: =IF(ISNUMBER(D21),IF(D21<E21,"🟢 ACHETER","⏳ ATTENDRE"),"—") -> ⏳ ATTENDRE | G21: — | H21: Énergie IA infrastructure · T1 · DCA dip >10%
B22: 🚫 NO-BUY ZONES · Ne pas acheter -7j avant earnings · Même si dip
B23: TICKER | C23: NO-BUY DU | D23: NO-BUY AU | E23: ÉVÉNEMENT | F23: ACTION | G23: STATUT
B24: META | D24: 28 avr 2026 | E24: Earnings Q1 META | F24: 🚫 Ne pas acheter
B25: AVGO | D25: 4 juin 2026 | E25: Earnings Q2 AVGO | F25: 🚫 Ne pas acheter
B26: NVDA | D26: 28 mai 2026 | E26: Earnings Q1 NVDA (T2) | F26: ⚠️ T2 seulement
B27: → Règle R10 : no-buy = -7 jours avant earnings T1/T2 · attendre résultats avant DCA
B30: 🏥 SCORE DE SANTÉ · /100 · Auto-calculé
B31: CRITÈRE | D31: POIDS | F31: DÉTAIL
B32: Diversification tiers T1>55% | D32: 15 | E32: 10 | F32: T1 actuel ~44% → sous cible
B33: Expo IA ≤45%
B34: Expo USD ≤65% | D34: 15 | F34: Actuel ~44% → 15/15 ✅ (post-trades)
B35: Fonds urgence $15K | D35: 15 | F35: Actuel $0 → 2/15
B36: Plan cotisation actif | D36: 15 | F36: FHSA actif → partiel
B37: T4 < 5% portfolio | D37: 15 | F37: T4 encore trop haut
B38: Calendrier earnings suivi | D38: 10 | E38: 8 | F38: Earnings dans CONTEXT
B39: SCORE TOTAL /100 | D39: =SUM(E24:E30) -> 0 | F39: =IF(D31>=80,"🟢 EXCELLENT",IF(D31>=65,"🟡 BON","🔴 À AMÉLIORER")) -> 🟢 EXCELLENT
B41: 💱 EXPOSITION USD/CAD · Surveillance change
B42: Taux live Google Finance | D42: =IFERROR(__xludf.DUMMYFUNCTION("IFERROR(googlefinance(""CURRENCY:USDCAD""),CONFIG!B3)"),1.3810498999999998) -> 1.3810499 | F42: Auto · sinon mettre à jour CONFIG!B3
B43: Taux CONFIG manuel | D43: =CONFIG!B3 -> 1.3559 | F43: Mettre à jour après dump Questrade
B44: Expo USD portfolio | D44: =CONFIG!B46 -> 0.96333537 | F44: Seuil max 65% · Actuel ~44% ✅ post-trades 11 mars
B45: Statut | D45: =IF(CONFIG!B46>0.65,"🔴 DÉPASSE 65%",IF(CONFIG!B46>0.6,"🟡 SURVEILLER","✅ OK")) -> 🔴 DÉPASSE 65%
B46: 📊 PRIX .UN — Fiabilité GOOGLEFINANCE TSX REITs
B47: REI.UN → TSE:REI-UN ✅ fiable · SRU.UN → TSE:SRU-UN ✅ fiable · PLZ.UN ✅ VENDU 11 mars 2026 @ $4.26 · SRU.UN reste actif en FHSA
A49: 📅 Verdicts J+30 | B49: 🔔 ALARME 11 AVRIL 2026 | C49: 6 trades à évaluer · Prix entrée documentés dans JOURNAL · Calculer alpha vs VFV.TO · Leçons à documenter
A50: 📊 Analyse Titres | B50: 🆕 Onglet créé S16 | C50: 29 titres à analyser · Commencer par T1 à chaque session · Grille 8 critères + scorecard /10

Sheet ❄️ FISCAL
B1: ❄️ STRATÉGIE FISCALE · Snowball REER · Remboursement ARC · FTQ · Fiscal avancé
B3: ❄️ SNOWBALL FISCAL · Impact réel taux 52.98%
B4: VÉHICULE | D4: ÉCON. /AN | E4: ÉCON. /MOIS | F4: RÈGLE
B5: FHSA $16K/an | D5: =16000*CONFIG!B11 -> 8476.8 | E5: =16000*CONFIG!B11/12 -> 706.4 | F5: Déduction + retrait maison tax-free
B6: REER $36K/an | D6: =36000*CONFIG!B11 -> 19072.8 | E6: =36000*CONFIG!B11/12 -> 1589.4 | F6: Déduction 52.98% · horizon retraite
B7: REER $2K/mois | D7: =2000*CONFIG!B11 -> 1059.6 | E7: =2000*CONFIG!B11/12 -> 88.3 | F7: ✅ EN COURS · $2,000/mois SCHD · Coût net $940/mois · ARC rembourse $1,060/mois
B8: FTQ $5K (si élig.) | D8: =5000*(CONFIG!B11+0.3) -> 4149 | E8: — | F8: 52.98%+30% = 82.98% retour effectif
B10: 🧾 CALCULATEUR REMBOURSEMENT FISCAL · Cotisations 2026 réelles
B11: POSTE | D11: COTISATION | E11: TAUX | F11: ÉCONOMIE IMPÔT
B12: FHSA 2026 | D12: =CONFIG!B33 -> 2300 | E12: =CONFIG!B11 -> 0.5298 | F12: =D12*E12 -> 1218.54
B13: REER 2026 | D13: =CONFIG!B34 -> 2000 | E13: =CONFIG!B11 -> 0.5298 | F13: =D13*E13 -> 1059.6
B14: FTQ 2026 | D14: =CONFIG!B27 -> 0 | E14: =CONFIG!B11+0.3 -> 0.8298 | F14: =D14*E14 -> 0
B15: TOTAL REMBOURSÉ ARC | D15: =SUM(D12:D14) -> 4300 | F15: =SUM(F12:F14) -> 2278.14
B17: 🌲 FTQ · Crédit 30% · Seuil admissibilité
B18: Seuil admissibilité | D18: Revenu NET 2025 < $129,590 | F18: ⚠️ Vérifier ARC Mon Dossier
B19: Cotisation max | D19: $5,000 avant 31 déc 2026 | F19: Crédit $1,500 garanti si éligible
B20: Retour combiné | D20: =TEXT(CONFIG!B11+0.3,"0.0%")&" retour effectif" -> 83.0% retour effectif | F20: $5,000 → $4,149 récupéré
B21: Revenu net | D21: =CONFIG!B35 -> 140000 | F21: CONFIG!B35 · mettre à jour
B22: Statut FTQ 2026 | D22: =IF(CONFIG!B35>129590,"🔴 NON ÉLIGIBLE · Revenu net > $129,590","✅ ÉLIGIBLE · Cotiser avant 31 déc") -> 🔴 NON ÉLIGIBLE · Revenu net > $129,590
B23: Statut FTQ | D23: Revenu net $140K > seuil $129,590 · Réévaluer si cotisation REER+FHSA réduit revenu net 2026
B25: 📊 PROJECTION REER → RAP $60,000 · Plan $2,000/mois
B26: POSTE | D26: VALEUR | E26: DATE EST. | F26: NOTE
B27: REER actuel (confirmé S18) | D27: =CONFIG!B34 -> 2000 | E27: Mar 2026 | F27: ← Cotisé YTD: $2,000 (SCHD 64.3053u)
B28: Cotisation mensuelle REER | D28: 2000 | E28: Mensuel | F28: SCHD · $1,060/mois ARC rembourse → coût net $940
B29: Mois pour atteindre $60,000 RAP | D29: =IFERROR(ROUNDUP((60000-CONFIG!B34)/2000,0),"⬜") -> 29 | E29: ← Auto | F29: Depuis solde actuel · ~29 mois si maintenu
B30: Date RAP $60K atteint (estimée) | D30: =IFERROR(TEXT(DATE(2026,3,1)+ROUNDUP((60000-CONFIG!B34)/2000,0)*30,"mmm yyyy"),"⬜ Saisir") -> Jul 2028 | E30: ← Auto | F30: ~Août 2028 si $2K/mois dès maintenant
B31: ARC remboursé total (cumul) | D31: =CONFIG!B34*CONFIG!B11 -> 1059.6 | E31: ← Auto | F31: Économie fiscale totale sur cotisations REER à date
B33: 📊 PROJECTION FHSA → $40,000 · Plan $1,000/mois FHSA
B34: POSTE | D34: VALEUR | E34: DATE EST. | F34: NOTE
B35: FHSA actuel (valeur marché) | D35: =CONFIG!B7 -> 13700 | E35: Mar 2026 | F35: ← Room restant 2026: $13,700 · Objectif: cotiser $16K en 2026
B36: Cotisé 2026 YTD (cash) | D36: =CONFIG!B33 -> 2300 | E36: ← Auto | F36: VFV.TO 16u @ $157.38
B37: Objectif FHSA pour maison 2030 | D37: 40000 | E37: 2030 | F37: Retrait tax-free pour mise de fonds · combiné RAP $60K = $100K
B38: Plan cotisations FHSA | D38: An 2026: $16K · An 2027: $8K · An 2028: $4K | F38: Selon plan confirmé par Hey S18

Sheet 💰 REVENUS
B1: 💰 REVENUS PASSIFS · Dividendes estimés · Dividendes reçus 2026
B3: 📊 DIVIDENDES ESTIMÉS /AN · Projections basées sur positions actuelles
B4: TICKER | C4: COMPTE | D4: QTÉ | E4: DIV/AN EST. | F4: TOTAL CAD EST. | H4: NOTE
B5: ENB.TO | C5: TFSA | D5: 9 | E5: ~$4.40 CAD/u | F5: =9*4.4 -> 39.6 | H5: Trimestriel ~6.0% yield
B6: SCHD | C6: 64.3053 | D6: 64.31 | E6: ~$2.90 USD/u | F6: =64.31*2.9*CONFIG!B3 -> 252.87399 | H6: Trimestriel ~3.8%
B7: JEPI | C7: REER | D7: 1 | E7: ~$4.60 USD/u | F7: =1*4.6*CONFIG!B3 -> 6.23714 | H7: Mensuel ~8%
B8: TD.TO | C8: TFSA+FHSA | D8: 102 | E8: ~$4.08 CAD/u | F8: =102*4.08 -> 416.16 | H8: Trimestriel ~3.1%
B9: SRU.UN.TO | C9: FHSA | D9: 63 | E9: ~$1.85 CAD/u | F9: =63*1.85 -> 116.55 | H9: Mensuel · REIT
A10: REI.UN.TO | B10: REI.UN.TO | C10: 0 | D10: ✅ VENDU 11 mars 2026 | E10: 0 | F10: 0 | H10: Mensuel · REIT
B11: MFC.TO | C11: TFSA | D11: 8 | E11: ~$1.60 CAD/u | F11: =8*1.6 -> 12.8 | H11: Trimestriel
B12: XEI.TO | C12: FHSA | D12: 26 | E12: ~$1.20 CAD/u | F12: =26*1.2 -> 31.2 | H12: Mensuel ETF
B13: TOTAL /AN ESTIMÉ | F13: =SUM(F5:F12) -> 875.42113 | H13: ~$3,200+/an ✅
B14: 📅 PROCHAINS DIVIDENDES ESTIMÉS · Approximatif — confirmer Questrade
B15: TICKER
B16: ENB.TO | C16: TFSA | D16: Trimestriel | E16: Mars/Juin/Sep/Déc | F16: ~$10 CAD/trim. | H16: 6.0% yield
B17: SCHD | C17: 64.3053 | D17: Trimestriel | E17: Mars/Juin/Sep/Déc | F17: ~$47 USD/trim. | H17: 3.8% yield · coeur snowball
B18: TD.TO | C18: TFSA+FHSA | D18: Trimestriel | E18: Jan/Avr/Juil/Oct | F18: ~$104 CAD/trim. | H18: 102u × $4.08/an ÷ 4
B19: SRU.UN | C19: FHSA | D19: Mensuel | E19: ~25 chaque mois | F19: ~$10 CAD/mois | H19: 63u × $1.85/an ÷ 12
A20: REI.UN.TO | B20: REI.UN | C20: 0 | D20: ✅ VENDU 11 mars 2026 | E20: 0 | F20: ~$6 CAD/mois | H20: 80u × $0.96/an ÷ 12
B22: 💸 DIVIDENDES RÉELS REÇUS 2026 · Saisir après réception Questrade
B23: DATE | C23: TICKER | D23: COMPTE | E23: MONTANT CAD | F23: MONTANT USD | G23: TYPE | H23: NOTE
B39: TOTAL YTD 2026 | E39: =SUMIF(C17:C31,"<>",E17:E31) -> 0
B42: 🔥 SNOWBALL ARC — Modélisation complète du remboursement REER → réinvestissement
B43: Cotisation REER mensuelle | C43: =CONFIG!B10*2000/3500 -> 2285.7143 | D43: ← $2,000/mois (proportion du plan total)
B44: Cotisation REER annuelle | C44: =C43*12 -> 27428.571 | D44: ← ×12
B45: Taux marginal QC | C45: =CONFIG!B11 -> 0.5298 | D45: ← auto CONFIG
B46: Remboursement ARC /an | C46: =C44*C45 -> 14531.657 | D46: ← Économie impôt réelle · reçue ~avril de l'année suivante
B47: Remboursement ARC /mois | C47: =C46/12 -> 1210.9714 | D47: ← Cash mensuel équivalent
B48: Réinvestissement ARC (où?) | C48: FHSA/TFSA/REER selon room | D48: ⬜ Décider chaque année en fonction du room restant
B49: Valeur ARC @20 ans (8%) | C49: =C46*(1.08^20-1)/0.08 -> 664997.18 | D49: ← Si réinvesti chaque année · intérêts composés
B50: COÛT NET réel REER /an | C50: =C44-C46 -> 12896.914 | D50: ← Ce que ça te coûte vraiment après remboursement
B52: 📅 CALENDRIER DIVIDENDES 2026 — Flux de trésorerie mensuel prévu
B53: TICKER / SOURCE | C53: COMPTE | D53: JAN | E53: FÉV | F53: MARS | G53: AVR | H53: MAI | I53: JUIN | J53: JUIL | K53: AOÛT | L53: SEP | M53: OCT | N53: NOV | O53: DÉC | P53: TOTAL/AN
B54: ENB.TO | C54: TFSA | D54: — | E54: — | F54: =IFERROR((9*4.4)/4,0) -> 9.9 | G54: — | H54: — | I54: =IFERROR((9*4.4)/4,0) -> 9.9 | J54: — | K54: — | L54: =IFERROR((9*4.4)/4,0) -> 9.9 | M54: — | N54: — | O54: =IFERROR((9*4.4)/4,0) -> 9.9 | P54: =IFERROR(SUM(D54:O54),0) -> 39.6
B55: SCHD | C55: REER | D55: — | E55: — | F55: =IFERROR((64.31*2.9*CONFIG!B3)/4,0) -> 63.218499 | G55: — | H55: — | I55: =IFERROR((64.31*2.9*CONFIG!B3)/4,0) -> 63.218499 | J55: — | K55: — | L55: =IFERROR((64.31*2.9*CONFIG!B3)/4,0) -> 63.218499 | M55: — | N55: — | O55: =IFERROR((64.31*2.9*CONFIG!B3)/4,0) -> 63.218499 | P55: =IFERROR(SUM(D55:O55),0) -> 252.87399
B56: JEPI | C56: REER | D56: =IFERROR((1*4.6*CONFIG!B3)/12,0) -> 0.51976167 | E56: =IFERROR((1*4.6*CONFIG!B3)/12,0) -> 0.51976167 | F56: =IFERROR((1*4.6*CONFIG!B3)/12,0) -> 0.51976167 | G56: =IFERROR((1*4.6*CONFIG!B3)/12,0) -> 0.51976167 | H56: =IFERROR((1*4.6*CONFIG!B3)/12,0) -> 0.51976167 | I56: =IFERROR((1*4.6*CONFIG!B3)/12,0) -> 0.51976167 | J56: =IFERROR((1*4.6*CONFIG!B3)/12,0) -> 0.51976167 | K56: =IFERROR((1*4.6*CONFIG!B3)/12,0) -> 0.51976167 | L56: =IFERROR((1*4.6*CONFIG!B3)/12,0) -> 0.51976167 | M56: =IFERROR((1*4.6*CONFIG!B3)/12,0) -> 0.51976167 | N56: =IFERROR((1*4.6*CONFIG!B3)/12,0) -> 0.51976167 | O56: =IFERROR((1*4.6*CONFIG!B3)/12,0) -> 0.51976167 | P56: =IFERROR(SUM(D56:O56),0) -> 6.23714
B57: TD.TO | C57: TFSA | D57: =IFERROR((87*4.08)/4,0) -> 88.74 | E57: — | F57: — | G57: =IFERROR((87*4.08)/4,0) -> 88.74 | H57: — | I57: — | J57: =IFERROR((87*4.08)/4,0) -> 88.74 | K57: — | L57: — | M57: =IFERROR((87*4.08)/4,0) -> 88.74 | N57: — | O57: — | P57: =IFERROR(SUM(D57:O57),0) -> 354.96
B58: TD.TO | C58: FHSA | D58: =IFERROR((87*4.08)/4,0) -> 88.74 | E58: — | F58: — | G58: =IFERROR((87*4.08)/4,0) -> 88.74 | H58: — | I58: — | J58: =IFERROR((87*4.08)/4,0) -> 88.74 | K58: — | L58: — | M58: =IFERROR((87*4.08)/4,0) -> 88.74 | N58: — | O58: — | P58: =IFERROR(SUM(D58:O58),0) -> 354.96
B59: SRU.UN | C59: FHSA | D59: =IFERROR((63*1.85)/12,0) -> 9.7125 | E59: =IFERROR((63*1.85)/12,0) -> 9.7125 | F59: =IFERROR((63*1.85)/12,0) -> 9.7125 | G59: =IFERROR((63*1.85)/12,0) -> 9.7125 | H59: =IFERROR((63*1.85)/12,0) -> 9.7125 | I59: =IFERROR((63*1.85)/12,0) -> 9.7125 | J59: =IFERROR((63*1.85)/12,0) -> 9.7125 | K59: =IFERROR((63*1.85)/12,0) -> 9.7125 | ... O59: =IFERROR((63*1.85)/12,0) -> 9.7125 | P59: =IFERROR(SUM(D59:O59),0) -> 116.55
B60: REI.UN | C60: FHSA | D60: =IFERROR((80*0.96)/12,0) -> 6.4 | E60: =IFERROR((80*0.96)/12,0) -> 6.4 | F60: =IFERROR((80*0.96)/12,0) -> 6.4 | G60: =IFERROR((80*0.96)/12,0) -> 6.4 | H60: =IFERROR((80*0.96)/12,0) -> 6.4 | I60: =IFERROR((80*0.96)/12,0) -> 6.4 | J60: =IFERROR((80*0.96)/12,0) -> 6.4 | K60: =IFERROR((80*0.96)/12,0) -> 6.4 | ... O60: =IFERROR((80*0.96)/12,0) -> 6.4 | P60: =IFERROR(SUM(D60:O60),0) -> 76.8
B61: MFC.TO | C61: TFSA | D61: — | E61: — | F61: =IFERROR((8*1.6)/4,0) -> 3.2 | G61: — | H61: — | I61: =IFERROR((8*1.6)/4,0) -> 3.2 | J61: — | K61: — | L61: =IFERROR((8*1.6)/4,0) -> 3.2 | M61: — | N61: — | O61: =IFERROR((8*1.6)/4,0) -> 3.2 | P61: =IFERROR(SUM(D61:O61),0) -> 12.8
B62: XEI.TO | C62: FHSA | D62: =IFERROR((26*1.2)/12,0) -> 2.6 | E62: =IFERROR((26*1.2)/12,0) -> 2.6 | F62: =IFERROR((26*1.2)/12,0) -> 2.6 | G62: =IFERROR((26*1.2)/12,0) -> 2.6 | H62: =IFERROR((26*1.2)/12,0) -> 2.6 | I62: =IFERROR((26*1.2)/12,0) -> 2.6 | J62: =IFERROR((26*1.2)/12,0) -> 2.6 | K62: =IFERROR((26*1.2)/12,0) -> 2.6 | ... O62: =IFERROR((26*1.2)/12,0) -> 2.6 | P62: =IFERROR(SUM(D62:O62),0) -> 31.2
B63: XEI.TO | C63: TFSA | D63: =IFERROR((51*1.2)/12,0) -> 5.1 | E63: =IFERROR((51*1.2)/12,0) -> 5.1 | F63: =IFERROR((51*1.2)/12,0) -> 5.1 | G63: =IFERROR((51*1.2)/12,0) -> 5.1 | H63: =IFERROR((51*1.2)/12,0) -> 5.1 | I63: =IFERROR((51*1.2)/12,0) -> 5.1 | J63: =IFERROR((51*1.2)/12,0) -> 5.1 | K63: =IFERROR((51*1.2)/12,0) -> 5.1 | ... O63: =IFERROR((51*1.2)/12,0) -> 5.1 | P63: =IFERROR(SUM(D63:O63),0) -> 61.2
B64: ▼ TOTAL /MOIS (CAD) | D64: =SUM(D54:D63) -> 201.81226 | E64: =SUM(E54:E63) -> 24.332262 | F64: =SUM(F54:F63) -> 100.65076 | G64: =SUM(G54:G63) -> 201.81226 | H64: =SUM(H54:H63) -> 24.332262 | I64: =SUM(I54:I63) -> 100.65076 | J64: =SUM(J54:J63) -> 201.81226 | K64: =SUM(K54:K63) -> 24.332262 | ... O64: =SUM(O54:O63) -> 100.65076 | P64: =SUM(D64:O64) -> 1307.1811
B66: 💡 Ces dividendes = argent réel qui rentre. SCHD REER + ENB TFSA + JEPI REER trimestriels/mensuels. Ajouter à CONFIG!B25 (HISA) si non réinvesti = tampon liquidité.

Sheet 🏠 MAISON 2030+
A1: 🏠 MAISON 2030+ · Plan d'achat complet · FHSA $40K + RAP REER $60K = $100K mise de fonds
A2: Mis à jour automatiquement via CONFIG · Cellules JAUNES = saisir à la main
A4: 📊 PROGRESSION — Où j'en suis aujourd'hui
B5: SOURCE | C5: VALEUR ACTUELLE | D5: OBJECTIF CAD | E5: MANQUANT | F5: PROGRESSION % | G5: STATUT | H5: RÔLE
B6: FHSA | C6: ='📈 PORTEFEUILLE'!L59 -> 14767.018 | E6: =CONFIG!B14 -> 40000 | F6: =E6-C6 -> 25232.982 | G6: =IFERROR(C6/E6,0) -> 0.36917545 | H6: =IF(C6/E6>=1,"✅ ATTEINT",IF(C6/E6>=0.8,"🟡 PRÈS","🔴 ACCÉLÉRER")) -> 🔴 ACCÉLÉRER
B7: REER (RAP) | C7: ='📈 PORTEFEUILLE'!L68 -> 2764.1683 | E7: =CONFIG!B15 -> 60000 | F7: =E7-C7 -> 57235.832 | G7: =IFERROR(C7/E7,0) -> 0.046069471 | H7: =IF(C7/E7>=1,"✅ ATTEINT",IF(C7/E7>=0.8,"🟡 PRÈS","🔴 ACCÉLÉRER")) -> 🔴 ACCÉLÉRER
B8: ▼ TOTAL MAISON | C8: =C6+C7 -> 17531.186 | E8: =CONFIG!B16 -> 100000 | F8: =E8-C8 -> 82468.814 | G8: =IFERROR(C8/E8,0) -> 0.17531186 | H8: =IF(C8/E8>=1,"✅ OBJECTIF ATTEINT!",IF(C8/E8>=0.8,"🟡 PRÈS DU BUT","🔴 EN COURS")) -> 🔴 EN COURS
A10: ⏳ COUNTDOWN — Temps restant
B11: Date cible achat maison | C11: 2030-06-01 | E11: Jours restants | F11: =IFERROR(DATEVALUE(C11)-TODAY(),0) -> 1539 | G11: =IF(C11="","",TEXT(DATEVALUE(C11)-TODAY(),"0")&" jours · "&TEXT((DATEVALUE(C11)-TODAY())/30.4,"0.0")&" mois") -> 1539 jours · 50.6 mois
B12: Manquant pour $100K (mise de fonds) | C12: =MAX(0,CONFIG!B16-C8) -> 82468.814
B13: À épargner par mois pour combler l'écart | C13: =IFERROR(MAX(0,CONFIG!B16-C8)/MAX(1,(DATEVALUE(C11)-TODAY())/30.4),0) -> 1629.0136
A15: 🏦 SIMULATION HYPOTHÈQUE — Ajuster les cellules JAUNES
B16: Prix de la maison ($CAD) | C16: 400000
B17: Mise de fonds ($CAD) | C17: 100000
B18: Taux hypothécaire (%) | C18: 0.045
B19: Amortissement (années) | C19: 25
B20: Fréquence paiement | C20: mensuel
B21: Montant emprunté | C21: =C16-C17 -> 300000
B22: Paiement mensuel estimé ($CAD) | C22: =IFERROR(C21*(C18/12)*(1+C18/12)^(C19*12)/((1+C18/12)^(C19*12)-1),0) -> 1667.4974
B23: Remboursement RAP annuel (15 ans) | C23: =IFERROR(CONFIG!B15/15,0) -> 4000
B24: Remboursement RAP mensuel | C24: =IFERROR(C23/12,0) -> 333.33333
B25: Coût mensuel total (hypothèque + RAP) | C25: =C22+C24 -> 2000.8308
A27: 📊 SCÉNARIOS TAUX — Impact sur paiement mensuel (maison $400K, mise $100K)
B28: TAUX | C28: PAIEMENT MENSUEL | D28: PAIEMENT ANNUEL | E28: TOTAL 25 ANS | F28: INTÉRÊTS PAYÉS
B29: 3.5% | C29: =IFERROR((C16-C17)*(0.035/12)*(1+0.035/12)^(C19*12)/((1+0.035/12)^(C19*12)-1),0) -> 1501.8707 | D29: =IFERROR((C16-C17)*(0.035/12)*(1+0.035/12)^(C19*12)/((1+0.035/12)^(C19*12)-1)*12,0) -> 18022.449 | E29: =IFERROR((C16-C17)*(0.035/12)*(1+0.035/12)^(C19*12)/((1+0.035/12)^(C19*12)-1)*12*C19,0) -> 450561.21 | F29: =IFERROR((C16-C17)*(0.035/12)*(1+0.035/12)^(C19*12)/((1+0.035/12)^(C19*12)-1)*12*C19-(C16-C17),0) -> 150561.21
B30: 4.0% | C30: =IFERROR((C16-C17)*(0.04/12)*(1+0.04/12)^(C19*12)/((1+0.04/12)^(C19*12)-1),0) -> 1583.5105 | D30: =IFERROR((C16-C17)*(0.04/12)*(1+0.04/12)^(C19*12)/((1+0.04/12)^(C19*12)-1)*12,0) -> 19002.126 | E30: =IFERROR((C16-C17)*(0.04/12)*(1+0.04/12)^(C19*12)/((1+0.04/12)^(C19*12)-1)*12*C19,0) -> 475053.16 | F30: =IFERROR((C16-C17)*(0.04/12)*(1+0.04/12)^(C19*12)/((1+0.04/12)^(C19*12)-1)*12*C19-(C16-C17),0) -> 175053.16
B31: 4.5% | C31: =IFERROR((C16-C17)*(0.045/12)*(1+0.045/12)^(C19*12)/((1+0.045/12)^(C19*12)-1),0) -> 1667.4974 | D31: =IFERROR((C16-C17)*(0.045/12)*(1+0.045/12)^(C19*12)/((1+0.045/12)^(C19*12)-1)*12,0) -> 20009.969 | E31: =IFERROR((C16-C17)*(0.045/12)*(1+0.045/12)^(C19*12)/((1+0.045/12)^(C19*12)-1)*12*C19,0) -> 500249.23 | F31: =IFERROR((C16-C17)*(0.045/12)*(1+0.045/12)^(C19*12)/((1+0.045/12)^(C19*12)-1)*12*C19-(C16-C17),0) -> 200249.23
B32: 5.0% | C32: =IFERROR((C16-C17)*(0.05/12)*(1+0.05/12)^(C19*12)/((1+0.05/12)^(C19*12)-1),0) -> 1753.7701 | D32: =IFERROR((C16-C17)*(0.05/12)*(1+0.05/12)^(C19*12)/((1+0.05/12)^(C19*12)-1)*12,0) -> 21045.241 | E32: =IFERROR((C16-C17)*(0.05/12)*(1+0.05/12)^(C19*12)/((1+0.05/12)^(C19*12)-1)*12*C19,0) -> 526131.04 | F32: =IFERROR((C16-C17)*(0.05/12)*(1+0.05/12)^(C19*12)/((1+0.05/12)^(C19*12)-1)*12*C19-(C16-C17),0) -> 226131.04
B33: 5.5% | C33: =IFERROR((C16-C17)*(0.055/12)*(1+0.055/12)^(C19*12)/((1+0.055/12)^(C19*12)-1),0) -> 1842.2625 | D33: =IFERROR((C16-C17)*(0.055/12)*(1+0.055/12)^(C19*12)/((1+0.055/12)^(C19*12)-1)*12,0) -> 22107.15 | E33: =IFERROR((C16-C17)*(0.055/12)*(1+0.055/12)^(C19*12)/((1+0.055/12)^(C19*12)-1)*12*C19,0) -> 552678.74 | F33: =IFERROR((C16-C17)*(0.055/12)*(1+0.055/12)^(C19*12)/((1+0.055/12)^(C19*12)-1)*12*C19-(C16-C17),0) -> 252678.74
B34: 6.0% | C34: =IFERROR((C16-C17)*(0.06/12)*(1+0.06/12)^(C19*12)/((1+0.06/12)^(C19*12)-1),0) -> 1932.9042 | D34: =IFERROR((C16-C17)*(0.06/12)*(1+0.06/12)^(C19*12)/((1+0.06/12)^(C19*12)-1)*12,0) -> 23194.85 | E34: =IFERROR((C16-C17)*(0.06/12)*(1+0.06/12)^(C19*12)/((1+0.06/12)^(C19*12)-1)*12*C19,0) -> 579871.26 | F34: =IFERROR((C16-C17)*(0.06/12)*(1+0.06/12)^(C19*12)/((1+0.06/12)^(C19*12)-1)*12*C19-(C16-C17),0) -> 279871.26
A36: 📊 VALIDATION FHSA → OBJECTIF $40K AVANT 2030
A37: FHSA actuel | C37: $14,932 CAD | F37: — | H37: —
A38: Cotisation mensuelle | C38: $1,000/mois = $12,000/an | F38: — | H38: —
A39: Room restant 2026 | C39: ~$4,000 (plafond $16K — déjà cotisé $12K) | F39: — | H39: —
A40: Projection 2030 (4 ans × $12K + $14,932) | C40: ~$62,932 CAD | F40: ✅ > $40K objectif | H40: Atteint avant 2029
A41: Conclusion | C41: $40K RAP FHSA atteint ~2028 au rythme actuel | F41: ✅ DANS LES DÉLAIS

Sheet 📈 PROJECTION FI
A1: 📈 PROJECTION INDÉPENDANCE FINANCIÈRE · Objectif: FI à 55 ans (2047) · v47-S18
A2: Cellules JAUNES = saisir · Noir = calculé · Vert = liens inter-onglets
A4: ⚙️ PARAMÈTRES FI
A5: PARAMÈTRE | B5: VALEUR (SAISIR) | C5: SOURCE AUTO | D5: UNITÉ
A6: Âge actuel | B6: 34 | C6: =CONFIG!B4 | D6: ans
A7: Portefeuille actuel | B7: 85681 | C7: Auto via CONFIG (saisir manuellement si besoin) | D7: CAD
A8: Contribution mensuelle actuelle | B8: =CONFIG!B10 -> 4000 | C8: ← Lié CONFIG!B10 = $5,000/mois · REER $2K + FHSA $1K + TFSA $500 + EQ $1,500 · Confirmé S16 | D8: CAD/mois
A9: Rendement annuel pessimiste | B9: 0.06 | D9: 6%/an
A10: Rendement annuel réaliste | B10: 0.08 | D10: 8%/an
A11: Rendement annuel optimiste | B11: 0.1 | D11: 10%/an
A12: Objectif FI (règle 4%) | B12: 2100000 | D12: $7K/mois × 12 × 25 = $2.1M · Plancher FI · Jamais un plafond
A13: Âge cible FI | B13: 55 | C13: 2047 | D13: 2047
A14: RRQ estimé (début 60 ans) | B14: 1200 | C14: =CONFIG!B25 -> 0 | D14: $CAD/mois
A16: 📊 PROJECTION ANNÉE PAR ANNÉE · 34 → 50 ans · 3 scénarios
A17: ANNÉE
A18: 2026 | B18: 34 | C18: =B7*(1+B9)+B8*12*(((1+B9)-1)/B9) -> 138821.86 | D18: =B7*(1+B10)+B8*12*(((1+B10)-1)/B10) -> 140535.48 | E18: =B7*(1+B11)+B8*12*(((1+B11)-1)/B11) -> 142249.1 | F18: =$B$12 -> 2100000
A19: 2027 | B19: 35 | C19: =C18*(1+$B$9)+$B$8*12*(((1+$B$9)-1)/$B$9) -> 195151.17 | D19: =D18*(1+$B$10)+$B$8*12*(((1+$B$10)-1)/$B$10) -> 199778.32 | E19: =E18*(1+$B$11)+$B$8*12*(((1+$B$11)-1)/$B$11) -> 204474.01 | F19: =$B$12 -> 2100000
A20: 2028 | B20: 36 | C20: =C19*(1+$B$9)+$B$8*12*(((1+$B$9)-1)/$B$9) -> 254860.24 | D20: =D19*(1+$B$10)+$B$8*12*(((1+$B$10)-1)/$B$10) -> 263760.58 | E20: =E19*(1+$B$11)+$B$8*12*(((1+$B$11)-1)/$B$11) -> 272921.41 | F20: =$B$12 -> 2100000
A21: 2029 | B21: 37 | C21: =C20*(1+$B$9)+$B$8*12*(((1+$B$9)-1)/$B$9) -> 318151.86 | D21: =D20*(1+$B$10)+$B$8*12*(((1+$B$10)-1)/$B$10) -> 332861.43 | E21: =E20*(1+$B$11)+$B$8*12*(((1+$B$11)-1)/$B$11) -> 348213.55 | F21: =$B$12 -> 2100000
A22: 2030 | B22: 38 | C22: =C21*(1+$B$9)+$B$8*12*(((1+$B$9)-1)/$B$9) -> 385240.97 | D22: =D21*(1+$B$10)+$B$8*12*(((1+$B$10)-1)/$B$10) -> 407490.34 | E22: =E21*(1+$B$11)+$B$8*12*(((1+$B$11)-1)/$B$11) -> 431034.91 | F22: =$B$12 -> 2100000
